Workbook

Sheet Cover
B9: American Aerospace Controls
B11: Adjusted EBITDA Analysis
B14: Date | C14: =TODAY() -> 45995
B17: Team Members:
B18: Jack McGoorty | C18: JMcGoorty@kreshmore.com
B20: Color Key
B21: Blue | C21: Indicates Inputs
B22: Green | C22: Indicates values referecing other sheets
B23: Black | C23: Indicates a calculation

Sheet EBITDA Analysis
B1: AAC Adjusted EBITDA Analysis
B2: EBITDA Analysis
B4: EBITDA Analysis | J4: EBITDA Analysis
B5: Per AAC | D5: 44561 | E5: =EOMONTH(D5,12) -> 44926 | F5: =EOMONTH(E5,12) -> 45291 | G5: =EOMONTH(F5,12) -> 45657 | H5: =EOMONTH(G5,9) -> 45930 | J5: Per Kreshmore | L5: 44561 | M5: =EOMONTH(L5,12) -> 44926 | N5: =EOMONTH(M5,12) -> 45291 | O5: =EOMONTH(N5,12) -> 45657 | P5: =EOMONTH(O5,9) -> 45930
B7: Net Income | D7: =EBITDA!D7 -> 119984 | E7: =EBITDA!E7 -> 1556136 | F7: =EBITDA!F7 -> 1000851 | G7: =EBITDA!G7 -> 220635 | H7: =EBITDA!H7 -> 121987 | J7: Net Income | L7: ='Income Statement'!D56 -> 46895.68 | M7: ='Income Statement'!E56 -> -918089.76 | N7: ='Income Statement'!F56 -> 329947.51 | O7: ='Income Statement'!G56 -> 735738.72 | P7: ='Income Statement'!H56 -> -82188.27
C9: Depreciation | D9: =EBITDA!D9 -> 69999 | E9: =EBITDA!E9 -> 78628 | F9: =EBITDA!F9 -> 168273 | G9: =EBITDA!G9 -> 134718 | H9: =EBITDA!H9 -> 17000 | K9: Depreciation | L9: ='Income Statement'!D39+'Income Statement'!D22 -> 5833.33 | M9: ='Income Statement'!E39+'Income Statement'!E22 -> 14461.69 | N9: ='Income Statement'!F39+'Income Statement'!F22 -> 43516.43 | O9: ='Income Statement'!G39+'Income Statement'!G22 -> 109436 | P9: ='Income Statement'!H39+'Income Statement'!H22 -> 375
C10: Interest Expense | D10: =EBITDA!D10 -> 0 | E10: =EBITDA!E10 -> 0 | F10: =EBITDA!F10 -> 13668 | G10: =EBITDA!G10 -> 5890 | H10: =EBITDA!H10 -> 9986 | K10: Interest Expense | L10: =-'Income Statement'!D46 -> 0 | M10: =-'Income Statement'!E46 -> 135.64 | N10: =-'Income Statement'!F46 -> 3878.91 | O10: =-'Income Statement'!G46 -> 240.56 | P10: =-'Income Statement'!H46 -> 724.46
C11: Taxes | D11: =EBITDA!D11 -> 25 | E11: =EBITDA!E11 -> 0 | F11: =EBITDA!F11 -> 30767 | G11: =EBITDA!G11 -> 80165 | H11: =EBITDA!H11 -> 0 | K11: Taxes | L11: ='Income Statement'!D54 -> 0 | M11: ='Income Statement'!E54 -> 166364.31 | N11: ='Income Statement'!F54 -> 26209.75 | O11: ='Income Statement'!G54 -> 6209.75 | P11: ='Income Statement'!H54 -> 0
C12: Fed Employee Tax Credits | D12: =EBITDA!D12 -> -4611 | E12: =EBITDA!E12 -> 0 | F12: =EBITDA!F12 -> 0 | G12: =EBITDA!G12 -> 0 | H12: =EBITDA!H12 -> 0 | K12: Gain/(Loss) on Disposal of Assets | L12: =-'Income Statement'!D48 -> 0 | M12: =-'Income Statement'!E48 -> 0 | N12: =-'Income Statement'!F48 -> 0 | O12: =-'Income Statement'!G48 -> 35311.14 | P12: =-'Income Statement'!H48 -> 0
C13: Investment (income) loss | D13: =EBITDA!D13 -> -23926 | E13: =EBITDA!E13 -> -111926 | F13: =EBITDA!F13 -> -14523 | G13: =EBITDA!G13 -> 17634 | H13: =EBITDA!H13 -> -130431 | K13: Investment (income) loss | L13: =-'Income Statement'!D47 -> -5872.84 | M13: =-'Income Statement'!E47 -> -3448.65 | N13: =-'Income Statement'!F47 -> -3801.01 | O13: =-'Income Statement'!G47 -> -4698.91 | P13: =-'Income Statement'!H47 -> -7147.64
B14: Total Add-Backs | D14: =SUM(D9:D13) -> 41487 | E14: =SUM(E9:E13) -> -33298 | F14: =SUM(F9:F13) -> 198185 | G14: =SUM(G9:G13) -> 238407 | H14: =SUM(H9:H13) -> -103445 | J14: Total Add-Backs | L14: =SUM(L9:L13) -> -39.51 | M14: =SUM(M9:M13) -> 177512.99 | N14: =SUM(N9:N13) -> 69804.08 | O14: =SUM(O9:O13) -> 146498.54 | P14: =SUM(P9:P13) -> -6048.18
B16: Book EBITDA | D16: =D7+D14 -> 161471 | E16: =E7+E14 -> 1522838 | F16: =F7+F14 -> 1199036 | G16: =G7+G14 -> 459042 | H16: =H7+H14 -> 18542 | J16: Book EBITDA | L16: =L7+L14 -> 46856.17 | M16: =M7+M14 -> -740576.77 | N16: =N7+N14 -> 399751.59 | O16: =O7+O14 -> 882237.26 | P16: =P7+P14 -> -88236.45
B18: Adjustments | J18: Adjustments*
C19: Officer's Salary | D19: =EBITDA!D18 -> 355769 | E19: =EBITDA!E18 -> 364361 | F19: =EBITDA!F18 -> 171000 | G19: =EBITDA!G18 -> 100000 | H19: =EBITDA!H18 -> 75000 | K19: Officer's Salary | L19: ='Detailed IS'!F104 -> 31846.15 | M19: ='Detailed IS'!G104 -> 31375.39 | N19: ='Detailed IS'!H104 -> 9615.4 | O19: ='Detailed IS'!I104 -> 8884.63 | P19: ='Detailed IS'!J104 -> 0
C20: Directors Fees | D20: =EBITDA!D19 -> 180693 | E20: =EBITDA!E19 -> 180000 | F20: =EBITDA!F19 -> 224000 | G20: =EBITDA!G19 -> 240000 | H20: =EBITDA!H19 -> 178846 | K20: Directors Fees | L20: ='Detailed IS'!F108 -> 15923.11 | M20: ='Detailed IS'!G108 -> 15230.8 | N20: ='Detailed IS'!H108 -> 19384.64 | O20: ='Detailed IS'!I108 -> 20307.71 | P20: ='Detailed IS'!J108 -> 20307.71
C21: Dennis PA | D21: =EBITDA!D20 -> 15000 | E21: =EBITDA!E20 -> 0 | F21: =EBITDA!F20 -> 0 | G21: =EBITDA!G20 -> 0 | H21: =EBITDA!H20 -> 0 | K21: Dennis PA | L21: =EBITDA!L20 -> 0 | M21: =EBITDA!M20 -> 0 | N21: =EBITDA!N20 -> 0 | O21: =EBITDA!O20 -> 0 | P21: =EBITDA!P20 -> 0
C22: Prof/Cons Fees | D22: =EBITDA!D21 -> 10580 | E22: =EBITDA!E21 -> 28054 | F22: =EBITDA!F21 -> 31288 | G22: =EBITDA!G21 -> 53880 | H22: =EBITDA!H21 -> 86402 | K22: Prof/Cons Fees | L22: ='Detailed IS'!F123+'Detailed IS'!F122 -> 9479.7 | M22: ='Detailed IS'!G123+'Detailed IS'!G122 -> 31472.39 | N22: ='Detailed IS'!H123+'Detailed IS'!H122 -> 17643.54 | O22: ='Detailed IS'!I123+'Detailed IS'!I122 -> 24331.22 | P22: ='Detailed IS'!J123+'Detailed IS'!J122 -> 10911.51
C23: Acctg Fees | D23: =EBITDA!D22 -> 0 | E23: =EBITDA!E22 -> 37000 | F23: =EBITDA!F22 -> 45000 | G23: =EBITDA!G22 -> 0 | H23: =EBITDA!H22 -> 0 | K23: Acctg Fees | L23: ='Detailed IS'!F121 -> 15150 | M23: ='Detailed IS'!G121 -> 4000 | N23: ='Detailed IS'!H121 -> 24935 | O23: ='Detailed IS'!I121 -> -13143 | P23: ='Detailed IS'!J121 -> 0
C24: MFG Variance | D24: =EBITDA!D23 -> 0 | E24: =EBITDA!E23 -> 0 | F24: =EBITDA!F23 -> 0 | G24: =EBITDA!G23 -> -265500 | H24: =EBITDA!H23 -> 265500 | K24: MFG Variance | L24: =EBITDA!L23 -> 0 | M24: =EBITDA!M23 -> 0 | N24: =EBITDA!N23 -> 0 | O24: =EBITDA!O23 -> 0 | P24: =EBITDA!P23 -> 0
C25: Staff Cash Bonuses | D25: =EBITDA!D24 -> 40000 | E25: =EBITDA!E24 -> 40000 | F25: =EBITDA!F24 -> 40000 | G25: =EBITDA!G24 -> 40000 | H25: =EBITDA!H24 -> 40000 | K25: Staff Cash Bonuses | L25: =EBITDA!L24 -> 0 | M25: =EBITDA!M24 -> 0 | N25: =EBITDA!N24 -> 0 | O25: =EBITDA!O24 -> 0 | P25: =EBITDA!P24 -> 0
B26: Total Adjustments | D26: =SUM(D19:D25) -> 602042 | E26: =SUM(E19:E25) -> 649415 | F26: =SUM(F19:F25) -> 511288 | G26: =SUM(G19:G25) -> 168380 | H26: =SUM(H19:H25) -> 645748 | J26: Total Adjustments | L26: =SUM(L19:L25) -> 72398.96 | M26: =SUM(M19:M25) -> 82078.58 | N26: =SUM(N19:N25) -> 71578.58 | O26: =SUM(O19:O25) -> 40380.56 | P26: =SUM(P19:P25) -> 31219.22
B28: Adjusted EBITDA | D28: =D16+D26 -> 763513 | E28: =E16+E26 -> 2172253 | F28: =F16+F26 -> 1710324 | G28: =G16+G26 -> 627422 | H28: =H16+H26 -> 664290 | J28: Adjusted EBITDA | L28: =L16+L26 -> 119255.13 | M28: =M16+M26 -> -658498.19 | N28: =N16+N26 -> 471330.17 | O28: =O16+O26 -> 922617.82 | P28: =P16+P26 -> -57017.23
J30: *Note: Kreshmore did not look for other add-back items

Sheet Financials >>

Sheet Income Statement
B1: AAC Adjusted EBITDA Analysis
B2: Income Statement
B4: American Aerospace Controls | J4: as a % of Revenue
B5: Income Statement | D5: Actual | E5: Actual | F5: Actual | G5: Actual | H5: Actual | J5: Actual | K5: Actual | L5: Actual | M5: Actual | N5: Actual
D6: 44561 | E6: =EOMONTH(D6,12) -> 44926 | F6: =EOMONTH(E6,12) -> 45291 | G6: =EOMONTH(F6,12) -> 45657 | H6: =EOMONTH(G6,9) -> 45930 | J6: 44561 | K6: =EOMONTH(J6,12) -> 44926 | L6: =EOMONTH(K6,12) -> 45291 | M6: =EOMONTH(L6,12) -> 45657 | N6: =EOMONTH(M6,9) -> 45930
B7: Revenue
C8: Product Sales | D8: =SUMIFS('Detailed IS'!F:F,'Detailed IS'!$D:$D,$C8) -> 1125166.1 | E8: =SUMIFS('Detailed IS'!G:G,'Detailed IS'!$D:$D,$C8) -> 515796.36 | F8: =SUMIFS('Detailed IS'!H:H,'Detailed IS'!$D:$D,$C8) -> 1245336.4 | G8: =SUMIFS('Detailed IS'!I:I,'Detailed IS'!$D:$D,$C8) -> 937459.54 | H8: =SUMIFS('Detailed IS'!J:J,'Detailed IS'!$D:$D,$C8) -> 392663.3 | J8: =D8/D$11 -> 0.99383911 | K8: =E8/E$11 -> 0.99901221 | L8: =F8/F$11 -> 0.99560351 | M8: =G8/G$11 -> 0.71897159 | N8: =H8/H$11 -> 0.99923657
C9: Other Income | D9: =SUMIFS('Detailed IS'!F:F,'Detailed IS'!$D:$D,$C9) -> 6975 | E9: =SUMIFS('Detailed IS'!G:G,'Detailed IS'!$D:$D,$C9) -> 510 | F9: =SUMIFS('Detailed IS'!H:H,'Detailed IS'!$D:$D,$C9) -> 5499.29 | G9: =SUMIFS('Detailed IS'!I:I,'Detailed IS'!$D:$D,$C9) -> 2198 | H9: =SUMIFS('Detailed IS'!J:J,'Detailed IS'!$D:$D,$C9) -> 300 | J9: =D9/D$11 -> 0.0061608926 | K9: =E9/E$11 -> 0.00098778562 | L9: =F9/F$11 -> 0.0043964927 | M9: =G9/G$11 -> 0.0016857256 | N9: =H9/H$11 -> 0.00076343007
C10: Engineering Services | D10: =SUMIFS('Detailed IS'!F:F,'Detailed IS'!$D:$D,$C10) -> 0 | E10: =SUMIFS('Detailed IS'!G:G,'Detailed IS'!$D:$D,$C10) -> 0 | F10: =SUMIFS('Detailed IS'!H:H,'Detailed IS'!$D:$D,$C10) -> 0 | G10: =SUMIFS('Detailed IS'!I:I,'Detailed IS'!$D:$D,$C10) -> 364232 | H10: =SUMIFS('Detailed IS'!J:J,'Detailed IS'!$D:$D,$C10) -> 0 | J10: =D10/D$11 -> 0 | K10: =E10/E$11 -> 0 | L10: =F10/F$11 -> 0 | M10: =G10/G$11 -> 0.27934268 | N10: =H10/H$11 -> 0
B11: Total Revenue | D11: =SUM(D8:D10) -> 1132141.1 | E11: =SUM(E8:E10) -> 516306.36 | F11: =SUM(F8:F10) -> 1250835.7 | G11: =SUM(G8:G10) -> 1303889.5 | H11: =SUM(H8:H10) -> 392963.3 | J11: =D11/D$11 -> 1 | K11: =E11/E$11 -> 1 | L11: =F11/F$11 -> 1 | M11: =G11/G$11 -> 1 | N11: =H11/H$11 -> 1
B13: Cost of Goods Sold
C14: Materials | D14: =SUMIFS('Detailed IS'!F:F,'Detailed IS'!$D:$D,$C14) -> 197111.02 | E14: =SUMIFS('Detailed IS'!G:G,'Detailed IS'!$D:$D,$C14) -> 440595.55 | F14: =SUMIFS('Detailed IS'!H:H,'Detailed IS'!$D:$D,$C14) -> 78394.86 | G14: =SUMIFS('Detailed IS'!I:I,'Detailed IS'!$D:$D,$C14) -> -205801.84 | H14: =SUMIFS('Detailed IS'!J:J,'Detailed IS'!$D:$D,$C14) -> 57992.53 | J14: =D14/D$11 -> 0.17410463 | K14: =E14/E$11 -> 0.85336069 | L14: =F14/F$11 -> 0.062673987 | M14: =G14/G$11 -> -0.15783687 | N14: =H14/H$11 -> 0.14757747
C15: Salaries and Wages - Direct | D15: =SUMIFS('Detailed IS'!F:F,'Detailed IS'!$D:$D,$C15) -> 271970.64 | E15: =SUMIFS('Detailed IS'!G:G,'Detailed IS'!$D:$D,$C15) -> 260468.73 | F15: =SUMIFS('Detailed IS'!H:H,'Detailed IS'!$D:$D,$C15) -> 272225.94 | G15: =SUMIFS('Detailed IS'!I:I,'Detailed IS'!$D:$D,$C15) -> 270315.94 | H15: =SUMIFS('Detailed IS'!J:J,'Detailed IS'!$D:$D,$C15) -> 238865.16 | J15: =D15/D$11 -> 0.2402268 | K15: =E15/E$11 -> 0.50448484 | L15: =F15/F$11 -> 0.21763525 | M15: =G15/G$11 -> 0.20731506 | N15: =H15/H$11 -> 0.60785615
C16: Overhead | D16: =SUMIFS('Detailed IS'!F:F,'Detailed IS'!$D:$D,$C16) -> -4331.7 | E16: =SUMIFS('Detailed IS'!G:G,'Detailed IS'!$D:$D,$C16) -> 21913.42 | F16: =SUMIFS('Detailed IS'!H:H,'Detailed IS'!$D:$D,$C16) -> 50427.7 | G16: =SUMIFS('Detailed IS'!I:I,'Detailed IS'!$D:$D,$C16) -> -30164 | H16: =SUMIFS('Detailed IS'!J:J,'Detailed IS'!$D:$D,$C16) -> -70770.26 | J16: =D16/D$11 -> -0.003826113 | K16: =E16/E$11 -> 0.042442669 | L16: =F16/F$11 -> 0.040315207 | M16: =G16/G$11 -> -0.023133861 | N16: =H16/H$11 -> -0.18009382
C17: Outside Services | D17: =SUMIFS('Detailed IS'!F:F,'Detailed IS'!$D:$D,$C17) -> 13578.35 | E17: =SUMIFS('Detailed IS'!G:G,'Detailed IS'!$D:$D,$C17) -> 6833.06 | F17: =SUMIFS('Detailed IS'!H:H,'Detailed IS'!$D:$D,$C17) -> 22493.41 | G17: =SUMIFS('Detailed IS'!I:I,'Detailed IS'!$D:$D,$C17) -> 9512.15 | H17: =SUMIFS('Detailed IS'!J:J,'Detailed IS'!$D:$D,$C17) -> 16237.04 | J17: =D17/D$11 -> 0.011993513 | K17: =E17/E$11 -> 0.013234507 | L17: =F17/F$11 -> 0.017982706 | M17: =G17/G$11 -> 0.0072952115 | N17: =H17/H$11 -> 0.041319482
C18: Other COGs | D18: =SUMIFS('Detailed IS'!F:F,'Detailed IS'!$D:$D,$C18) -> 29942.33 | E18: =SUMIFS('Detailed IS'!G:G,'Detailed IS'!$D:$D,$C18) -> 15588.64 | F18: =SUMIFS('Detailed IS'!H:H,'Detailed IS'!$D:$D,$C18) -> -11281.36 | G18: =SUMIFS('Detailed IS'!I:I,'Detailed IS'!$D:$D,$C18) -> 59598.5 | H18: =SUMIFS('Detailed IS'!J:J,'Detailed IS'!$D:$D,$C18) -> 24568.06 | J18: =D18/D$11 -> 0.026447524 | K18: =E18/E$11 -> 0.030192617 | L18: =F18/F$11 -> -0.0090190583 | M18: =G18/G$11 -> 0.045708243 | N18: =H18/H$11 -> 0.062519986
C19: MFG Variance | D19: =SUMIFS('Detailed IS'!F:F,'Detailed IS'!$D:$D,$C19) -> 42577.59 | E19: =SUMIFS('Detailed IS'!G:G,'Detailed IS'!$D:$D,$C19) -> -232.1 | F19: =SUMIFS('Detailed IS'!H:H,'Detailed IS'!$D:$D,$C19) -> 1416.88 | G19: =SUMIFS('Detailed IS'!I:I,'Detailed IS'!$D:$D,$C19) -> 670.34 | H19: =SUMIFS('Detailed IS'!J:J,'Detailed IS'!$D:$D,$C19) -> 22291.02 | J19: =D19/D$11 -> 0.037608023 | K19: =E19/E$11 -> -0.0004495393 | L19: =F19/F$11 -> 0.0011327467 | M19: =G19/G$11 -> 0.00051410797 | N19: =H19/H$11 -> 0.05672545
C20: Freight | D20: =SUMIFS('Detailed IS'!F:F,'Detailed IS'!$D:$D,$C20) -> 6917.18 | E20: =SUMIFS('Detailed IS'!G:G,'Detailed IS'!$D:$D,$C20) -> 3219.95 | F20: =SUMIFS('Detailed IS'!H:H,'Detailed IS'!$D:$D,$C20) -> 2284.07 | G20: =SUMIFS('Detailed IS'!I:I,'Detailed IS'!$D:$D,$C20) -> 4374.26 | H20: =SUMIFS('Detailed IS'!J:J,'Detailed IS'!$D:$D,$C20) -> 6552.37 | J20: =D20/D$11 -> 0.0061098212 | K20: =E20/E$11 -> 0.0062365104 | L20: =F20/F$11 -> 0.0018260352 | M20: =G20/G$11 -> 0.003354778 | N20: =H20/H$11 -> 0.016674254
C21: Building Expenses - Direct | D21: =SUMIFS('Detailed IS'!F:F,'Detailed IS'!$D:$D,$C21) -> 25208.55 | E21: =SUMIFS('Detailed IS'!G:G,'Detailed IS'!$D:$D,$C21) -> 14822.71 | F21: =SUMIFS('Detailed IS'!H:H,'Detailed IS'!$D:$D,$C21) -> 16294.2 | G21: =SUMIFS('Detailed IS'!I:I,'Detailed IS'!$D:$D,$C21) -> 17015.01 | H21: =SUMIFS('Detailed IS'!J:J,'Detailed IS'!$D:$D,$C21) -> 18536.48 | J21: =D21/D$11 -> 0.022266261 | K21: =E21/E$11 -> 0.028709137 | L21: =F21/F$11 -> 0.013026651 | M21: =G21/G$11 -> 0.013049426 | N21: =H21/H$11 -> 0.047171021
C22: Depreciation & Amortization - Direct | D22: =SUMIFS('Detailed IS'!F:F,'Detailed IS'!$D:$D,$C22) -> 4958.33 | E22: =SUMIFS('Detailed IS'!G:G,'Detailed IS'!$D:$D,$C22) -> 12292.44 | F22: =SUMIFS('Detailed IS'!H:H,'Detailed IS'!$D:$D,$C22) -> 42385.13 | G22: =SUMIFS('Detailed IS'!I:I,'Detailed IS'!$D:$D,$C22) -> 93020.6 | H22: =SUMIFS('Detailed IS'!J:J,'Detailed IS'!$D:$D,$C22) -> 375 | J22: =D22/D$11 -> 0.0043796041 | K22: =E22/E$11 -> 0.023808423 | L22: =F22/F$11 -> 0.03388545 | M22: =G22/G$11 -> 0.071340859 | N22: =H22/H$11 -> 0.00095428759
B23: Total Cost of Goods Sold | D23: =SUM(D14:D22) -> 587932.29 | E23: =SUM(E14:E22) -> 775502.4 | F23: =SUM(F14:F22) -> 474640.83 | G23: =SUM(G14:G22) -> 218540.96 | H23: =SUM(H14:H22) -> 314647.4 | J23: =D23/D$11 -> 0.51931006 | K23: =E23/E$11 -> 1.5020198 | L23: =F23/F$11 -> 0.37945898 | M23: =G23/G$11 -> 0.16760696 | N23: =H23/H$11 -> 0.80070429
B25: Gross Profit | D25: =D11-D23 -> 544208.86 | E25: =E11-E23 -> -259196.04 | F25: =F11-F23 -> 776194.86 | G25: =G11-G23 -> 1085348.6 | H25: =H11-H23 -> 78315.9 | J25: =D25/D$11 -> 0.48068994 | K25: =E25/E$11 -> -0.50201985 | L25: =F25/F$11 -> 0.62054102 | M25: =G25/G$11 -> 0.83239304 | N25: =H25/H$11 -> 0.19929571
B27: SG&A Expenses
C28: Salaries & Wages | D28: =SUMIFS('Detailed IS'!F:F,'Detailed IS'!$D:$D,$C28) -> 114955.85 | E28: =SUMIFS('Detailed IS'!G:G,'Detailed IS'!$D:$D,$C28) -> 166624.8 | F28: =SUMIFS('Detailed IS'!H:H,'Detailed IS'!$D:$D,$C28) -> 93718.26 | G28: =SUMIFS('Detailed IS'!I:I,'Detailed IS'!$D:$D,$C28) -> 105528.13 | H28: =SUMIFS('Detailed IS'!J:J,'Detailed IS'!$D:$D,$C28) -> 101135.73 | J28: =D28/D$11 -> 0.10153844 | K28: =E28/E$11 -> 0.32272467 | L28: =F28/F$11 -> 0.074924517 | M28: =G28/G$11 -> 0.080933336 | N28: =H28/H$11 -> 0.25736686
C29: Sales & Marketing | D29: =SUMIFS('Detailed IS'!F:F,'Detailed IS'!$D:$D,$C29) -> 24421.28 | E29: =SUMIFS('Detailed IS'!G:G,'Detailed IS'!$D:$D,$C29) -> 37034.35 | F29: =SUMIFS('Detailed IS'!H:H,'Detailed IS'!$D:$D,$C29) -> 7442.57 | G29: =SUMIFS('Detailed IS'!I:I,'Detailed IS'!$D:$D,$C29) -> 28874.28 | H29: =SUMIFS('Detailed IS'!J:J,'Detailed IS'!$D:$D,$C29) -> 29451.06 | J29: =D29/D$11 -> 0.021570879 | K29: =E29/E$11 -> 0.071729409 | L29: =F29/F$11 -> 0.0059500781 | M29: =G29/G$11 -> 0.022144729 | N29: =H29/H$11 -> 0.074946083
C30: Directors Fees | D30: =SUMIFS('Detailed IS'!F:F,'Detailed IS'!$D:$D,$C30) -> 15923.11 | E30: =SUMIFS('Detailed IS'!G:G,'Detailed IS'!$D:$D,$C30) -> 15230.8 | F30: =SUMIFS('Detailed IS'!H:H,'Detailed IS'!$D:$D,$C30) -> 19384.64 | G30: =SUMIFS('Detailed IS'!I:I,'Detailed IS'!$D:$D,$C30) -> 20307.71 | H30: =SUMIFS('Detailed IS'!J:J,'Detailed IS'!$D:$D,$C30) -> 20307.71 | J30: =D30/D$11 -> 0.014064598 | K30: =E30/E$11 -> 0.02949954 | L30: =F30/F$11 -> 0.015497351 | M30: =G30/G$11 -> 0.015574717 | N30: =H30/H$11 -> 0.051678388
C31: Other Expenses | D31: =SUMIFS('Detailed IS'!F:F,'Detailed IS'!$D:$D,$C31) -> 12242.28 | E31: =SUMIFS('Detailed IS'!G:G,'Detailed IS'!$D:$D,$C31) -> 38020.75 | F31: =SUMIFS('Detailed IS'!H:H,'Detailed IS'!$D:$D,$C31) -> 13384.12 | G31: =SUMIFS('Detailed IS'!I:I,'Detailed IS'!$D:$D,$C31) -> 3535.94 | H31: =SUMIFS('Detailed IS'!J:J,'Detailed IS'!$D:$D,$C31) -> 597.67 | J31: =D31/D$11 -> 0.010813387 | K31: =E31/E$11 -> 0.073639902 | L31: =F31/F$11 -> 0.010700142 | M31: =G31/G$11 -> 0.0027118401 | N31: =H31/H$11 -> 0.0015209308
C32: Professional Fees | D32: =SUMIFS('Detailed IS'!F:F,'Detailed IS'!$D:$D,$C32) -> 24629.7 | E32: =SUMIFS('Detailed IS'!G:G,'Detailed IS'!$D:$D,$C32) -> 35472.39 | F32: =SUMIFS('Detailed IS'!H:H,'Detailed IS'!$D:$D,$C32) -> 42578.54 | G32: =SUMIFS('Detailed IS'!I:I,'Detailed IS'!$D:$D,$C32) -> 11188.22 | H32: =SUMIFS('Detailed IS'!J:J,'Detailed IS'!$D:$D,$C32) -> 10911.51 | J32: =D32/D$11 -> 0.021754973 | K32: =E32/E$11 -> 0.068704151 | L32: =F32/F$11 -> 0.034040074 | M32: =G32/G$11 -> 0.0085806502 | N32: =H32/H$11 -> 0.02776725
C33: Human Resources & Trianing Expenses | D33: =SUMIFS('Detailed IS'!F:F,'Detailed IS'!$D:$D,$C33) -> 40323 | E33: =SUMIFS('Detailed IS'!G:G,'Detailed IS'!$D:$D,$C33) -> 45000 | F33: =SUMIFS('Detailed IS'!H:H,'Detailed IS'!$D:$D,$C33) -> 40000 | G33: =SUMIFS('Detailed IS'!I:I,'Detailed IS'!$D:$D,$C33) -> 40708.77 | H33: =SUMIFS('Detailed IS'!J:J,'Detailed IS'!$D:$D,$C33) -> 1192.02 | J33: =D33/D$11 -> 0.035616584 | K33: =E33/E$11 -> 0.087157555 | L33: =F33/F$11 -> 0.031978621 | M33: =G33/G$11 -> 0.031221027 | N33: =H33/H$11 -> 0.003033413
C34: Office Expense | D34: =SUMIFS('Detailed IS'!F:F,'Detailed IS'!$D:$D,$C34) -> 7710.08 | E34: =SUMIFS('Detailed IS'!G:G,'Detailed IS'!$D:$D,$C34) -> 9456.74 | F34: =SUMIFS('Detailed IS'!H:H,'Detailed IS'!$D:$D,$C34) -> 18443.85 | G34: =SUMIFS('Detailed IS'!I:I,'Detailed IS'!$D:$D,$C34) -> 34152.84 | H34: =SUMIFS('Detailed IS'!J:J,'Detailed IS'!$D:$D,$C34) -> 2366.91 | J34: =D34/D$11 -> 0.0068101756 | K34: =E34/E$11 -> 0.018316141 | L34: =F34/F$11 -> 0.014745222 | M34: =G34/G$11 -> 0.026193047 | N34: =H34/H$11 -> 0.0060232342
C35: Charity | D35: =SUMIFS('Detailed IS'!F:F,'Detailed IS'!$D:$D,$C35) -> 3025 | E35: =SUMIFS('Detailed IS'!G:G,'Detailed IS'!$D:$D,$C35) -> 300 | F35: =SUMIFS('Detailed IS'!H:H,'Detailed IS'!$D:$D,$C35) -> 1625 | G35: =SUMIFS('Detailed IS'!I:I,'Detailed IS'!$D:$D,$C35) -> 1675 | H35: =SUMIFS('Detailed IS'!J:J,'Detailed IS'!$D:$D,$C35) -> 300 | J35: =D35/D$11 -> 0.0026719283 | K35: =E35/E$11 -> 0.00058105037 | L35: =F35/F$11 -> 0.0012991315 | M35: =G35/G$11 -> 0.001284618 | N35: =H35/H$11 -> 0.00076343007
C36: Bank Charges | D36: =SUMIFS('Detailed IS'!F:F,'Detailed IS'!$D:$D,$C36) -> 1610.05 | E36: =SUMIFS('Detailed IS'!G:G,'Detailed IS'!$D:$D,$C36) -> 534.41 | F36: =SUMIFS('Detailed IS'!H:H,'Detailed IS'!$D:$D,$C36) -> 2384.29 | G36: =SUMIFS('Detailed IS'!I:I,'Detailed IS'!$D:$D,$C36) -> 2117.34 | H36: =SUMIFS('Detailed IS'!J:J,'Detailed IS'!$D:$D,$C36) -> 1501.51 | J36: =D36/D$11 -> 0.0014221283 | K36: =E36/E$11 -> 0.0010350638 | L36: =F36/F$11 -> 0.0019061576 | M36: =G36/G$11 -> 0.0016238645 | N36: =H36/H$11 -> 0.003820993
C37: Building Expenses | D37: =SUMIFS('Detailed IS'!F:F,'Detailed IS'!$D:$D,$C37) -> 8051.32 | E37: =SUMIFS('Detailed IS'!G:G,'Detailed IS'!$D:$D,$C37) -> 5129.33 | F37: =SUMIFS('Detailed IS'!H:H,'Detailed IS'!$D:$D,$C37) -> 5276.24 | G37: =SUMIFS('Detailed IS'!I:I,'Detailed IS'!$D:$D,$C37) -> -960.21 | H37: =SUMIFS('Detailed IS'!J:J,'Detailed IS'!$D:$D,$C37) -> 0 | J37: =D37/D$11 -> 0.0071115867 | K37: =E37/E$11 -> 0.0099346636 | L37: =F37/F$11 -> 0.0042181719 | M37: =G37/G$11 -> -0.00073641974 | N37: =H37/H$11 -> 0
C38: Profit Sharing | D38: =SUMIFS('Detailed IS'!F:F,'Detailed IS'!$D:$D,$C38) -> 250000 | E38: =SUMIFS('Detailed IS'!G:G,'Detailed IS'!$D:$D,$C38) -> 150000 | F38: =SUMIFS('Detailed IS'!H:H,'Detailed IS'!$D:$D,$C38) -> 175000 | G38: =SUMIFS('Detailed IS'!I:I,'Detailed IS'!$D:$D,$C38) -> 50000 | H38: =SUMIFS('Detailed IS'!J:J,'Detailed IS'!$D:$D,$C38) -> 0 | J38: =D38/D$11 -> 0.22082052 | K38: =E38/E$11 -> 0.29052518 | L38: =F38/F$11 -> 0.13990647 | M38: =G38/G$11 -> 0.038346807 | N38: =H38/H$11 -> 0
C39: Depreciation & Amortization | D39: =SUMIFS('Detailed IS'!F:F,'Detailed IS'!$D:$D,$C39) -> 875 | E39: =SUMIFS('Detailed IS'!G:G,'Detailed IS'!$D:$D,$C39) -> 2169.25 | F39: =SUMIFS('Detailed IS'!H:H,'Detailed IS'!$D:$D,$C39) -> 1131.3 | G39: =SUMIFS('Detailed IS'!I:I,'Detailed IS'!$D:$D,$C39) -> 16415.4 | H39: =SUMIFS('Detailed IS'!J:J,'Detailed IS'!$D:$D,$C39) -> 0 | J39: =D39/D$11 -> 0.00077287183 | K39: =E39/E$11 -> 0.0042014784 | L39: =F39/F$11 -> 0.00090443534 | M39: =G39/G$11 -> 0.012589563 | N39: =H39/H$11 -> 0
B40: Total SG&A Expenses | D40: =SUM(D28:D39) -> 503766.67 | E40: =SUM(E28:E39) -> 504972.82 | F40: =SUM(F28:F39) -> 420368.81 | G40: =SUM(G28:G39) -> 313543.42 | H40: =SUM(H28:H39) -> 167764.12 | J40: =D40/D$11 -> 0.44496808 | K40: =E40/E$11 -> 0.97804881 | L40: =F40/F$11 -> 0.33607037 | M40: =G40/G$11 -> 0.24046778 | N40: =H40/H$11 -> 0.42692058
B42: Net Operating Income | D42: =D25-D40 -> 40442.19 | E42: =E25-E40 -> -764168.86 | F42: =F25-F40 -> 355826.05 | G42: =G25-G40 -> 771805.16 | H42: =H25-H40 -> -89448.22 | J42: =D42/D$11 -> 0.035721862 | K42: =E42/E$11 -> -1.4800687 | L42: =F42/F$11 -> 0.28447066 | M42: =G42/G$11 -> 0.59192526 | N42: =H42/H$11 -> -0.22762487
J43: =D43/D$11 -> 0 | K43: =E43/E$11 -> 0 | L43: =F43/F$11 -> 0 | M43: =G43/G$11 -> 0 | N43: =H43/H$11 -> 0
B44: Other Income (Expenses) | J44: =D44/D$11 -> 0 | K44: =E44/E$11 -> 0 | L44: =F44/F$11 -> 0 | M44: =G44/G$11 -> 0 | N44: =H44/H$11 -> 0
C45: Interest Income | D45: =SUMIFS('Detailed IS'!F:F,'Detailed IS'!$D:$D,$C45) -> 0.96 | E45: =SUMIFS('Detailed IS'!G:G,'Detailed IS'!$D:$D,$C45) -> 0 | F45: =SUMIFS('Detailed IS'!H:H,'Detailed IS'!$D:$D,$C45) -> 0 | G45: =SUMIFS('Detailed IS'!I:I,'Detailed IS'!$D:$D,$C45) -> 0.72 | H45: =SUMIFS('Detailed IS'!J:J,'Detailed IS'!$D:$D,$C45) -> 0.02 | J45: =D45/D$11 -> 8.4795081e-07 | K45: =E45/E$11 -> 0 | L45: =F45/F$11 -> 0 | M45: =G45/G$11 -> 5.5219401e-07 | N45: =H45/H$11 -> 5.0895338e-08
C46: Interest Expense | D46: =SUMIFS('Detailed IS'!F:F,'Detailed IS'!$D:$D,$C46) -> 0 | E46: =SUMIFS('Detailed IS'!G:G,'Detailed IS'!$D:$D,$C46) -> -135.64 | F46: =SUMIFS('Detailed IS'!H:H,'Detailed IS'!$D:$D,$C46) -> -3878.91 | G46: =SUMIFS('Detailed IS'!I:I,'Detailed IS'!$D:$D,$C46) -> -240.56 | H46: =SUMIFS('Detailed IS'!J:J,'Detailed IS'!$D:$D,$C46) -> -724.46 | J46: =D46/D$11 -> 0 | K46: =E46/E$11 -> -0.00026271224 | L46: =F46/F$11 -> -0.0031010548 | M46: =G46/G$11 -> -0.00018449416 | N46: =H46/H$11 -> -0.0018435818
C47: Investment Income | D47: =SUMIFS('Detailed IS'!F:F,'Detailed IS'!$D:$D,$C47) -> 5872.84 | E47: =SUMIFS('Detailed IS'!G:G,'Detailed IS'!$D:$D,$C47) -> 3448.65 | F47: =SUMIFS('Detailed IS'!H:H,'Detailed IS'!$D:$D,$C47) -> 3801.01 | G47: =SUMIFS('Detailed IS'!I:I,'Detailed IS'!$D:$D,$C47) -> 4698.91 | H47: =SUMIFS('Detailed IS'!J:J,'Detailed IS'!$D:$D,$C47) -> 7147.64 | J47: =D47/D$11 -> 0.0051873744 | K47: =E47/E$11 -> 0.0066794645 | L47: =F47/F$11 -> 0.0030387764 | M47: =G47/G$11 -> 0.0036037639 | N47: =H47/H$11 -> 0.018189078
C48: Gain (Loss) on disposal of assets | D48: =SUMIFS('Detailed IS'!F:F,'Detailed IS'!$D:$D,$C48) -> 0 | E48: =SUMIFS('Detailed IS'!G:G,'Detailed IS'!$D:$D,$C48) -> 0 | F48: =SUMIFS('Detailed IS'!H:H,'Detailed IS'!$D:$D,$C48) -> 0 | G48: =SUMIFS('Detailed IS'!I:I,'Detailed IS'!$D:$D,$C48) -> -35311.14 | H48: =SUMIFS('Detailed IS'!J:J,'Detailed IS'!$D:$D,$C48) -> 0 | J48: =D48/D$11 -> 0 | K48: =E48/E$11 -> 0 | L48: =F48/F$11 -> 0 | M48: =G48/G$11 -> -0.027081389 | N48: =H48/H$11 -> 0
C49: Other Income and Expense | D49: =SUMIFS('Detailed IS'!F:F,'Detailed IS'!$D:$D,$C49) -> 579.69 | E49: =SUMIFS('Detailed IS'!G:G,'Detailed IS'!$D:$D,$C49) -> 9130.4 | F49: =SUMIFS('Detailed IS'!H:H,'Detailed IS'!$D:$D,$C49) -> 409.11 | G49: =SUMIFS('Detailed IS'!I:I,'Detailed IS'!$D:$D,$C49) -> 995.38 | H49: =SUMIFS('Detailed IS'!J:J,'Detailed IS'!$D:$D,$C49) -> 836.75 | J49: =D49/D$11 -> 0.00051202979 | K49: =E49/E$11 -> 0.017684074 | L49: =F49/F$11 -> 0.00032706934 | M49: =G49/G$11 -> 0.00076339289 | N49: =H49/H$11 -> 0.0021293337
B50: Total Other Income (Expenses) | D50: =SUM(D45:D49) -> 6453.49 | E50: =SUM(E45:E49) -> 12443.41 | F50: =SUM(F45:F49) -> 331.21 | G50: =SUM(G45:G49) -> -29856.69 | H50: =SUM(H45:H49) -> 7259.95 | J50: =D50/D$11 -> 0.0057002521 | K50: =E50/E$11 -> 0.024100826 | L50: =F50/F$11 -> 0.00026479097 | M50: =G50/G$11 -> -0.022898174 | N50: =H50/H$11 -> 0.01847488
B52: EBT | D52: =D42+D50 -> 46895.68 | E52: =E42+E50 -> -751725.45 | F52: =F42+F50 -> 356157.26 | G52: =G42+G50 -> 741948.47 | H52: =H42+H50 -> -82188.27 | J52: =D52/D$11 -> 0.041422114 | K52: =E52/E$11 -> -1.4559678 | L52: =F52/F$11 -> 0.28473545 | M52: =G52/G$11 -> 0.56902709 | N52: =H52/H$11 -> -0.20914999
C54: Corporate Taxes | D54: =SUMIFS('Detailed IS'!F:F,'Detailed IS'!$D:$D,$C54) -> 0 | E54: =SUMIFS('Detailed IS'!G:G,'Detailed IS'!$D:$D,$C54) -> 166364.31 | F54: =SUMIFS('Detailed IS'!H:H,'Detailed IS'!$D:$D,$C54) -> 26209.75 | G54: =SUMIFS('Detailed IS'!I:I,'Detailed IS'!$D:$D,$C54) -> 6209.75 | H54: =SUMIFS('Detailed IS'!J:J,'Detailed IS'!$D:$D,$C54) -> 0 | J54: =D54/D$11 -> 0 | K54: =E54/E$11 -> 0.32222014 | L54: =F54/F$11 -> 0.020953791 | M54: =G54/G$11 -> 0.0047624816 | N54: =H54/H$11 -> 0
B56: Net Income | D56: =D52-D54 -> 46895.68 | E56: =E52-E54 -> -918089.76 | F56: =F52-F54 -> 329947.51 | G56: =G52-G54 -> 735738.72 | H56: =H52-H54 -> -82188.27 | J56: =D56/D$11 -> 0.041422114 | K56: =E56/E$11 -> -1.778188 | L56: =F56/F$11 -> 0.26378166 | M56: =G56/G$11 -> 0.56426461 | N56: =H56/H$11 -> -0.20914999

Sheet Balance Sheet
B1: AAC Adjusted EBITDA Analysis
B2: Balance Sheet
B4: American Aerospace Controls
B5: Balance Sheet | D5: Actual | E5: Actual | F5: Actual | G5: Actual | H5: Actual
B6: As of | D6: 44561 | E6: =EOMONTH(D6,12) -> 44926 | F6: =EOMONTH(E6,12) -> 45291 | G6: =EOMONTH(F6,12) -> 45657 | H6: =EOMONTH(G6,9) -> 45930
B7: Assets
B8: Current Assets
C9: Cash | D9: =SUMIFS('Detailed BS'!F:F,'Detailed BS'!$D:$D,$C9) -> 1199208 | E9: =SUMIFS('Detailed BS'!G:G,'Detailed BS'!$D:$D,$C9) -> 2398756.5 | F9: =SUMIFS('Detailed BS'!H:H,'Detailed BS'!$D:$D,$C9) -> 1615267.5 | G9: =SUMIFS('Detailed BS'!I:I,'Detailed BS'!$D:$D,$C9) -> 1026698.9 | H9: =SUMIFS('Detailed BS'!J:J,'Detailed BS'!$D:$D,$C9) -> 580318.35
C10: Accounts Receivable | D10: =SUMIFS('Detailed BS'!F:F,'Detailed BS'!$D:$D,$C10) -> 1105726.3 | E10: =SUMIFS('Detailed BS'!G:G,'Detailed BS'!$D:$D,$C10) -> 525775.94 | F10: =SUMIFS('Detailed BS'!H:H,'Detailed BS'!$D:$D,$C10) -> 1262808.8 | G10: =SUMIFS('Detailed BS'!I:I,'Detailed BS'!$D:$D,$C10) -> 1147802.6 | H10: =SUMIFS('Detailed BS'!J:J,'Detailed BS'!$D:$D,$C10) -> 437988.79
C11: Allowance for Doubtful Accounts | D11: =SUMIFS('Detailed BS'!F:F,'Detailed BS'!$D:$D,$C11) -> -15130.57 | E11: =SUMIFS('Detailed BS'!G:G,'Detailed BS'!$D:$D,$C11) -> -15130.57 | F11: =SUMIFS('Detailed BS'!H:H,'Detailed BS'!$D:$D,$C11) -> -15130.57 | G11: =SUMIFS('Detailed BS'!I:I,'Detailed BS'!$D:$D,$C11) -> -15130.57 | H11: =SUMIFS('Detailed BS'!J:J,'Detailed BS'!$D:$D,$C11) -> -15130.57
C12: Customer Depsits | D12: =SUMIFS('Detailed BS'!F:F,'Detailed BS'!$D:$D,$C12) -> -24542.41 | E12: =SUMIFS('Detailed BS'!G:G,'Detailed BS'!$D:$D,$C12) -> -18599.3 | F12: =SUMIFS('Detailed BS'!H:H,'Detailed BS'!$D:$D,$C12) -> -28159.91 | G12: =SUMIFS('Detailed BS'!I:I,'Detailed BS'!$D:$D,$C12) -> -31574.74 | H12: =SUMIFS('Detailed BS'!J:J,'Detailed BS'!$D:$D,$C12) -> -19542.76
C13: Investments | D13: =SUMIFS('Detailed BS'!F:F,'Detailed BS'!$D:$D,$C13) -> 585157.33 | E13: =SUMIFS('Detailed BS'!G:G,'Detailed BS'!$D:$D,$C13) -> 405784.26 | F13: =SUMIFS('Detailed BS'!H:H,'Detailed BS'!$D:$D,$C13) -> 420307.73 | G13: =SUMIFS('Detailed BS'!I:I,'Detailed BS'!$D:$D,$C13) -> 815111.44 | H13: =SUMIFS('Detailed BS'!J:J,'Detailed BS'!$D:$D,$C13) -> 1723864.4
C14: Inventory | D14: =SUMIFS('Detailed BS'!F:F,'Detailed BS'!$D:$D,$C14) -> 2081585 | E14: =SUMIFS('Detailed BS'!G:G,'Detailed BS'!$D:$D,$C14) -> 1935775.6 | F14: =SUMIFS('Detailed BS'!H:H,'Detailed BS'!$D:$D,$C14) -> 2102234.8 | G14: =SUMIFS('Detailed BS'!I:I,'Detailed BS'!$D:$D,$C14) -> 2655768 | H14: =SUMIFS('Detailed BS'!J:J,'Detailed BS'!$D:$D,$C14) -> 2922283.8
C15: Prepaid Expenses | D15: =SUMIFS('Detailed BS'!F:F,'Detailed BS'!$D:$D,$C15) -> 83628.36 | E15: =SUMIFS('Detailed BS'!G:G,'Detailed BS'!$D:$D,$C15) -> 51113.57 | F15: =SUMIFS('Detailed BS'!H:H,'Detailed BS'!$D:$D,$C15) -> 94379.15 | G15: =SUMIFS('Detailed BS'!I:I,'Detailed BS'!$D:$D,$C15) -> 56427.01 | H15: =SUMIFS('Detailed BS'!J:J,'Detailed BS'!$D:$D,$C15) -> 36704.78
B16: Total Current Assets | D16: =SUM(D9:D15) -> 5015632 | E16: =SUM(E9:E15) -> 5283476 | F16: =SUM(F9:F15) -> 5451707.5 | G16: =SUM(G9:G15) -> 5655102.7 | H16: =SUM(H9:H15) -> 5666486.8
B18: Fixed Assets
C19: Land | D19: =SUMIFS('Detailed BS'!F:F,'Detailed BS'!$D:$D,$C19) -> 122000 | E19: =SUMIFS('Detailed BS'!G:G,'Detailed BS'!$D:$D,$C19) -> 122000 | F19: =SUMIFS('Detailed BS'!H:H,'Detailed BS'!$D:$D,$C19) -> 122000 | G19: =SUMIFS('Detailed BS'!I:I,'Detailed BS'!$D:$D,$C19) -> 122000 | H19: =SUMIFS('Detailed BS'!J:J,'Detailed BS'!$D:$D,$C19) -> 122000
C20: Building | D20: =SUMIFS('Detailed BS'!F:F,'Detailed BS'!$D:$D,$C20) -> 1039840.7 | E20: =SUMIFS('Detailed BS'!G:G,'Detailed BS'!$D:$D,$C20) -> 1039840.7 | F20: =SUMIFS('Detailed BS'!H:H,'Detailed BS'!$D:$D,$C20) -> 1039840.7 | G20: =SUMIFS('Detailed BS'!I:I,'Detailed BS'!$D:$D,$C20) -> 1039840.7 | H20: =SUMIFS('Detailed BS'!J:J,'Detailed BS'!$D:$D,$C20) -> 1039840.7
C21: Leasehold Improvements | D21: =SUMIFS('Detailed BS'!F:F,'Detailed BS'!$D:$D,$C21) -> 230619.89 | E21: =SUMIFS('Detailed BS'!G:G,'Detailed BS'!$D:$D,$C21) -> 230619.89 | F21: =SUMIFS('Detailed BS'!H:H,'Detailed BS'!$D:$D,$C21) -> 230619.89 | G21: =SUMIFS('Detailed BS'!I:I,'Detailed BS'!$D:$D,$C21) -> 270383.64 | H21: =SUMIFS('Detailed BS'!J:J,'Detailed BS'!$D:$D,$C21) -> 270383.64
C22: Machinery & Equipment | D22: =SUMIFS('Detailed BS'!F:F,'Detailed BS'!$D:$D,$C22) -> 1849633.8 | E22: =SUMIFS('Detailed BS'!G:G,'Detailed BS'!$D:$D,$C22) -> 2015708.6 | F22: =SUMIFS('Detailed BS'!H:H,'Detailed BS'!$D:$D,$C22) -> 2156400.1 | G22: =SUMIFS('Detailed BS'!I:I,'Detailed BS'!$D:$D,$C22) -> 2162584.7 | H22: =SUMIFS('Detailed BS'!J:J,'Detailed BS'!$D:$D,$C22) -> 2162584.7
C23: Computer Equipment | D23: =SUMIFS('Detailed BS'!F:F,'Detailed BS'!$D:$D,$C23) -> 0 | E23: =SUMIFS('Detailed BS'!G:G,'Detailed BS'!$D:$D,$C23) -> 0 | F23: =SUMIFS('Detailed BS'!H:H,'Detailed BS'!$D:$D,$C23) -> 0 | G23: =SUMIFS('Detailed BS'!I:I,'Detailed BS'!$D:$D,$C23) -> 61187.02 | H23: =SUMIFS('Detailed BS'!J:J,'Detailed BS'!$D:$D,$C23) -> 61187.02
C24: Computer Software | D24: =SUMIFS('Detailed BS'!F:F,'Detailed BS'!$D:$D,$C24) -> 96925.38 | E24: =SUMIFS('Detailed BS'!G:G,'Detailed BS'!$D:$D,$C24) -> 96925.38 | F24: =SUMIFS('Detailed BS'!H:H,'Detailed BS'!$D:$D,$C24) -> 96925.38 | G24: =SUMIFS('Detailed BS'!I:I,'Detailed BS'!$D:$D,$C24) -> 96925.38 | H24: =SUMIFS('Detailed BS'!J:J,'Detailed BS'!$D:$D,$C24) -> 96925.38
C25: Automobiles | D25: =SUMIFS('Detailed BS'!F:F,'Detailed BS'!$D:$D,$C25) -> 110411.14 | E25: =SUMIFS('Detailed BS'!G:G,'Detailed BS'!$D:$D,$C25) -> 110411.14 | F25: =SUMIFS('Detailed BS'!H:H,'Detailed BS'!$D:$D,$C25) -> 110411.14 | G25: =SUMIFS('Detailed BS'!I:I,'Detailed BS'!$D:$D,$C25) -> 0 | H25: =SUMIFS('Detailed BS'!J:J,'Detailed BS'!$D:$D,$C25) -> 0
C26: Accumulated Depreciation | D26: =SUMIFS('Detailed BS'!F:F,'Detailed BS'!$D:$D,$C26) -> -3143237.1 | E26: =SUMIFS('Detailed BS'!G:G,'Detailed BS'!$D:$D,$C26) -> -3221865.5 | F26: =SUMIFS('Detailed BS'!H:H,'Detailed BS'!$D:$D,$C26) -> -3262811 | G26: =SUMIFS('Detailed BS'!I:I,'Detailed BS'!$D:$D,$C26) -> -3322429 | H26: =SUMIFS('Detailed BS'!J:J,'Detailed BS'!$D:$D,$C26) -> -3344929
C27: Accumulated Amortization | D27: =SUMIFS('Detailed BS'!F:F,'Detailed BS'!$D:$D,$C27) -> -96925.38 | E27: =SUMIFS('Detailed BS'!G:G,'Detailed BS'!$D:$D,$C27) -> -96925.38 | F27: =SUMIFS('Detailed BS'!H:H,'Detailed BS'!$D:$D,$C27) -> -96925.38 | G27: =SUMIFS('Detailed BS'!I:I,'Detailed BS'!$D:$D,$C27) -> -96925.38 | H27: =SUMIFS('Detailed BS'!J:J,'Detailed BS'!$D:$D,$C27) -> -96925.38
B28: Total Fixed Assets | D28: =SUM(D19:D27) -> 209268.38 | E28: =SUM(E19:E27) -> 296714.88 | F28: =SUM(F19:F27) -> 396460.82 | G28: =SUM(G19:G27) -> 333567.05 | H28: =SUM(H19:H27) -> 311067.05
B30: Total Assets | D30: =D28+D16 -> 5224900.4 | E30: =E28+E16 -> 5580190.9 | F30: =F28+F16 -> 5848168.3 | G30: =G28+G16 -> 5988669.7 | H30: =H28+H16 -> 5977553.8
B32: Liabilites & Equity
B33: Current Liabilities
C34: Accounts Payable | D34: =SUMIFS('Detailed BS'!F:F,'Detailed BS'!$D:$D,$C34) -> 34422.94 | E34: =SUMIFS('Detailed BS'!G:G,'Detailed BS'!$D:$D,$C34) -> 198880.72 | F34: =SUMIFS('Detailed BS'!H:H,'Detailed BS'!$D:$D,$C34) -> 176183.42 | G34: =SUMIFS('Detailed BS'!I:I,'Detailed BS'!$D:$D,$C34) -> 115586.41 | H34: =SUMIFS('Detailed BS'!J:J,'Detailed BS'!$D:$D,$C34) -> 78017.62
C35: Accured Expenses | D35: =SUMIFS('Detailed BS'!F:F,'Detailed BS'!$D:$D,$C35) -> 220208.63 | E35: =SUMIFS('Detailed BS'!G:G,'Detailed BS'!$D:$D,$C35) -> 267425.5 | F35: =SUMIFS('Detailed BS'!H:H,'Detailed BS'!$D:$D,$C35) -> 288664.96 | G35: =SUMIFS('Detailed BS'!I:I,'Detailed BS'!$D:$D,$C35) -> 205684.8 | H35: =SUMIFS('Detailed BS'!J:J,'Detailed BS'!$D:$D,$C35) -> 123292.21
C36: Leases Payable | D36: =SUMIFS('Detailed BS'!F:F,'Detailed BS'!$D:$D,$C36) -> 0 | E36: =SUMIFS('Detailed BS'!G:G,'Detailed BS'!$D:$D,$C36) -> 141531.06 | F36: =SUMIFS('Detailed BS'!H:H,'Detailed BS'!$D:$D,$C36) -> 178423.59 | G36: =SUMIFS('Detailed BS'!I:I,'Detailed BS'!$D:$D,$C36) -> 116507.76 | H36: =SUMIFS('Detailed BS'!J:J,'Detailed BS'!$D:$D,$C36) -> 66348.67
B37: Total Current Liabilites | D37: =SUM(D34:D36) -> 254631.57 | E37: =SUM(E34:E36) -> 607837.28 | F37: =SUM(F34:F36) -> 643271.97 | G37: =SUM(G34:G36) -> 437778.97 | H37: =SUM(H34:H36) -> 267658.5
B39: Equity
C40: Common Stock | D40: =SUMIFS('Detailed BS'!F:F,'Detailed BS'!$D:$D,$C40) -> 165000 | E40: =SUMIFS('Detailed BS'!G:G,'Detailed BS'!$D:$D,$C40) -> 165000 | F40: =SUMIFS('Detailed BS'!H:H,'Detailed BS'!$D:$D,$C40) -> 165000 | G40: =SUMIFS('Detailed BS'!I:I,'Detailed BS'!$D:$D,$C40) -> 165000 | H40: =SUMIFS('Detailed BS'!J:J,'Detailed BS'!$D:$D,$C40) -> 165000
C41: Dividends | D41: =SUMIFS('Detailed BS'!F:F,'Detailed BS'!$D:$D,$C41) -> -1792102.6 | E41: =SUMIFS('Detailed BS'!G:G,'Detailed BS'!$D:$D,$C41) -> -1554050.7 | F41: =SUMIFS('Detailed BS'!H:H,'Detailed BS'!$D:$D,$C41) -> -905247.85 | G41: =SUMIFS('Detailed BS'!I:I,'Detailed BS'!$D:$D,$C41) -> 0 | H41: =SUMIFS('Detailed BS'!J:J,'Detailed BS'!$D:$D,$C41) -> 37017.44
C42: Retained Earnings | D42: =SUMIFS('Detailed BS'!F:F,'Detailed BS'!$D:$D,$C42) -> 6477387 | E42: =SUMIFS('Detailed BS'!G:G,'Detailed BS'!$D:$D,$C42) -> 4805268.8 | F42: =SUMIFS('Detailed BS'!H:H,'Detailed BS'!$D:$D,$C42) -> 4944293.6 | G42: =SUMIFS('Detailed BS'!I:I,'Detailed BS'!$D:$D,$C42) -> 5164656.3 | H42: =SUMIFS('Detailed BS'!J:J,'Detailed BS'!$D:$D,$C42) -> 5385890.8
C43: Net Income | D43: =SUMIFS('Detailed BS'!F:F,'Detailed BS'!$D:$D,$C43) -> 119984.37 | E43: =SUMIFS('Detailed BS'!G:G,'Detailed BS'!$D:$D,$C43) -> 1556135.5 | F43: =SUMIFS('Detailed BS'!H:H,'Detailed BS'!$D:$D,$C43) -> 1000850.6 | G43: =SUMIFS('Detailed BS'!I:I,'Detailed BS'!$D:$D,$C43) -> 221234.47 | H43: =SUMIFS('Detailed BS'!J:J,'Detailed BS'!$D:$D,$C43) -> 121987.15
B44: Total Equity | D44: =SUM(D40:D43) -> 4970268.8 | E44: =SUM(E40:E43) -> 4972353.6 | F44: =SUM(F40:F43) -> 5204896.4 | G44: =SUM(G40:G43) -> 5550890.7 | H44: =SUM(H40:H43) -> 5709895.3
B46: Total Liabilities & Equity | D46: =D44+D37 -> 5224900.4 | E46: =E44+E37 -> 5580190.9 | F46: =F44+F37 -> 5848168.3 | G46: =G44+G37 -> 5988669.7 | H46: =H44+H37 -> 5977553.8
B48: Check | D48: =D30-D46 -> 0 | E48: =E30-E46 -> 0 | F48: =F30-F46 -> 0 | G48: =G30-G46 -> 0 | H48: =H30-H46 -> 0

Sheet Mapping>>

Sheet Chart of Accounts
B1: AAC Adjusted EBITDA Analysis
B2: Chart of Accounts
B5: Account Number | C5: Name | D5: KG Mapping | E5: Type
B6: 00-1110-000 | C6: =_xlfn.XLOOKUP(B6,'Sep 2025 BS'!A:A,'Sep 2025 BS'!B:B) -> -Chase - Checking | D6: Cash | E6: Asset
B7: 00-1111-000 | C7: =_xlfn.XLOOKUP(B7,'Sep 2025 BS'!A:A,'Sep 2025 BS'!B:B) -> -Chase - Payroll | D7: Cash | E7: Asset
B8: 00-1112-000 | C8: =_xlfn.XLOOKUP(B8,'Sep 2025 BS'!A:A,'Sep 2025 BS'!B:B) -> -Chase - AR Payments | D8: Cash | E8: Asset
B9: 00-1125-000 | C9: =_xlfn.XLOOKUP(B9,'Sep 2025 BS'!A:A,'Sep 2025 BS'!B:B) -> -Allowance for Doubtful Accounts | D9: Allowance for Doubtful Accounts | E9: Asset
B10: 00-1126-000 | C10: =_xlfn.XLOOKUP(B10,'Sep 2025 BS'!A:A,'Sep 2025 BS'!B:B) -> -Customer Deposits | D10: Customer Depsits | E10: Asset
B11: 00-1127-000 | C11: -A/R - Other | D11: Accounts Receivable | E11: Asset
B12: 00-1140-000 | C12: =_xlfn.XLOOKUP(B12,'Sep 2025 BS'!A:A,'Sep 2025 BS'!B:B) -> -Morgan Stanley | D12: Investments | E12: Asset
B13: 00-1150-000 | C13: Charles Scwab | D13: Investments | E13: Asset
B14: 00-1190-000 | C14: =_xlfn.XLOOKUP(B14,'Sep 2025 BS'!A:A,'Sep 2025 BS'!B:B) -> Petty Cash | D14: Cash | E14: Asset
B15: 00-1210-000 | C15: =_xlfn.XLOOKUP(B15,'Sep 2025 BS'!A:A,'Sep 2025 BS'!B:B) -> -Accounts Receivable | D15: Accounts Receivable | E15: Asset
B16: 00-1310-000 | C16: =_xlfn.XLOOKUP(B16,'Sep 2025 BS'!A:A,'Sep 2025 BS'!B:B) -> -Raw Material | D16: Inventory | E16: Asset
B17: 00-1320-000 | C17: =_xlfn.XLOOKUP(B17,'Sep 2025 BS'!A:A,'Sep 2025 BS'!B:B) -> -W I P | D17: Inventory | E17: Asset
B18: 00-1330-000 | C18: =_xlfn.XLOOKUP(B18,'Sep 2025 BS'!A:A,'Sep 2025 BS'!B:B) -> -Finished Goods | D18: Inventory | E18: Asset
B19: 00-1340-000 | C19: =_xlfn.XLOOKUP(B19,'Sep 2025 BS'!A:A,'Sep 2025 BS'!B:B) -> -Inventory - Inspection | D19: Inventory | E19: Asset
B20: 00-1350-000 | C20: =_xlfn.XLOOKUP(B20,'Sep 2025 BS'!A:A,'Sep 2025 BS'!B:B) -> -Inventory - DMR Pending | D20: Inventory | E20: Asset
B21: 00-1410-000 | C21: =_xlfn.XLOOKUP(B21,'Sep 2025 BS'!A:A,'Sep 2025 BS'!B:B) -> -Land | D21: Land | E21: Asset
B22: 00-1420-000 | C22: =_xlfn.XLOOKUP(B22,'Sep 2025 BS'!A:A,'Sep 2025 BS'!B:B) -> -Building | D22: Building | E22: Asset
B23: 00-1430-000 | C23: =_xlfn.XLOOKUP(B23,'Sep 2025 BS'!A:A,'Sep 2025 BS'!B:B) -> -Leasehold Improvements | D23: Leasehold Improvements | E23: Asset
B24: 00-1440-000 | C24: =_xlfn.XLOOKUP(B24,'Sep 2025 BS'!A:A,'Sep 2025 BS'!B:B) -> -Machinery & Equipment | D24: Machinery & Equipment | E24: Asset
B25: 00-1460-000 | C25: =_xlfn.XLOOKUP(B25,'Sep 2025 BS'!A:A,'Sep 2025 BS'!B:B) -> -Computer Equipment | D25: Computer Equipment | E25: Asset
... B32: 00-1530-000 | C32: =_xlfn.XLOOKUP(B32,'Sep 2025 BS'!A:A,'Sep 2025 BS'!B:B) -> -Prepaid RE Taxes | D32: Prepaid Expenses | E32: Asset
B33: 00-1540-000 | C33: -Prepaid Other | D33: Prepaid Expenses | E33: Asset
B34: 00-1550-000 | C34: =_xlfn.XLOOKUP(B34,'Sep 2025 BS'!A:A,'Sep 2025 BS'!B:B) -> -Advances | D34: Prepaid Expenses | E34: Asset
B35: 00-1560-000 | C35: =_xlfn.XLOOKUP(B35,'Sep 2025 BS'!A:A,'Sep 2025 BS'!B:B) -> -PPD - Trade Show Expenses | D35: Prepaid Expenses | E35: Asset
B36: 00-2110-000 | C36: =_xlfn.XLOOKUP(B36,'Sep 2025 BS'!A:A,'Sep 2025 BS'!B:B) -> -Accounts Payable | D36: Accounts Payable | E36: Liability
B37: 00-2115-000 | C37: =_xlfn.XLOOKUP(B37,'Sep 2025 BS'!A:A,'Sep 2025 BS'!B:B) -> AMEX Payable | D37: Accounts Payable | E37: Liability
B38: 00-2116-000 | C38: -VISA Payable | D38: Accounts Payable | E38: Liability
B39: 00-2120-000 | C39: =_xlfn.XLOOKUP(B39,'Sep 2025 BS'!A:A,'Sep 2025 BS'!B:B) -> -Accrued Purchase Receipts | D39: Accounts Payable | E39: Liability
B40: 00-2230-000 | C40: -401K Payable | D40: Accured Expenses | E40: Liability
B41: 00-2295-000 | C41: =_xlfn.XLOOKUP(B41,'Sep 2025 BS'!A:A,'Sep 2025 BS'!B:B) -> -Lease Payable - Screen Printer | D41: Leases Payable | E41: Liability
B42: 00-2296-000 | C42: =_xlfn.XLOOKUP(B42,'Sep 2025 BS'!A:A,'Sep 2025 BS'!B:B) -> -Lease Payable - Pick and Place | D42: Leases Payable | E42: Liability
B43: 00-2297-000 | C43: =_xlfn.XLOOKUP(B43,'Sep 2025 BS'!A:A,'Sep 2025 BS'!B:B) -> -Lease Payable - Phone System | D43: Leases Payable | E43: Liability
B44: 00-2310-000 | C44: =_xlfn.XLOOKUP(B44,'Sep 2025 BS'!A:A,'Sep 2025 BS'!B:B) -> -Accrued Payroll & Taxes | D44: Accured Expenses | E44: Liability
B45: 00-2340-000 | C45: =_xlfn.XLOOKUP(B45,'Sep 2025 BS'!A:A,'Sep 2025 BS'!B:B) -> -Accrued Expenses | D45: Accured Expenses | E45: Liability
B46: 00-2350-000 | C46: =_xlfn.XLOOKUP(B46,'Sep 2025 BS'!A:A,'Sep 2025 BS'!B:B) -> -Accrued Profit Sharing | D46: Accured Expenses | E46: Liability
B47: 00-3300-000 | C47: Common Stock | D47: Common Stock | E47: Equity
B48: 00-3310-000 | C48: =_xlfn.XLOOKUP(B48,'Sep 2025 BS'!A:A,'Sep 2025 BS'!B:B) -> -Retained Earnings - Distributions | D48: Retained Earnings | E48: Equity
B49: 00-3320-000 | C49: Tax Payments-Current Year | D49: Dividends | E49: Equity
B50: 00-3330-000 | C50: Distributions-Current Year | D50: Dividends | E50: Equity
B51: 00-3340-000 | C51: Retained Earnings-Prior Years | D51: Retained Earnings | E51: Equity
B52: 00-3350-000 | C52: Current Year - Profit ( Loss ) | D52: Net Income | E52: Equity
B53: 00-5110 | C53: -Product Sales | D53: Product Sales | E53: Revenue
B54: 00-5110-000 | C54: -Product Sales | D54: Product Sales | E54: Revenue
B55: 00-5120-000 | C55: -Customer Returns | D55: Other Income | E55: Revenue
B56: 00-5130 | C56: -Customer Credits & Discounts | D56: Other Income | E56: Revenue
B57: 00-5130-000 | C57: -Customer Credits & Discounts | D57: Other Income | E57: Revenue
B58: 00-5190-000 | C58: -Other Customer Charges | D58: Other Income | E58: Revenue
B59: 00-5510-000 | C59: -Engineering Services | D59: Engineering Services | E59: Revenue
B60: 00-6110-000 | C60: -Material - Product Sales | D60: Materials | E60: Cost of Goods Sold
... B214: -9310 | C214: -Travel & Lodging | D214: Other Expenses | E214: General & Administrative

Sheet Detailed IS
B1: AAC Adjusted EBITDA Analysis
B2: Detailed IS
B4: Account Number | C4: Name | D4: KG Mapping | E4: Type | F4: 44561 | G4: =EOMONTH(F4,12) -> 44926 | H4: =EOMONTH(G4,12) -> 45291 | I4: =EOMONTH(H4,12) -> 45657 | J4: =EOMONTH(I4,9) -> 45930
B5: 00-5110 | C5: -Product Sales | D5: =_xlfn.XLOOKUP(B5,'Chart of Accounts'!B:B,'Chart of Accounts'!D:D) -> Product Sales | E5: Revenue | F5: =SUMIFS('2021 IS'!C:C,'2021 IS'!A:A,B5) -> 0 | G5: =SUMIFS('2022 IS'!C:C,'2022 IS'!A:A,B5) -> 0 | H5: =SUMIFS('2023 IS'!C:C,'2023 IS'!A:A,B5) -> 0 | I5: =SUMIFS('2024 IS'!C:C,'2024 IS'!A:A,B5) -> 0 | J5: =SUMIFS('2025 IS'!C:C,'2025 IS'!A:A,B5) -> 0
B6: 00-5110-000 | C6: -Product Sales | D6: =_xlfn.XLOOKUP(B6,'Chart of Accounts'!B:B,'Chart of Accounts'!D:D) -> Product Sales | E6: Revenue | F6: =SUMIFS('2021 IS'!C:C,'2021 IS'!A:A,B6) -> 1125166.1 | G6: =SUMIFS('2022 IS'!C:C,'2022 IS'!A:A,B6) -> 515796.36 | H6: =SUMIFS('2023 IS'!C:C,'2023 IS'!A:A,B6) -> 1245336.4 | I6: =SUMIFS('2024 IS'!C:C,'2024 IS'!A:A,B6) -> 937459.54 | J6: =SUMIFS('2025 IS'!C:C,'2025 IS'!A:A,B6) -> 392663.3
B7: 00-5120-000 | C7: -Customer Returns | D7: =_xlfn.XLOOKUP(B7,'Chart of Accounts'!B:B,'Chart of Accounts'!D:D) -> Other Income | E7: Revenue | F7: =SUMIFS('2021 IS'!C:C,'2021 IS'!A:A,B7) -> 0 | G7: =SUMIFS('2022 IS'!C:C,'2022 IS'!A:A,B7) -> 0 | H7: =SUMIFS('2023 IS'!C:C,'2023 IS'!A:A,B7) -> 0 | I7: =SUMIFS('2024 IS'!C:C,'2024 IS'!A:A,B7) -> 0 | J7: =SUMIFS('2025 IS'!C:C,'2025 IS'!A:A,B7) -> 0
B8: 00-5130 | C8: -Customer Credits & Discounts | D8: =_xlfn.XLOOKUP(B8,'Chart of Accounts'!B:B,'Chart of Accounts'!D:D) -> Other Income | E8: Revenue | F8: =SUMIFS('2021 IS'!C:C,'2021 IS'!A:A,B8) -> 0 | G8: =SUMIFS('2022 IS'!C:C,'2022 IS'!A:A,B8) -> 0 | H8: =SUMIFS('2023 IS'!C:C,'2023 IS'!A:A,B8) -> 0 | I8: =SUMIFS('2024 IS'!C:C,'2024 IS'!A:A,B8) -> 0 | J8: =SUMIFS('2025 IS'!C:C,'2025 IS'!A:A,B8) -> 0
B9: 00-5130-000 | C9: -Customer Credits & Discounts | D9: =_xlfn.XLOOKUP(B9,'Chart of Accounts'!B:B,'Chart of Accounts'!D:D) -> Other Income | E9: Revenue | F9: =SUMIFS('2021 IS'!C:C,'2021 IS'!A:A,B9) -> 6300 | G9: =SUMIFS('2022 IS'!C:C,'2022 IS'!A:A,B9) -> 0 | H9: =SUMIFS('2023 IS'!C:C,'2023 IS'!A:A,B9) -> -0.71 | I9: =SUMIFS('2024 IS'!C:C,'2024 IS'!A:A,B9) -> -102 | J9: =SUMIFS('2025 IS'!C:C,'2025 IS'!A:A,B9) -> 0
B10: 00-5190-000 | C10: -Other Customer Charges | D10: =_xlfn.XLOOKUP(B10,'Chart of Accounts'!B:B,'Chart of Accounts'!D:D) -> Other Income | E10: Revenue | F10: =SUMIFS('2021 IS'!C:C,'2021 IS'!A:A,B10) -> 675 | G10: =SUMIFS('2022 IS'!C:C,'2022 IS'!A:A,B10) -> 510 | H10: =SUMIFS('2023 IS'!C:C,'2023 IS'!A:A,B10) -> 5500 | I10: =SUMIFS('2024 IS'!C:C,'2024 IS'!A:A,B10) -> 2300 | J10: =SUMIFS('2025 IS'!C:C,'2025 IS'!A:A,B10) -> 300
B11: 00-5510-000 | C11: -Engineering Services | D11: =_xlfn.XLOOKUP(B11,'Chart of Accounts'!B:B,'Chart of Accounts'!D:D) -> Engineering Services | E11: Revenue | F11: =SUMIFS('2021 IS'!C:C,'2021 IS'!A:A,B11) -> 0 | G11: =SUMIFS('2022 IS'!C:C,'2022 IS'!A:A,B11) -> 0 | H11: =SUMIFS('2023 IS'!C:C,'2023 IS'!A:A,B11) -> 0 | I11: =SUMIFS('2024 IS'!C:C,'2024 IS'!A:A,B11) -> 364232 | J11: =SUMIFS('2025 IS'!C:C,'2025 IS'!A:A,B11) -> 0
B12: -5130 | C12: -Customer Credits & Discounts | D12: =_xlfn.XLOOKUP(B12,'Chart of Accounts'!B:B,'Chart of Accounts'!D:D) -> Other Income | E12: Revenue | F12: =SUMIFS('2021 IS'!C:C,'2021 IS'!A:A,B12) -> 0 | G12: =SUMIFS('2022 IS'!C:C,'2022 IS'!A:A,B12) -> 0 | H12: =SUMIFS('2023 IS'!C:C,'2023 IS'!A:A,B12) -> 0 | I12: =SUMIFS('2024 IS'!C:C,'2024 IS'!A:A,B12) -> 0 | J12: =SUMIFS('2025 IS'!C:C,'2025 IS'!A:A,B12) -> 0
B13: 00-6110-000 | C13: -Material - Product Sales | D13: =_xlfn.XLOOKUP(B13,'Chart of Accounts'!B:B,'Chart of Accounts'!D:D) -> Materials | E13: Cost of Goods Sold | F13: =SUMIFS('2021 IS'!C:C,'2021 IS'!A:A,B13) -> 189511.51 | G13: =SUMIFS('2022 IS'!C:C,'2022 IS'!A:A,B13) -> 439243.06 | H13: =SUMIFS('2023 IS'!C:C,'2023 IS'!A:A,B13) -> 76639.33 | I13: =SUMIFS('2024 IS'!C:C,'2024 IS'!A:A,B13) -> -209294.31 | J13: =SUMIFS('2025 IS'!C:C,'2025 IS'!A:A,B13) -> 44925.16
B14: 00-6120-000 | C14: -Labor - Product Sales | D14: =_xlfn.XLOOKUP(B14,'Chart of Accounts'!B:B,'Chart of Accounts'!D:D) -> Salaries and Wages - Direct | E14: Cost of Goods Sold | F14: =SUMIFS('2021 IS'!C:C,'2021 IS'!A:A,B14) -> 29407.01 | G14: =SUMIFS('2022 IS'!C:C,'2022 IS'!A:A,B14) -> 30516.8 | H14: =SUMIFS('2023 IS'!C:C,'2023 IS'!A:A,B14) -> 52120.78 | I14: =SUMIFS('2024 IS'!C:C,'2024 IS'!A:A,B14) -> 29716.65 | J14: =SUMIFS('2025 IS'!C:C,'2025 IS'!A:A,B14) -> 35372.67
B15: 00-6130-000 | C15: -Overhead - Product Sales | D15: =_xlfn.XLOOKUP(B15,'Chart of Accounts'!B:B,'Chart of Accounts'!D:D) -> Overhead | E15: Cost of Goods Sold | F15: =SUMIFS('2021 IS'!C:C,'2021 IS'!A:A,B15) -> 44154.87 | G15: =SUMIFS('2022 IS'!C:C,'2022 IS'!A:A,B15) -> 45772.59 | H15: =SUMIFS('2023 IS'!C:C,'2023 IS'!A:A,B15) -> 78436.09 | I15: =SUMIFS('2024 IS'!C:C,'2024 IS'!A:A,B15) -> 44657.41 | J15: =SUMIFS('2025 IS'!C:C,'2025 IS'!A:A,B15) -> 126933.91
B16: 00-6140-000 | C16: -Outside Services - Product Sales | D16: =_xlfn.XLOOKUP(B16,'Chart of Accounts'!B:B,'Chart of Accounts'!D:D) -> Outside Services | E16: Cost of Goods Sold | F16: =SUMIFS('2021 IS'!C:C,'2021 IS'!A:A,B16) -> 13578.35 | G16: =SUMIFS('2022 IS'!C:C,'2022 IS'!A:A,B16) -> 6833.06 | H16: =SUMIFS('2023 IS'!C:C,'2023 IS'!A:A,B16) -> 22493.41 | I16: =SUMIFS('2024 IS'!C:C,'2024 IS'!A:A,B16) -> 9512.15 | J16: =SUMIFS('2025 IS'!C:C,'2025 IS'!A:A,B16) -> 16237.04
... B166: 00-9995-000 | C166: -Corporate Taxes - State | D166: =_xlfn.XLOOKUP(B166,'Chart of Accounts'!B:B,'Chart of Accounts'!D:D) -> Corporate Taxes | E166: Taxes | F166: =SUMIFS('2021 IS'!C:C,'2021 IS'!A:A,B166) -> 0 | G166: =SUMIFS('2022 IS'!C:C,'2022 IS'!A:A,B166) -> 166364.31 | H166: =SUMIFS('2023 IS'!C:C,'2023 IS'!A:A,B166) -> 26209.75 | I166: =SUMIFS('2024 IS'!C:C,'2024 IS'!A:A,B166) -> 6209.75 | J166: =SUMIFS('2025 IS'!C:C,'2025 IS'!A:A,B166) -> 0

Sheet Detailed BS
B1: AAC Adjusted EBITDA Analysis
B2: Detailed BS
B4: Account Number | C4: Name | D4: KG Mapping | E4: Type | F4: 44561 | G4: =EOMONTH(F4,12) -> 44926 | H4: =EOMONTH(G4,12) -> 45291 | I4: =EOMONTH(H4,12) -> 45657 | J4: =EOMONTH(I4,9) -> 45930
B5: 00-1110-000 | C5: =_xlfn.XLOOKUP(B5,'Chart of Accounts'!B:B,'Chart of Accounts'!C:C) -> -Chase - Checking | D5: =_xlfn.XLOOKUP(B5,'Chart of Accounts'!B:B,'Chart of Accounts'!D:D) -> Cash | E5: Asset | F5: =SUMIFS('2022 BS'!D:D,'2022 BS'!A:A,$B5) -> 968363.21 | G5: =SUMIFS('2022 BS'!C:C,'2022 BS'!A:A,B5) -> 2210695.4 | H5: =SUMIFS('2023 BS'!C:C,'2023 BS'!A:A,B5) -> 1598672.4 | I5: =SUMIFS('2024 BS'!C:C,'2024 BS'!A:A,B5) -> 533754.04 | J5: =SUMIFS('Sep 2025 BS'!C:C,'Sep 2025 BS'!A:A,B5) -> 382938.75
B6: 00-1111-000 | C6: =_xlfn.XLOOKUP(B6,'Chart of Accounts'!B:B,'Chart of Accounts'!C:C) -> -Chase - Payroll | D6: =_xlfn.XLOOKUP(B6,'Chart of Accounts'!B:B,'Chart of Accounts'!D:D) -> Cash | E6: Asset | F6: =SUMIFS('2022 BS'!D:D,'2022 BS'!A:A,$B6) -> 223606.31 | G6: =SUMIFS('2022 BS'!C:C,'2022 BS'!A:A,B6) -> 185561.08 | H6: =SUMIFS('2023 BS'!C:C,'2023 BS'!A:A,B6) -> 14095.12 | I6: =SUMIFS('2024 BS'!C:C,'2024 BS'!A:A,B6) -> 131962.6 | J6: =SUMIFS('Sep 2025 BS'!C:C,'Sep 2025 BS'!A:A,B6) -> 116237.34
B7: 00-1112-000 | C7: =_xlfn.XLOOKUP(B7,'Chart of Accounts'!B:B,'Chart of Accounts'!C:C) -> -Chase - AR Payments | D7: =_xlfn.XLOOKUP(B7,'Chart of Accounts'!B:B,'Chart of Accounts'!D:D) -> Cash | E7: Asset | F7: =SUMIFS('2022 BS'!D:D,'2022 BS'!A:A,$B7) -> 6738.44 | G7: =SUMIFS('2022 BS'!C:C,'2022 BS'!A:A,B7) -> 2000 | H7: =SUMIFS('2023 BS'!C:C,'2023 BS'!A:A,B7) -> 2000 | I7: =SUMIFS('2024 BS'!C:C,'2024 BS'!A:A,B7) -> 360982.28 | J7: =SUMIFS('Sep 2025 BS'!C:C,'Sep 2025 BS'!A:A,B7) -> 81142.26
B8: 00-1125-000 | C8: =_xlfn.XLOOKUP(B8,'Chart of Accounts'!B:B,'Chart of Accounts'!C:C) -> -Allowance for Doubtful Accounts | D8: =_xlfn.XLOOKUP(B8,'Chart of Accounts'!B:B,'Chart of Accounts'!D:D) -> Allowance for Doubtful Accounts | E8: Asset | F8: =SUMIFS('2022 BS'!D:D,'2022 BS'!A:A,$B8) -> -15130.57 | G8: =SUMIFS('2022 BS'!C:C,'2022 BS'!A:A,B8) -> -15130.57 | H8: =SUMIFS('2023 BS'!C:C,'2023 BS'!A:A,B8) -> -15130.57 | I8: =SUMIFS('2024 BS'!C:C,'2024 BS'!A:A,B8) -> -15130.57 | J8: =SUMIFS('Sep 2025 BS'!C:C,'Sep 2025 BS'!A:A,B8) -> -15130.57
B9: 00-1126-000 | C9: =_xlfn.XLOOKUP(B9,'Chart of Accounts'!B:B,'Chart of Accounts'!C:C) -> -Customer Deposits | D9: =_xlfn.XLOOKUP(B9,'Chart of Accounts'!B:B,'Chart of Accounts'!D:D) -> Customer Depsits | E9: Asset | F9: =SUMIFS('2022 BS'!D:D,'2022 BS'!A:A,$B9) -> -24542.41 | G9: =SUMIFS('2022 BS'!C:C,'2022 BS'!A:A,B9) -> -18599.3 | H9: =SUMIFS('2023 BS'!C:C,'2023 BS'!A:A,B9) -> -28159.91 | I9: =SUMIFS('2024 BS'!C:C,'2024 BS'!A:A,B9) -> -31574.74 | J9: =SUMIFS('Sep 2025 BS'!C:C,'Sep 2025 BS'!A:A,B9) -> -19542.76
B10: 00-1127-000 | C10: =_xlfn.XLOOKUP(B10,'Chart of Accounts'!B:B,'Chart of Accounts'!C:C) -> -A/R - Other | D10: =_xlfn.XLOOKUP(B10,'Chart of Accounts'!B:B,'Chart of Accounts'!D:D) -> Accounts Receivable | E10: Asset | F10: =SUMIFS('2022 BS'!D:D,'2022 BS'!A:A,$B10) -> 0 | G10: =SUMIFS('2022 BS'!C:C,'2022 BS'!A:A,B10) -> 0 | H10: =SUMIFS('2023 BS'!C:C,'2023 BS'!A:A,B10) -> 0 | I10: =SUMIFS('2024 BS'!C:C,'2024 BS'!A:A,B10) -> 6098.5 | J10: =SUMIFS('Sep 2025 BS'!C:C,'Sep 2025 BS'!A:A,B10) -> 0
B11: 00-1140-000 | C11: =_xlfn.XLOOKUP(B11,'Chart of Accounts'!B:B,'Chart of Accounts'!C:C) -> -Morgan Stanley | D11: =_xlfn.XLOOKUP(B11,'Chart of Accounts'!B:B,'Chart of Accounts'!D:D) -> Investments | E11: Asset | F11: =SUMIFS('2022 BS'!D:D,'2022 BS'!A:A,$B11) -> 579372.3 | G11: =SUMIFS('2022 BS'!C:C,'2022 BS'!A:A,B11) -> 405784.26 | H11: =SUMIFS('2023 BS'!C:C,'2023 BS'!A:A,B11) -> 420307.73 | I11: =SUMIFS('2024 BS'!C:C,'2024 BS'!A:A,B11) -> 815111.44 | J11: =SUMIFS('Sep 2025 BS'!C:C,'Sep 2025 BS'!A:A,B11) -> 1723864.4
B12: 00-1150-000 | C12: =_xlfn.XLOOKUP(B12,'Chart of Accounts'!B:B,'Chart of Accounts'!C:C) -> Charles Scwab | D12: =_xlfn.XLOOKUP(B12,'Chart of Accounts'!B:B,'Chart of Accounts'!D:D) -> Investments | E12: Asset | F12: =SUMIFS('2022 BS'!D:D,'2022 BS'!A:A,$B12) -> 5785.03 | G12: =SUMIFS('2022 BS'!C:C,'2022 BS'!A:A,B12) -> 0 | H12: =SUMIFS('2023 BS'!C:C,'2023 BS'!A:A,B12) -> 0 | I12: =SUMIFS('2024 BS'!C:C,'2024 BS'!A:A,B12) -> 0 | J12: =SUMIFS('Sep 2025 BS'!C:C,'Sep 2025 BS'!A:A,B12) -> 0
B13: 00-1190-000 | C13: =_xlfn.XLOOKUP(B13,'Chart of Accounts'!B:B,'Chart of Accounts'!C:C) -> Petty Cash | D13: =_xlfn.XLOOKUP(B13,'Chart of Accounts'!B:B,'Chart of Accounts'!D:D) -> Cash | E13: Asset | F13: =SUMIFS('2022 BS'!D:D,'2022 BS'!A:A,$B13) -> 500 | G13: =SUMIFS('2022 BS'!C:C,'2022 BS'!A:A,B13) -> 500 | H13: =SUMIFS('2023 BS'!C:C,'2023 BS'!A:A,B13) -> 500 | I13: =SUMIFS('2024 BS'!C:C,'2024 BS'!A:A,B13) -> 0 | J13: =SUMIFS('Sep 2025 BS'!C:C,'Sep 2025 BS'!A:A,B13) -> 0
B14: 00-1210-000 | C14: =_xlfn.XLOOKUP(B14,'Chart of Accounts'!B:B,'Chart of Accounts'!C:C) -> -Accounts Receivable | D14: =_xlfn.XLOOKUP(B14,'Chart of Accounts'!B:B,'Chart of Accounts'!D:D) -> Accounts Receivable | E14: Asset | F14: =SUMIFS('2022 BS'!D:D,'2022 BS'!A:A,$B14) -> 1105726.3 | G14: =SUMIFS('2022 BS'!C:C,'2022 BS'!A:A,B14) -> 525775.94 | H14: =SUMIFS('2023 BS'!C:C,'2023 BS'!A:A,B14) -> 1262808.8 | I14: =SUMIFS('2024 BS'!C:C,'2024 BS'!A:A,B14) -> 1141704.1 | J14: =SUMIFS('Sep 2025 BS'!C:C,'Sep 2025 BS'!A:A,B14) -> 437988.79
B15: 00-1310-000 | C15: =_xlfn.XLOOKUP(B15,'Chart of Accounts'!B:B,'Chart of Accounts'!C:C) -> -Raw Material | D15: =_xlfn.XLOOKUP(B15,'Chart of Accounts'!B:B,'Chart of Accounts'!D:D) -> Inventory | E15: Asset | F15: =SUMIFS('2022 BS'!D:D,'2022 BS'!A:A,$B15) -> 1415642.8 | G15: =SUMIFS('2022 BS'!C:C,'2022 BS'!A:A,B15) -> 1444746.5 | H15: =SUMIFS('2023 BS'!C:C,'2023 BS'!A:A,B15) -> 1624790.3 | I15: =SUMIFS('2024 BS'!C:C,'2024 BS'!A:A,B15) -> 2020749.1 | J15: =SUMIFS('Sep 2025 BS'!C:C,'Sep 2025 BS'!A:A,B15) -> 2080333.4
B16: 00-1320-000 | C16: =_xlfn.XLOOKUP(B16,'Chart of Accounts'!B:B,'Chart of Accounts'!C:C) -> -W I P | D16: =_xlfn.XLOOKUP(B16,'Chart of Accounts'!B:B,'Chart of Accounts'!D:D) -> Inventory | E16: Asset | F16: =SUMIFS('2022 BS'!D:D,'2022 BS'!A:A,$B16) -> 375815.92 | G16: =SUMIFS('2022 BS'!C:C,'2022 BS'!A:A,B16) -> 379024.97 | H16: =SUMIFS('2023 BS'!C:C,'2023 BS'!A:A,B16) -> 323109.05 | I16: =SUMIFS('2024 BS'!C:C,'2024 BS'!A:A,B16) -> 562533.14 | J16: =SUMIFS('Sep 2025 BS'!C:C,'Sep 2025 BS'!A:A,B16) -> 741600.29
... B46: 00-3310-000 | C46: =_xlfn.XLOOKUP(B46,'Chart of Accounts'!B:B,'Chart of Accounts'!C:C) -> -Retained Earnings - Distributions | D46: =_xlfn.XLOOKUP(B46,'Chart of Accounts'!B:B,'Chart of Accounts'!D:D) -> Retained Earnings | E46: Equity | F46: =SUMIFS('2022 BS'!D:D,'2022 BS'!A:A,$B46) -> -14380363 | G46: =SUMIFS('2022 BS'!C:C,'2022 BS'!A:A,B46) -> -16172466 | H46: =SUMIFS('2023 BS'!C:C,'2023 BS'!A:A,B46) -> -17589577 | I46: =SUMIFS('2024 BS'!C:C,'2024 BS'!A:A,B46) -> -18370065 | J46: =SUMIFS('Sep 2025 BS'!C:C,'Sep 2025 BS'!A:A,B46) -> -18370065
B47: 00-3300-000 | C47: Common Stock | D47: =_xlfn.XLOOKUP(B47,'Chart of Accounts'!B:B,'Chart of Accounts'!D:D) -> Common Stock | E47: Equity | F47: =SUMIFS('2022 BS'!D:D,'2022 BS'!A:A,$B47) -> 165000 | G47: =SUMIFS('2022 BS'!C:C,'2022 BS'!A:A,B47) -> 165000 | H47: =SUMIFS('2023 BS'!C:C,'2023 BS'!A:A,B47) -> 165000 | I47: =SUMIFS('2024 BS'!C:C,'2024 BS'!A:A,B47) -> 165000 | J47: =SUMIFS('Sep 2025 BS'!C:C,'Sep 2025 BS'!A:A,B47) -> 165000
B48: 00-3320-000 | C48: Tax Payments-Current Year | D48: =_xlfn.XLOOKUP(B48,'Chart of Accounts'!B:B,'Chart of Accounts'!D:D) -> Dividends | E48: Equity | F48: =SUMIFS('2022 BS'!D:D,'2022 BS'!A:A,$B48) -> -871770 | G48: =SUMIFS('2022 BS'!C:C,'2022 BS'!A:A,B48) -> -1181600 | H48: =SUMIFS('2023 BS'!C:C,'2023 BS'!A:A,B48) -> -170000 | I48: =SUMIFS('2024 BS'!C:C,'2024 BS'!A:A,B48) -> 0 | J48: =SUMIFS('Sep 2025 BS'!C:C,'Sep 2025 BS'!A:A,B48) -> 37017.44
B49: 00-3330-000 | C49: Distributions-Current Year | D49: =_xlfn.XLOOKUP(B49,'Chart of Accounts'!B:B,'Chart of Accounts'!D:D) -> Dividends | E49: Equity | F49: =SUMIFS('2022 BS'!D:D,'2022 BS'!A:A,$B49) -> -920332.57 | G49: =SUMIFS('2022 BS'!C:C,'2022 BS'!A:A,B49) -> -372450.74 | H49: =SUMIFS('2023 BS'!C:C,'2023 BS'!A:A,B49) -> -735247.85 | I49: =SUMIFS('2024 BS'!C:C,'2024 BS'!A:A,B49) -> 0 | J49: =SUMIFS('Sep 2025 BS'!C:C,'Sep 2025 BS'!A:A,B49) -> 0
B50: 00-3340-000 | C50: Retained Earnings-Prior Years | D50: =_xlfn.XLOOKUP(B50,'Chart of Accounts'!B:B,'Chart of Accounts'!D:D) -> Retained Earnings | E50: Equity | F50: =SUMIFS('2022 BS'!D:D,'2022 BS'!A:A,$B50) -> 20857750 | G50: =SUMIFS('2022 BS'!C:C,'2022 BS'!A:A,B50) -> 20977735 | H50: =SUMIFS('2023 BS'!C:C,'2023 BS'!A:A,B50) -> 22533870 | I50: =SUMIFS('2024 BS'!C:C,'2024 BS'!A:A,B50) -> 23534721 | J50: =SUMIFS('Sep 2025 BS'!C:C,'Sep 2025 BS'!A:A,B50) -> 23755955
B51: 00-3350-000 | C51: Current Year - Profit ( Loss ) | D51: =_xlfn.XLOOKUP(B51,'Chart of Accounts'!B:B,'Chart of Accounts'!D:D) -> Net Income | E51: Equity | F51: =SUMIFS('2022 BS'!D:D,'2022 BS'!A:A,$B51) -> 119984.37 | G51: =SUMIFS('2022 BS'!C:C,'2022 BS'!A:A,B51) -> 1556135.5 | H51: =SUMIFS('2023 BS'!C:C,'2023 BS'!A:A,B51) -> 1000850.6 | I51: =SUMIFS('2024 BS'!C:C,'2024 BS'!A:A,B51) -> 221234.47 | J51: =SUMIFS('Sep 2025 BS'!C:C,'Sep 2025 BS'!A:A,B51) -> 121987.15

Sheet Source Documents >>>

Sheet EBITDA
A1: American Aerospace Controls, Inc.
A2: Adjusted EBITDA Summaries
A4: 2021-2025
D5: 2021 | E5: 2022 | F5: 2023 | G5: 2024 | H5: 2025 YTD
H6: Sept
A7: Net Income per Books | D7: 119984 | E7: 1556136 | F7: 1000851 | G7: 220635 | H7: 121987
A9: Depreciation & Amortization | D9: =10500+59499 -> 69999 | E9: =11794+66834 -> 78628 | F9: 168273 | G9: =114510+20208 -> 134718 | H9: 17000
A10: Interest Expense | D10: 0 | E10: 0 | F10: 13668 | G10: 5890 | H10: 9986
A11: Taxes | D11: 25 | E11: 0 | F11: 30767 | G11: 80165 | H11: 0
A12: Fed Employee Tax Credits | D12: -4611 | E12: 0 | F12: 0 | G12: 0 | H12: 0
A13: Investment (income) loss | D13: -23926 | E13: =-19566-92360 -> -111926 | F13: -14523 | G13: =-17677+35311 -> 17634 | H13: =-41956-88475 -> -130431
B15: Book EBITDA | D15: =SUM(D7:D14) -> 161471 | E15: =SUM(E7:E14) -> 1522838 | F15: =SUM(F7:F14) -> 1199036 | G15: =SUM(G7:G14) -> 459042 | H15: =SUM(H7:H14) -> 18542
A17: Adjustments:
B18: Officer's Salary | D18: 355769 | E18: 364361 | F18: 171000 | G18: 100000 | H18: 75000
B19: Directors Fees | D19: 180693 | E19: 180000 | F19: 224000 | G19: 240000 | H19: 178846
B20: Dennis PA | D20: 15000 | E20: 0 | F20: 0 | G20: 0 | H20: 0
B21: Prof/Cons Fees | D21: =+'Prof Fees'!C8 -> 10580 | E21: =+'Prof Fees'!C20 -> 28054 | F21: =+'Prof Fees'!C35 -> 31288 | G21: =+'Prof Fees'!C44 -> 53880 | H21: =+'Prof Fees'!C56 -> 86402
B22: Acctg Fees | D22: 0 | E22: =+'Prof Fees'!G20 -> 37000 | F22: =+'Prof Fees'!G35 -> 45000 | G22: 0 | H22: 0
B23: MFG Variance | D23: 0 | E23: 0 | F23: 0 | G23: =-H23 -> -265500 | H23: 265500
B24: Staff Cash Bonuses | D24: 40000 | E24: 40000 | F24: 40000 | G24: 40000 | H24: 40000
B25: Net Adjustments | D25: =SUM(D18:D24) -> 602042 | E25: =SUM(E18:E24) -> 649415 | F25: =SUM(F18:F24) -> 511288 | G25: =SUM(G18:G24) -> 168380 | H25: =SUM(H18:H24) -> 645748
B27: Adjusted EBITDA | D27: =+D15+D25 -> 763513 | E27: =+E15+E25 -> 2172253 | F27: =+F15+F25 -> 1710324 | G27: =+G15+G25 -> 627422 | H27: =+H15+H25 -> 664290

Sheet Prof Fees
A1: AAC
A2: Consulting Fees - Non recurring
A4: Date | B4: Payee | C4: Amount
A5: 44561 | B5: Farrell Fritz | C5: 9480
A6: 44408 | B6: Ross Rizley | C6: 1100
C8: =SUM(C5:C7) -> 10580
A10: 44798 | B10: Farrell Fritz | C10: 11414 | E10: 44726 | F10: Jay Gelbein | G10: 9000
A11: 44706 | B11: Sharon Hairston | C11: 1920 | E11: 44754 | F11: Jay Gelbein | G11: 4000
A12: 44741 | B12: Sharon Hairston | C12: 2560 | E12: 44764 | F12: Jay Gelbein | G12: 4000
A13: 44771 | B13: Sharon Hairston | C13: 1920 | E13: 44797 | F13: Jay Gelbein | G13: 4000
A14: 44811 | B14: Sharon Hairston | C14: 3200 | E14: 44826 | F14: Jay Gelbein | G14: 4000
A15: 44837 | B15: Sharon Hairston | C15: 1920 | E15: 44859 | F15: Jay Gelbein | G15: 4000
A16: 44861 | B16: Sharon Hairston | C16: 2560 | E16: 44883 | F16: Jay Gelbein | G16: 4000
A17: 44896 | B17: Sharon Hairston | C17: 1920 | E17: 44900 | F17: Jay Gelbein | G17: 4000
A18: 44914 | B18: Sharon Hairston | C18: 640
C20: =SUM(C10:C19) -> 28054 | G20: =SUM(G10:G19) -> 37000
A22: 44951 | B22: Sharon Hairston | C22: 1920 | E22: 44938 | F22: Jay Gelbein | G22: 9000
A23: 44980 | B23: Sharon Hairston | C23: 2560 | E23: 44971 | F23: Jay Gelbein | G23: 4000
A24: 45015 | B24: Sharon Hairston | C24: 2560 | E24: 44998 | F24: Jay Gelbein | G24: 4000
A25: 45042 | B25: Sharon Hairston | C25: 2560 | E25: 45027 | F25: Jay Gelbein | G25: 4000
A26: 45077 | B26: Sharon Hairston | C26: 2560 | E26: 45055 | F26: Jay Gelbein | G26: 4000
A27: 45093 | B27: Sharon Hairston | C27: 1280 | E27: 45083 | F27: Jay Gelbein | G27: 4000
A28: 45127 | B28: Sharon Hairston | C28: 640 | E28: 45124 | F28: Jay Gelbein | G28: 4000
A29: 45140 | B29: Sharon Hairston | C29: 640 | E29: 45162 | F29: Jay Gelbein | G29: 4000
A30: 45167 | B30: Sharon Hairston | C30: 640 | E30: 45183 | F30: Jay Gelbein | G30: 4000
A31: 45189 | B31: Sharon Hairston | C31: 640 | E31: 45211 | F31: Jay Gelbein | G31: 4000
A32: 45244 | B32: Farrell Fritz | C32: 12358
A33: 45291 | B33: Farrell Fritz | C33: 2930
C35: =SUM(C22:C34) -> 31288 | G35: =SUM(G22:G34) -> 45000
A37: 45421 | B37: Randstad | C37: 10400
A38: 45497 | B38: Randstad | C38: 17680
A39: 45523 | B39: Randstad | C39: 10400
A40: 45590 | B40: JG Lawyer | C40: 2500
A41: 45657 | B41: Farrell Fritz | C41: 7039
A42: 45657 | B42: Farrell Fritz | C42: 5861
C44: =SUM(C37:C43) -> 53880
A46: 45716 | B46: A Abramotwitz | C46: 5955
A47: 45747 | B47: A Abramotwitz | C47: 6975
A48: 45856 | B48: A Abramotwitz | C48: 14493
A49: 45890 | B49: CM Law | C49: 1283
A50: 45868 | B50: PY Acctg svces | C50: 7500
A51: 45874 | B51: PY Acctg svces | C51: 16236
A52: 45884 | B52: PY Acctg svces | C52: 5861
A53: 45887 | B53: PY Acctg svces | C53: 8339
A54: 45898 | B54: S Guzman | C54: 19760
C56: =SUM(C46:C54) -> 86402

Sheet 2021 IS
A1: Account | B1: Description | C1: Current Period | D1: Current Period | E1: Variance | F1: Current YTD | G1: YTD | H1: Variance
D2: Last Year | G2: Last Year
B3: REVENUES
A4: 00-5110 | B4: -Product Sales | C4: 0 | D4: 0 | E4: 0 | F4: 0 | G4: 0 | H4: 0
A5: 00-5110-000 | B5: -Product Sales | C5: 1125166.1 | D5: 1092810.7 | E5: 32355.45 | F5: 6435117.2 | G5: 9491342.2 | H5: -3056224.9
A6: 00-5120-000 | B6: -Customer Returns | C6: 0 | D6: 0 | E6: 0 | F6: 0 | G6: -12600 | H6: 12600
A7: 00-5130 | B7: -Customer Credits & Discounts | C7: 0 | D7: 0 | E7: 0 | F7: 0 | G7: 0 | H7: 0
A8: 00-5130-000 | B8: -Customer Credits & Discounts | C8: 6300 | D8: -0.58 | E8: 6300.58 | F8: -5.7 | G8: 1030.56 | H8: -1036.26
A9: 00-5190-000 | B9: -Other Customer Charges | C9: 675 | D9: 2150 | E9: -1475 | F9: 4473.12 | G9: 9567.66 | H9: -5094.54
A10: 00-5510-000 | B10: -Engineering Services | C10: 0 | D10: 0 | E10: 0 | F10: 0 | G10: 0 | H10: 0
A11: -5130 | B11: -Customer Credits & Discounts | C11: 0 | D11: 0 | E11: 0 | F11: 0 | G11: 0 | H11: 0
B12: Total Revenues | C12: 1132141.1 | D12: 1094960.1 | E12: 37181.03 | F12: 6439584.7 | G12: 9489340.4 | H12: -3049755.7
B13: .
B14: COST OF GOODS SOLD
A15: 00-6110-000 | B15: -Material - Product Sales | C15: 189511.51 | D15: 140609.27 | E15: 48902.24 | F15: 718236.62 | G15: 922018.07 | H15: -203781.45
A16: 00-6120-000 | B16: -Labor - Product Sales | C16: 29407.01 | D16: 38794.3 | E16: -9387.29 | F16: 258832.28 | G16: 360065.31 | H16: -101233.03
A17: 00-6130-000 | B17: -Overhead - Product Sales | C17: 44154.87 | D17: 48296.26 | E17: -4141.39 | F17: 389969.4 | G17: 538794.14 | H17: -148824.74
A18: 00-6140-000 | B18: -Outside Services - Product Sales | C18: 13578.35 | D18: 18919.22 | E18: -5340.87 | F18: 100914.86 | G18: 141172.95 | H18: -40258.09
A19: 00-6145-000 | B19: -Non-Recurring Engineering Costs | C19: 0 | D19: 0 | E19: 0 | F19: 0 | G19: 0 | H19: 0
A20: 00-6150-000 | B20: -Cost of Returns | C20: -356.64 | D20: -632.68 | E20: 276.04 | F20: -4234.42 | G20: -11735.79 | H20: 7501.37
A21: 00-6160-000 | B21: -MFG Variance | C21: 42577.59 | D21: 674.15 | E21: 41903.44 | F21: 60556.48 | G21: 44044.61 | H21: 16511.87
A22: 00-6190-000 | B22: -DMR - COGS | C22: 3004.8 | D22: 78.65 | E22: 2926.15 | F22: 7268.77 | G22: 3529.55 | H22: 3739.22
A23: 00-7610-000 | B23: Travel & Lodging | C23: 0 | D23: 0 | E23: 0 | F23: 24 | G23: 513.13 | H23: -489.13
A24: 00-7620-000 | B24: Meals & Entertainment | C24: 92.21 | D24: 0 | E24: 92.21 | F24: 92.21 | G24: 1000 | H24: -907.79
A25: 00-7010-000 | B25: -Applied Direct Labor | C25: -38068.43 | D25: -25973.03 | E25: -12095.4 | F25: -331068.86 | G25: -378003.67 | H25: 46934.81
A26: 00-7050-000 | B26: -Applied Factory Overhead | C26: -48486.57 | D26: -36831.34 | E26: -11655.23 | F26: -449332.59 | G26: -532342.94 | H26: 83010.35
... A79: 00-7960-000 | B79: -Depreciation & Amortization | C79: 4958.33 | D79: -18657.66 | E79: 23615.99 | F79: 59498.98 | G79: 35884 | H79: 23614.98
B80: Total Cost of Goods Sold | C80: 587932.29 | D80: 450823.18 | E80: 137109.11 | F80: 3953655.4 | G80: 4268109.7 | H80: -314454.33
B81: .
B82: OPERATING INCOME | C82: 544208.86 | D82: 644136.94 | E82: -99928.08 | F82: 2485929.3 | G82: 5221230.7 | H82: -2735301.4
B83: .
B84: SALES & MARKETING
A85: 00-8110-000 | B85: -Salaries Sales Dept | C85: 0 | D85: 0 | E85: 0 | F85: 0 | G85: 0 | H85: 0
A86: 00-8110-010 | B86: -Salaries Sales Dept | C86: 39107.34 | D86: 40073.27 | E86: -965.93 | F86: 444439.27 | G86: 439104.05 | H86: 5335.22
A87: 00-8210-000 | B87: -Medical Insurance | C87: 0 | D87: 0 | E87: 0 | F87: 0 | G87: 0 | H87: 0
A88: 00-8210-020 | B88: -Medical Insurance | C88: 3651.78 | D88: -1899.36 | E88: 5551.14 | F88: 41433.92 | G88: 30982.96 | H88: 10450.96
A89: 00-8220-000 | B89: -Payroll Taxes | C89: 0 | D89: 0 | E89: 0 | F89: 0 | G89: 0 | H89: 0
A90: 00-8220-020 | B90: -Payroll Taxes | C90: 0 | D90: 0 | E90: 0 | F90: 0 | G90: 0 | H90: 0
A91: 00-8220-030 | B91: -Payroll Taxes | C91: 1499.54 | D91: 2068 | E91: -568.46 | F91: 27586.4 | G91: 26710.15 | H91: 876.25
A92: 00-8310-000 | B92: -Travel & Lodging | C92: 2201.79 | D92: 0 | E92: 2201.79 | F92: 38269.63 | G92: 19785.29 | H92: 18484.34
A93: 00-8310-020 | B93: -Travel & Lodging | C93: 0 | D93: 0 | E93: 0 | F93: 0 | G93: 0 | H93: 0
A94: 00-8320-000 | B94: -Meals & Entertainment | C94: 0 | D94: 0 | E94: 0 | F94: 5507.4 | G94: 1486.42 | H94: 4020.98
A95: 00-8320-030 | B95: -Meals & Entertainment | C95: 0 | D95: 0 | E95: 0 | F95: 0 | G95: 0 | H95: 0
A96: 00-8410 | B96: -Advertising | C96: 0 | D96: 0 | E96: 0 | F96: 0 | G96: 0 | H96: 0
... A109: -8540 | B109: -Customer Charges & Fees | C109: 0 | D109: 0 | E109: 0 | F109: 0 | G109: 0 | H109: 0
B110: Total Sales & Marketing | C110: 68679.94 | D110: 120837.8 | E110: -52157.86 | F110: 666709.28 | G110: 668005.45 | H110: -1296.17
B111: .
B112: GENERAL & ADMINISTRATIVE
A113: 00-9110-000 | B113: -Salaries Officers | C113: 0 | D113: 0 | E113: 0 | F113: 0 | G113: 0 | H113: 0
A114: 00-9110-010 | B114: -Salaries Officers | C114: 31846.15 | D114: 32307.69 | E114: -461.54 | F114: 355769.22 | G114: 352692.35 | H114: 3076.87
A115: 00-9120-000 | B115: -Salaries Office Staff | C115: 0 | D115: 0 | E115: 0 | F115: 0 | G115: 0 | H115: 0
A116: 00-9120-010 | B116: -Salaries Office Staff | C116: 30458.94 | D116: 33951.43 | E116: -3492.49 | F116: 383959 | G116: 433109.65 | H116: -49150.65
A117: 00-9130-000 | B117: -Directors Fees | C117: 0 | D117: 0 | E117: 0 | F117: 0 | G117: 0 | H117: 0
A118: 00-9130-010 | B118: -Directors Fees | C118: 15923.11 | D118: 16615.41 | E118: -692.3 | F118: 180692.66 | G118: 181384.96 | H118: -692.3
A119: 00-9210-000 | B119: -Medical Insurance | C119: 0 | D119: 0 | E119: 0 | F119: 0 | G119: 0 | H119: 0
A120: 00-9210-010 | B120: -Medical Insurance | C120: 0 | D120: 0 | E120: 0 | F120: 0 | G120: 0 | H120: 0
A121: 00-9210-020 | B121: -Medical Insurance | C121: 1839.01 | D121: 1701.57 | E121: 137.44 | F121: 39974.26 | G121: 25986 | H121: 13988.26
A122: 00-9220-000 | B122: -Payroll Taxes | C122: 0 | D122: 0 | E122: 0 | F122: 0 | G122: 0 | H122: 0
A123: 00-9220-030 | B123: -Payroll Taxes | C123: 4777.61 | D123: 4167.28 | E123: 610.33 | F123: 65842.6 | G123: 65982.99 | H123: -140.39
A124: 00-9230-000 | B124: -Payroll Costs | C124: 1775.48 | D124: 1150.93 | E124: 624.55 | F124: 16704.73 | G124: 13809.79 | H124: 2894.94
... A161: -9310 | B161: -Travel & Lodging | C161: 0 | D161: 0 | E161: 0 | F161: 0 | G161: 0 | H161: 0
B162: Total General & Admin | C162: 435086.73 | D162: 270346.5 | E162: 164740.23 | F162: 1740053.7 | G162: 1654575.3 | H162: 85478.39
B163: .
B164: OTHER INCOME / EXPENSE
A165: 00-7810-000 | B165: -Purchase Price Variance | C165: 0 | D165: 1.72 | E165: -1.72 | F165: 66.17 | G165: 292 | H165: -225.83
A166: 00-7820-000 | B166: -A/P Discounts | C166: 541.39 | D166: 1140.71 | E166: -599.32 | F166: 12237.54 | G166: 5058.88 | H166: 7178.66
A167: 00-9910-000 | B167: -Interest Income | C167: 0.96 | D167: 0.19 | E167: 0.77 | F167: 1.84 | G167: 987.66 | H167: -985.82
A168: 00-9912-000 | B168: -Interest Expense | C168: 0 | D168: 0 | E168: 0 | F168: 0 | G168: 0 | H168: 0
A169: 00-9915-000 | B169: Investment Income | C169: 5872.84 | D169: 5501.65 | E169: 371.19 | F169: 23926.14 | G169: 27040.94 | H169: -3114.8
A170: 00-9920-000 | B170: -Other Income / Expense | C170: 0 | D170: 0 | E170: 0 | F170: 0 | G170: 0 | H170: 0
A171: 00-9925-000 | B171: Realized Gain (Loss) Investments-- | C171: 0 | D171: 68223.21 | E171: -68223.21 | F171: 0 | G171: 68042.19 | H171: -68042.19
A172: 00-9935-000 | B172: -SBA Grant Funds | C172: 0 | D172: 0 | E172: 0 | F172: 0 | G172: 10000 | H172: -10000
A173: 00-9936-000 | B173: -FFCRA - Payroll Reimbusement | C173: 0 | D173: 32736.3 | E173: -32736.3 | F173: 4611.41 | G173: 32736.3 | H173: -28124.89
A174: 00-9937-000 | B174: -PPP Funds | C174: 0 | D174: 0 | E174: 0 | F174: 0 | G174: 0 | H174: 0
A175: 00-9940-000 | B175: -Gain (loss) on disposal of asset | C175: 0 | D175: 0 | E175: 0 | F175: 0 | G175: 0 | H175: 0
A176: 00-9999-000 | B176: -Expense - Suspense | C176: 38.3 | D176: 1227.32 | E176: -1189.02 | F176: 0 | G176: 0 | H176: 0
B177: Total Other Income (Exp) | C177: 6453.49 | D177: 108831.1 | E177: -102377.61 | F177: 40843.1 | G177: 144157.97 | H177: -103314.87
B178: .
B179: NET INCOME BEFORE TAXES | C179: 46895.68 | D179: 361783.74 | E179: -314888.06 | F179: 120009.37 | G179: 3042807.8 | H179: -2922798.5
B180: .
B181: TAXES PAID
A182: 00-9990-000 | B182: -Corporate Taxes - Federal | C182: 0 | D182: 0 | E182: 0 | F182: 0 | G182: 0 | H182: 0
A183: 00-9993-000 | B183: Corporate Taxes - NYC | C183: 0 | D183: 0 | E183: 0 | F183: 0 | G183: 0 | H183: 0
A184: 00-9995-000 | B184: -Corporate Taxes - State | C184: 0 | D184: 0 | E184: 0 | F184: 25 | G184: 25 | H184: 0
B185: Total Taxes Paid | C185: 0 | D185: 0 | E185: 0 | F185: 25 | G185: 25 | H185: 0
B186: .
B187: NET PROFIT (LOSS) | C187: 46895.68 | D187: 361783.74 | E187: -314888.06 | F187: 119984.37 | G187: 3042782.8 | H187: -2922798.5

Sheet 2022 IS
A1: Account | B1: Description | C1: Current Period | D1: Current Period | E1: Variance | F1: Current YTD | G1: YTD | H1: Variance
D2: Last Year | G2: Last Year
B3: REVENUES
A4: 00-5110 | B4: -Product Sales | C4: 0 | D4: 0 | E4: 0 | F4: 0 | G4: 0 | H4: 0
A5: 00-5110-000 | B5: -Product Sales | C5: 515796.36 | D5: 1125166.1 | E5: -609369.79 | F5: 9119442.9 | G5: 6435117.2 | H5: 2684325.6
A6: 00-5120-000 | B6: -Customer Returns | C6: 0 | D6: 0 | E6: 0 | F6: -2493 | G6: 0 | H6: -2493
A7: 00-5130 | B7: -Customer Credits & Discounts | C7: 0 | D7: 0 | E7: 0 | F7: 0 | G7: 0 | H7: 0
A8: 00-5130-000 | B8: -Customer Credits & Discounts | C8: 0 | D8: 6300 | E8: -6300 | F8: 0 | G8: -5.7 | H8: 5.7
A9: 00-5190-000 | B9: -Other Customer Charges | C9: 510 | D9: 675 | E9: -165 | F9: 4845 | G9: 4473.12 | H9: 371.88
A10: 00-5510-000 | B10: -Engineering Services | C10: 0 | D10: 0 | E10: 0 | F10: 0 | G10: 0 | H10: 0
A11: -5130 | B11: -Customer Credits & Discounts | C11: 0 | D11: 0 | E11: 0 | F11: 0 | G11: 0 | H11: 0
B12: Total Revenues | C12: 516306.36 | D12: 1132141.1 | E12: -615834.79 | F12: 9121794.9 | G12: 6439584.7 | H12: 2682210.2
B13: .
B14: COST OF GOODS SOLD
A15: 00-6110-000 | B15: -Material - Product Sales | C15: 439243.06 | D15: 189511.51 | E15: 249731.55 | F15: 1228571.7 | G15: 718236.62 | H15: 510335.09
A16: 00-6120-000 | B16: -Labor - Product Sales | C16: 30516.8 | D16: 29407.01 | E16: 1109.79 | F16: 393804.13 | G16: 258832.28 | H16: 134971.85
A17: 00-6130-000 | B17: -Overhead - Product Sales | C17: 45772.59 | D17: 44154.87 | E17: 1617.72 | F17: 592796.68 | G17: 389969.4 | H17: 202827.28
A18: 00-6140-000 | B18: -Outside Services - Product Sales | C18: 6833.06 | D18: 13578.35 | E18: -6745.29 | F18: 126329.18 | G18: 100914.86 | H18: 25414.32
A19: 00-6145-000 | B19: -Non-Recurring Engineering Costs | C19: 0 | D19: 0 | E19: 0 | F19: 0 | G19: 0 | H19: 0
A20: 00-6150-000 | B20: -Cost of Returns | C20: -777.09 | D20: -356.64 | E20: -420.45 | F20: -21117.57 | G20: -4234.42 | H20: -16883.15
A21: 00-6160-000 | B21: -MFG Variance | C21: -232.1 | D21: 42577.59 | E21: -42809.69 | F21: 41613.85 | G21: 60556.48 | H21: -18942.63
A22: 00-6190-000 | B22: -DMR - COGS | C22: 1902.39 | D22: 3004.8 | E22: -1102.41 | F22: 11957.31 | G22: 7268.77 | H22: 4688.54
A23: 00-7610-000 | B23: Travel & Lodging | C23: 0 | D23: 0 | E23: 0 | F23: 3958.38 | G23: 24 | H23: 3934.38
A24: 00-7620-000 | B24: Meals & Entertainment | C24: 0 | D24: 92.21 | E24: -92.21 | F24: 0 | G24: 92.21 | H24: -92.21
A25: 00-7010-000 | B25: -Applied Direct Labor | C25: -15951.04 | D25: -38068.43 | E25: 22117.39 | F25: -359500.48 | G25: -331068.86 | H25: -28431.62
A26: 00-7050-000 | B26: -Applied Factory Overhead | C26: -23859.17 | D26: -48486.57 | E26: 24627.4 | F26: -508443.17 | G26: -449332.59 | H26: -59110.58
... A79: 00-7960-000 | B79: -Depreciation & Amortization | C79: 12292.44 | D79: 4958.33 | E79: 7334.11 | F79: 66834.07 | G79: 59498.98 | H79: 7335.09
B80: Total Cost of Goods Sold | C80: 775502.4 | D80: 587932.29 | E80: 187570.11 | F80: 4901995.2 | G80: 3953655.4 | H80: 948339.79
B81: .
B82: OPERATING INCOME | C82: -259196.04 | D82: 544208.86 | E82: -803404.9 | F82: 4219799.7 | G82: 2485929.3 | H82: 1733870.4
B83: .
B84: SALES & MARKETING
A85: 00-8110-000 | B85: -Salaries Sales Dept | C85: 0 | D85: 0 | E85: 0 | F85: 0 | G85: 0 | H85: 0
A86: 00-8110-010 | B86: -Salaries Sales Dept | C86: 86562.94 | D86: 39107.34 | E86: 47455.6 | F86: 489254.32 | G86: 444439.27 | H86: 44815.05
A87: 00-8210-000 | B87: -Medical Insurance | C87: 0 | D87: 0 | E87: 0 | F87: 0 | G87: 0 | H87: 0
A88: 00-8210-020 | B88: -Medical Insurance | C88: 2518.4 | D88: 3651.78 | E88: -1133.38 | F88: 37528.67 | G88: 41433.92 | H88: -3905.25
A89: 00-8220-000 | B89: -Payroll Taxes | C89: 0 | D89: 0 | E89: 0 | F89: 0 | G89: 0 | H89: 0
A90: 00-8220-020 | B90: -Payroll Taxes | C90: 0 | D90: 0 | E90: 0 | F90: 0 | G90: 0 | H90: 0
A91: 00-8220-030 | B91: -Payroll Taxes | C91: 3308.5 | D91: 1499.54 | E91: 1808.96 | F91: 28185.24 | G91: 27586.4 | H91: 598.84
A92: 00-8310-000 | B92: -Travel & Lodging | C92: 2133.89 | D92: 2201.79 | E92: -67.9 | F92: 61655.97 | G92: 38269.63 | H92: 23386.34
A93: 00-8310-020 | B93: -Travel & Lodging | C93: 0 | D93: 0 | E93: 0 | F93: 0 | G93: 0 | H93: 0
A94: 00-8320-000 | B94: -Meals & Entertainment | C94: 0 | D94: 0 | E94: 0 | F94: 2223.05 | G94: 5507.4 | H94: -3284.35
A95: 00-8320-030 | B95: -Meals & Entertainment | C95: 0 | D95: 0 | E95: 0 | F95: 0 | G95: 0 | H95: 0
A96: 00-8410 | B96: -Advertising | C96: 0 | D96: 0 | E96: 0 | F96: 0 | G96: 0 | H96: 0
... A109: -8540 | B109: -Customer Charges & Fees | C109: 0 | D109: 0 | E109: 0 | F109: 0 | G109: 0 | H109: 0
B110: Total Sales & Marketing | C110: 129424.19 | D110: 68679.94 | E110: 60744.25 | F110: 931166.63 | G110: 666709.28 | H110: 264457.35
B111: .
B112: GENERAL & ADMINISTRATIVE
A113: 00-9110-000 | B113: -Salaries Officers | C113: 0 | D113: 0 | E113: 0 | F113: 0 | G113: 0 | H113: 0
A114: 00-9110-010 | B114: -Salaries Officers | C114: 31375.39 | D114: 31846.15 | E114: -470.76 | F114: 364361.49 | G114: 355769.22 | H114: 8592.27
A115: 00-9120-000 | B115: -Salaries Office Staff | C115: 0 | D115: 0 | E115: 0 | F115: 0 | G115: 0 | H115: 0
A116: 00-9120-010 | B116: -Salaries Office Staff | C116: 32168.24 | D116: 30458.94 | E116: 1709.3 | F116: 344191.96 | G116: 383959 | H116: -39767.04
A117: 00-9130-000 | B117: -Directors Fees | C117: 0 | D117: 0 | E117: 0 | F117: 0 | G117: 0 | H117: 0
A118: 00-9130-010 | B118: -Directors Fees | C118: 15230.8 | D118: 15923.11 | E118: -692.31 | F118: 180000.34 | G118: 180692.66 | H118: -692.32
A119: 00-9210-000 | B119: -Medical Insurance | C119: 0 | D119: 0 | E119: 0 | F119: 3.99 | G119: 0 | H119: 3.99
A120: 00-9210-010 | B120: -Medical Insurance | C120: 0 | D120: 0 | E120: 0 | F120: 0 | G120: 0 | H120: 0
A121: 00-9210-020 | B121: -Medical Insurance | C121: 2795.63 | D121: 1839.01 | E121: 956.62 | F121: 28599.98 | G121: 39974.26 | H121: -11374.28
A122: 00-9220-000 | B122: -Payroll Taxes | C122: 0 | D122: 0 | E122: 0 | F122: 0 | G122: 0 | H122: 0
A123: 00-9220-030 | B123: -Payroll Taxes | C123: 5736.93 | D123: 4777.61 | E123: 959.32 | F123: 64657.08 | G123: 65842.6 | H123: -1185.52
A124: 00-9230-000 | B124: -Payroll Costs | C124: 2158.77 | D124: 1775.48 | E124: 383.29 | F124: 16517.39 | G124: 16704.73 | H124: -187.34
... A161: -9310 | B161: -Travel & Lodging | C161: 0 | D161: 0 | E161: 0 | F161: 0 | G161: 0 | H161: 0
B162: Total General & Admin | C162: 375548.63 | D162: 435086.73 | E162: -59538.1 | F162: 1679677.8 | G162: 1740053.7 | H162: -60375.89
B163: .
B164: OTHER INCOME / EXPENSE
A165: 00-7810-000 | B165: -Purchase Price Variance | C165: -65.9 | D165: 0 | E165: -65.9 | F165: -213.02 | G165: 66.17 | H165: -279.19
A166: 00-7820-000 | B166: -A/P Discounts | C166: 450.12 | D166: 541.39 | E166: -91.27 | F166: 12674.97 | G166: 12237.54 | H166: 437.43
A167: 00-9910-000 | B167: -Interest Income | C167: 0 | D167: 0.96 | E167: -0.96 | F167: 35.93 | G167: 1.84 | H167: 34.09
A168: 00-9912-000 | B168: -Interest Expense | C168: -135.64 | D168: 0 | E168: -135.64 | F168: -135.64 | G168: 0 | H168: -135.64
A169: 00-9915-000 | B169: Investment Income | C169: 3448.65 | D169: 5872.84 | E169: -2424.19 | F169: 19565.51 | G169: 23926.14 | H169: -4360.63
A170: 00-9920-000 | B170: -Other Income / Expense | C170: 0 | D170: 0 | E170: 0 | F170: 7 | G170: 0 | H170: 7
A171: 00-9925-000 | B171: Realized Gain (Loss) Investments-- | C171: 0 | D171: 0 | E171: 0 | F171: 92359.85 | G171: 0 | H171: 92359.85
A172: 00-9935-000 | B172: -SBA Grant Funds | C172: 0 | D172: 0 | E172: 0 | F172: 0 | G172: 0 | H172: 0
A173: 00-9936-000 | B173: -FFCRA - Payroll Reimbusement | C173: 0 | D173: 0 | E173: 0 | F173: 0 | G173: 4611.41 | H173: -4611.41
A174: 00-9937-000 | B174: -PPP Funds | C174: 0 | D174: 0 | E174: 0 | F174: 0 | G174: 0 | H174: 0
A175: 00-9940-000 | B175: -Gain (loss) on disposal of asset | C175: 0 | D175: 0 | E175: 0 | F175: 0 | G175: 0 | H175: 0
A176: 00-9999-000 | B176: -Expense - Suspense | C176: 8746.18 | D176: 38.3 | E176: 8707.88 | F176: 0 | G176: 0 | H176: 0
B177: Total Other Income (Exp) | C177: 12443.41 | D177: 6453.49 | E177: 5989.92 | F177: 124294.6 | G177: 40843.1 | H177: 83451.5
B178: .
B179: NET INCOME BEFORE TAXES | C179: -751725.45 | D179: 46895.68 | E179: -798621.13 | F179: 1733249.8 | G179: 120009.37 | H179: 1613240.4
B180: .
B181: TAXES PAID
A182: 00-9990-000 | B182: -Corporate Taxes - Federal | C182: 0 | D182: 0 | E182: 0 | F182: 0 | G182: 0 | H182: 0
A183: 00-9993-000 | B183: Corporate Taxes - NYC | C183: 0 | D183: 0 | E183: 0 | F183: 0 | G183: 0 | H183: 0
A184: 00-9995-000 | B184: -Corporate Taxes - State | C184: 166364.31 | D184: 0 | E184: 166364.31 | F184: 177114.31 | G184: 25 | H184: 177089.31
B185: Total Taxes Paid | C185: 166364.31 | D185: 0 | E185: 166364.31 | F185: 177114.31 | G185: 25 | H185: 177089.31
B186: .
B187: NET PROFIT (LOSS) | C187: -918089.76 | D187: 46895.68 | E187: -964985.44 | F187: 1556135.5 | G187: 119984.37 | H187: 1436151.1

Sheet 2023 IS
A1: Account | B1: Description | C1: Current Period | D1: Current Period | E1: Variance | F1: Current YTD | G1: YTD | H1: Variance
D2: Last Year | G2: Last Year
B3: REVENUES
A4: 00-5110 | B4: -Product Sales | C4: 0 | D4: 0 | E4: 0 | F4: 0 | G4: 0 | H4: 0
A5: 00-5110-000 | B5: -Product Sales | C5: 1245336.4 | D5: 515796.36 | E5: 729540.04 | F5: 7883831.6 | G5: 9119442.9 | H5: -1235611.2
A6: 00-5120-000 | B6: -Customer Returns | C6: 0 | D6: 0 | E6: 0 | F6: 0 | G6: -2493 | H6: 2493
A7: 00-5130 | B7: -Customer Credits & Discounts | C7: 0 | D7: 0 | E7: 0 | F7: 0 | G7: 0 | H7: 0
A8: 00-5130-000 | B8: -Customer Credits & Discounts | C8: -0.71 | D8: 0 | E8: -0.71 | F8: 2653.95 | G8: 0 | H8: 2653.95
A9: 00-5190-000 | B9: -Other Customer Charges | C9: 5500 | D9: 510 | E9: 4990 | F9: 13042.89 | G9: 4845 | H9: 8197.89
A10: 00-5510-000 | B10: -Engineering Services | C10: 0 | D10: 0 | E10: 0 | F10: 0 | G10: 0 | H10: 0
A11: -5130 | B11: -Customer Credits & Discounts | C11: 0 | D11: 0 | E11: 0 | F11: 0 | G11: 0 | H11: 0
B12: Total Revenues | C12: 1250835.7 | D12: 516306.36 | E12: 734529.33 | F12: 7899528.5 | G12: 9121794.9 | H12: -1222266.4
B13: .
B14: COST OF GOODS SOLD
A15: 00-6110-000 | B15: -Material - Product Sales | C15: 76639.33 | D15: 439243.06 | E15: -362603.73 | F15: 679907.15 | G15: 1228571.7 | H15: -548664.56
A16: 00-6120-000 | B16: -Labor - Product Sales | C16: 52120.78 | D16: 30516.8 | E16: 21603.98 | F16: 315197.93 | G16: 393804.13 | H16: -78606.2
A17: 00-6130-000 | B17: -Overhead - Product Sales | C17: 78436.09 | D17: 45772.59 | E17: 32663.5 | F17: 473199.62 | G17: 592796.68 | H17: -119597.06
A18: 00-6140-000 | B18: -Outside Services - Product Sales | C18: 22493.41 | D18: 6833.06 | E18: 15660.35 | F18: 127658.9 | G18: 126329.18 | H18: 1329.72
A19: 00-6145-000 | B19: -Non-Recurring Engineering Costs | C19: 0 | D19: 0 | E19: 0 | F19: 0 | G19: 0 | H19: 0
A20: 00-6150-000 | B20: -Cost of Returns | C20: 0 | D20: -777.09 | E20: 777.09 | F20: -1925.91 | G20: -21117.57 | H20: 19191.66
A21: 00-6160-000 | B21: -MFG Variance | C21: 1416.88 | D21: -232.1 | E21: 1648.98 | F21: 42933.69 | G21: 41613.85 | H21: 1319.84
A22: 00-6190-000 | B22: -DMR - COGS | C22: 5414.97 | D22: 1902.39 | E22: 3512.58 | F22: 4497.29 | G22: 11957.31 | H22: -7460.02
A23: 00-7610-000 | B23: Travel & Lodging | C23: 0 | D23: 0 | E23: 0 | F23: 705.8 | G23: 3958.38 | H23: -3252.58
A24: 00-7620-000 | B24: Meals & Entertainment | C24: 0 | D24: 0 | E24: 0 | F24: 0 | G24: 0 | H24: 0
A25: 00-7010-000 | B25: -Applied Direct Labor | C25: -18648.88 | D25: -15951.04 | E25: -2697.84 | F25: -338380.1 | G25: -359500.48 | H25: 21120.38
A26: 00-7050-000 | B26: -Applied Factory Overhead | C26: -28008.39 | D26: -23859.17 | E26: -4149.22 | F26: -507058.11 | G26: -508443.17 | H26: 1385.06
... A79: 00-7960-000 | B79: -Depreciation & Amortization | C79: 42385.13 | D79: 12292.44 | E79: 30092.69 | F79: 154697.4 | G79: 66834.07 | H79: 87863.33
B80: Total Cost of Goods Sold | C80: 474640.83 | D80: 775502.4 | E80: -300861.57 | F80: 4306089.7 | G80: 4901995.2 | H80: -595905.47
B81: .
B82: OPERATING INCOME | C82: 776194.86 | D82: -259196.04 | E82: 1035390.9 | F82: 3593438.7 | G82: 4219799.7 | H82: -626360.94
B83: .
B84: SALES & MARKETING
A85: 00-8110-000 | B85: -Salaries Sales Dept | C85: 0 | D85: 0 | E85: 0 | F85: 0 | G85: 0 | H85: 0
A86: 00-8110-010 | B86: -Salaries Sales Dept | C86: 42369.2 | D86: 86562.94 | E86: -44193.74 | F86: 505055.52 | G86: 489254.32 | H86: 15801.2
A87: 00-8210-000 | B87: -Medical Insurance | C87: 0 | D87: 0 | E87: 0 | F87: 0 | G87: 0 | H87: 0
A88: 00-8210-020 | B88: -Medical Insurance | C88: 2659.04 | D88: 2518.4 | E88: 140.64 | F88: 30002.58 | G88: 37528.67 | H88: -7526.09
A89: 00-8220-000 | B89: -Payroll Taxes | C89: 0 | D89: 0 | E89: 0 | F89: 0 | G89: 0 | H89: 0
A90: 00-8220-020 | B90: -Payroll Taxes | C90: 0 | D90: 0 | E90: 0 | F90: 0 | G90: 0 | H90: 0
A91: 00-8220-030 | B91: -Payroll Taxes | C91: 1475.38 | D91: 3308.5 | E91: -1833.12 | F91: 27354.73 | G91: 28185.24 | H91: -830.51
A92: 00-8310-000 | B92: -Travel & Lodging | C92: 8225.6 | D92: 2133.89 | E92: 6091.71 | F92: 59438.03 | G92: 61655.97 | H92: -2217.94
A93: 00-8310-020 | B93: -Travel & Lodging | C93: 0 | D93: 0 | E93: 0 | F93: 0 | G93: 0 | H93: 0
A94: 00-8320-000 | B94: -Meals & Entertainment | C94: 0 | D94: 0 | E94: 0 | F94: 336 | G94: 2223.05 | H94: -1887.05
A95: 00-8320-030 | B95: -Meals & Entertainment | C95: 0 | D95: 0 | E95: 0 | F95: 0 | G95: 0 | H95: 0
A96: 00-8410 | B96: -Advertising | C96: 0 | D96: 0 | E96: 0 | F96: 0 | G96: 0 | H96: 0
... A109: -8540 | B109: -Customer Charges & Fees | C109: 0 | D109: 0 | E109: 0 | F109: 0 | G109: 0 | H109: 0
B110: Total Sales & Marketing | C110: 53946.19 | D110: 129424.19 | E110: -75478 | F110: 841502.2 | G110: 931166.63 | H110: -89664.43
B111: .
B112: GENERAL & ADMINISTRATIVE
A113: 00-9110-000 | B113: -Salaries Officers | C113: 0 | D113: 0 | E113: 0 | F113: 0 | G113: 0 | H113: 0
A114: 00-9110-010 | B114: -Salaries Officers | C114: 9615.4 | D114: 31375.39 | E114: -21759.99 | F114: 310653.95 | G114: 364361.49 | H114: -53707.54
A115: 00-9120-000 | B115: -Salaries Office Staff | C115: 0 | D115: 0 | E115: 0 | F115: 0 | G115: 0 | H115: 0
A116: 00-9120-010 | B116: -Salaries Office Staff | C116: 30782.53 | D116: 32168.24 | E116: -1385.71 | F116: 376966.94 | G116: 344191.96 | H116: 32774.98
A117: 00-9130-000 | B117: -Directors Fees | C117: 0 | D117: 0 | E117: 0 | F117: 0 | G117: 0 | H117: 0
A118: 00-9130-010 | B118: -Directors Fees | C118: 19384.64 | D118: 15230.8 | E118: 4153.84 | F118: 216538.76 | G118: 180000.34 | H118: 36538.42
A119: 00-9210-000 | B119: -Medical Insurance | C119: 0 | D119: 0 | E119: 0 | F119: 0 | G119: 3.99 | H119: -3.99
A120: 00-9210-010 | B120: -Medical Insurance | C120: 0 | D120: 0 | E120: 0 | F120: 0 | G120: 0 | H120: 0
A121: 00-9210-020 | B121: -Medical Insurance | C121: 0 | D121: 2795.63 | E121: -2795.63 | F121: 22720.54 | G121: 28599.98 | H121: -5879.44
A122: 00-9220-000 | B122: -Payroll Taxes | C122: 0 | D122: 0 | E122: 0 | F122: 0 | G122: 0 | H122: 0
A123: 00-9220-030 | B123: -Payroll Taxes | C123: 4758.16 | D123: 5736.93 | E123: -978.77 | F123: 68673.72 | G123: 64657.08 | H123: 4016.64
A124: 00-9230-000 | B124: -Payroll Costs | C124: 2058.55 | D124: 2158.77 | E124: -100.22 | F124: 18730.22 | G124: 16517.39 | H124: 2212.83
... A161: -9310 | B161: -Travel & Lodging | C161: 0 | D161: 0 | E161: 0 | F161: 0 | G161: 0 | H161: 0
B162: Total General & Admin | C162: 366422.62 | D162: 375548.63 | E162: -9126.01 | F162: 1727577.8 | G162: 1679677.8 | H162: 47900.01
B163: .
B164: OTHER INCOME / EXPENSE
A165: 00-7810-000 | B165: -Purchase Price Variance | C165: 19.87 | D165: -65.9 | E165: 85.77 | F165: -0.38 | G165: -213.02 | H165: 212.64
A166: 00-7820-000 | B166: -A/P Discounts | C166: 389.24 | D166: 450.12 | E166: -60.88 | F166: 6403.54 | G166: 12674.97 | H166: -6271.43
A167: 00-9910-000 | B167: -Interest Income | C167: 0 | D167: 0 | E167: 0 | F167: 0 | G167: 35.93 | H167: -35.93
A168: 00-9912-000 | B168: -Interest Expense | C168: -3878.91 | D168: -135.64 | E168: -3743.27 | F168: -13668.09 | G168: -135.64 | H168: -13532.45
A169: 00-9915-000 | B169: Investment Income | C169: 3801.01 | D169: 3448.65 | E169: 352.36 | F169: 14523.47 | G169: 19565.51 | H169: -5042.04
A170: 00-9920-000 | B170: -Other Income / Expense | C170: 0 | D170: 0 | E170: 0 | F170: 0 | G170: 7 | H170: -7
A171: 00-9925-000 | B171: Realized Gain (Loss) Investments-- | C171: 0 | D171: 0 | E171: 0 | F171: 0 | G171: 92359.85 | H171: -92359.85
A172: 00-9935-000 | B172: -SBA Grant Funds | C172: 0 | D172: 0 | E172: 0 | F172: 0 | G172: 0 | H172: 0
A173: 00-9936-000 | B173: -FFCRA - Payroll Reimbusement | C173: 0 | D173: 0 | E173: 0 | F173: 0 | G173: 0 | H173: 0
A174: 00-9937-000 | B174: -PPP Funds | C174: 0 | D174: 0 | E174: 0 | F174: 0 | G174: 0 | H174: 0
A175: 00-9940-000 | B175: -Gain (loss) on disposal of asset | C175: 0 | D175: 0 | E175: 0 | F175: 0 | G175: 0 | H175: 0
A176: 00-9999-000 | B176: -Expense - Suspense | C176: 0 | D176: 8746.18 | E176: -8746.18 | F176: 0 | G176: 0 | H176: 0
B177: Total Other Income (Exp) | C177: 331.21 | D177: 12443.41 | E177: -12112.2 | F177: 7258.54 | G177: 124294.6 | H177: -117036.06
B178: .
B179: NET INCOME BEFORE TAXES | C179: 356157.26 | D179: -751725.45 | E179: 1107882.7 | F179: 1031617.2 | G179: 1733249.8 | H179: -701632.58
B180: .
B181: TAXES PAID
A182: 00-9990-000 | B182: -Corporate Taxes - Federal | C182: 0 | D182: 0 | E182: 0 | F182: 0 | G182: 0 | H182: 0
A183: 00-9993-000 | B183: Corporate Taxes - NYC | C183: 0 | D183: 0 | E183: 0 | F183: 0 | G183: 0 | H183: 0
A184: 00-9995-000 | B184: -Corporate Taxes - State | C184: 26209.75 | D184: 166364.31 | E184: -140154.56 | F184: 30766.59 | G184: 177114.31 | H184: -146347.72
B185: Total Taxes Paid | C185: 26209.75 | D185: 166364.31 | E185: -140154.56 | F185: 30766.59 | G185: 177114.31 | H185: -146347.72
B186: .
B187: NET PROFIT (LOSS) | C187: 329947.51 | D187: -918089.76 | E187: 1248037.3 | F187: 1000850.6 | G187: 1556135.5 | H187: -555284.86

Sheet 2024 IS
A1: Account | B1: Description | C1: Current Period | D1: Current Period | E1: Variance | F1: Current YTD | G1: YTD | H1: Variance
D2: Last Year | G2: Last Year
B3: REVENUES
A4: 00-5110 | B4: -Product Sales | C4: 0 | D4: 0 | E4: 0 | F4: 0 | G4: 0 | H4: 0
A5: 00-5110-000 | B5: -Product Sales | C5: 937459.54 | D5: 1245336.4 | E5: -307876.86 | F5: 6241831.4 | G5: 7883831.6 | H5: -1642000.2
A6: 00-5120-000 | B6: -Customer Returns | C6: 0 | D6: 0 | E6: 0 | F6: 0 | G6: 0 | H6: 0
A7: 00-5130 | B7: -Customer Credits & Discounts | C7: 0 | D7: 0 | E7: 0 | F7: 0 | G7: 0 | H7: 0
A8: 00-5130-000 | B8: -Customer Credits & Discounts | C8: -102 | D8: -0.71 | E8: -101.29 | F8: -951.59 | G8: 2653.95 | H8: -3605.54
A9: 00-5190-000 | B9: -Other Customer Charges | C9: 2300 | D9: 5500 | E9: -3200 | F9: 24408 | G9: 13042.89 | H9: 11365.11
A10: 00-5510-000 | B10: -Engineering Services | C10: 364232 | D10: 0 | E10: 364232 | F10: 662042 | G10: 0 | H10: 662042
A11: -5130 | B11: -Customer Credits & Discounts | C11: 0 | D11: 0 | E11: 0 | F11: 0 | G11: 0 | H11: 0
B12: Total Revenues | C12: 1303889.5 | D12: 1250835.7 | E12: 53053.85 | F12: 6927329.8 | G12: 7899528.5 | H12: -972198.66
B13: .
B14: COST OF GOODS SOLD
A15: 00-6110-000 | B15: -Material - Product Sales | C15: -209294.31 | D15: 76639.33 | E15: -285933.64 | F15: 329002.48 | G15: 679907.15 | H15: -350904.67
A16: 00-6120-000 | B16: -Labor - Product Sales | C16: 29716.65 | D16: 52120.78 | E16: -22404.13 | F16: 262033.83 | G16: 315197.93 | H16: -53164.1
A17: 00-6130-000 | B17: -Overhead - Product Sales | C17: 44657.41 | D17: 78436.09 | E17: -33778.68 | F17: 393475.86 | G17: 473199.62 | H17: -79723.76
A18: 00-6140-000 | B18: -Outside Services - Product Sales | C18: 9512.15 | D18: 22493.41 | E18: -12981.26 | F18: 160421.85 | G18: 127658.9 | H18: 32762.95
A19: 00-6145-000 | B19: -Non-Recurring Engineering Costs | C19: 40776 | D19: 0 | E19: 40776 | F19: 139158.5 | G19: 0 | H19: 139158.5
A20: 00-6150-000 | B20: -Cost of Returns | C20: 0 | D20: 0 | E20: 0 | F20: -17692.96 | G20: -1925.91 | H20: -15767.05
A21: 00-6160-000 | B21: -MFG Variance | C21: 670.34 | D21: 1416.88 | E21: -746.54 | F21: 13968.14 | G21: 42933.69 | H21: -28965.55
A22: 00-6190-000 | B22: -DMR - COGS | C22: 3894.66 | D22: 5414.97 | E22: -1520.31 | F22: 8702.5 | G22: 4497.29 | H22: 4205.21
A23: 00-7610-000 | B23: Travel & Lodging | C23: 2790.63 | D23: 0 | E23: 2790.63 | F23: 20052.65 | G23: 705.8 | H23: 19346.85
A24: 00-7620-000 | B24: Meals & Entertainment | C24: 393.78 | D24: 0 | E24: 393.78 | F24: 2257.29 | G24: 0 | H24: 2257.29
A25: 00-7010-000 | B25: -Applied Direct Labor | C25: -30009.32 | D25: -18648.88 | E25: -11360.44 | F25: -275881.93 | G25: -338380.1 | H25: 62498.17
A26: 00-7050-000 | B26: -Applied Factory Overhead | C26: -74821.41 | D26: -28008.39 | E26: -46813.02 | F26: -442512.01 | G26: -507058.11 | H26: 64546.1
... A79: 00-7960-000 | B79: -Depreciation & Amortization | C79: 93020.6 | D79: 42385.13 | E79: 50635.47 | F79: 114510.3 | G79: 154697.4 | H79: -40187.1
B80: Total Cost of Goods Sold | C80: 218540.96 | D80: 474640.83 | E80: -256099.87 | F80: 4300426.6 | G80: 4306089.7 | H80: -5663.08
B81: .
B82: OPERATING INCOME | C82: 1085348.6 | D82: 776194.86 | E82: 309153.72 | F82: 2626903.1 | G82: 3593438.7 | H82: -966535.58
B83: .
B84: SALES & MARKETING
A85: 00-8110-000 | B85: -Salaries Sales Dept | C85: 0 | D85: 0 | E85: 0 | F85: 0 | G85: 0 | H85: 0
A86: 00-8110-010 | B86: -Salaries Sales Dept | C86: 52290.43 | D86: 42369.2 | E86: 9921.23 | F86: 585032.77 | G86: 505055.52 | H86: 79977.25
A87: 00-8210-000 | B87: -Medical Insurance | C87: 0 | D87: 0 | E87: 0 | F87: 0 | G87: 0 | H87: 0
A88: 00-8210-020 | B88: -Medical Insurance | C88: 3274.49 | D88: 2659.04 | E88: 615.45 | F88: 34406.51 | G88: 30002.58 | H88: 4403.93
A89: 00-8220-000 | B89: -Payroll Taxes | C89: 0 | D89: 0 | E89: 0 | F89: 0 | G89: 0 | H89: 0
A90: 00-8220-020 | B90: -Payroll Taxes | C90: 0 | D90: 0 | E90: 0 | F90: 0 | G90: 0 | H90: 0
A91: 00-8220-030 | B91: -Payroll Taxes | C91: 2119.06 | D91: 1475.38 | E91: 643.68 | F91: 32633.11 | G91: 27354.73 | H91: 5278.38
A92: 00-8310-000 | B92: -Travel & Lodging | C92: 6767.14 | D92: 8225.6 | E92: -1458.46 | F92: 101762.31 | G92: 59438.03 | H92: 42324.28
A93: 00-8310-020 | B93: -Travel & Lodging | C93: 0 | D93: 0 | E93: 0 | F93: 0 | G93: 0 | H93: 0
A94: 00-8320-000 | B94: -Meals & Entertainment | C94: 2272.99 | D94: 0 | E94: 2272.99 | F94: 14658.64 | G94: 336 | H94: 14322.64
A95: 00-8320-030 | B95: -Meals & Entertainment | C95: 0 | D95: 0 | E95: 0 | F95: 0 | G95: 0 | H95: 0
A96: 00-8410 | B96: -Advertising | C96: 0 | D96: 0 | E96: 0 | F96: 0 | G96: 0 | H96: 0
... A109: -8540 | B109: -Customer Charges & Fees | C109: 0 | D109: 0 | E109: 0 | F109: 0 | G109: 0 | H109: 0
B110: Total Sales & Marketing | C110: 86558.26 | D110: 53946.19 | E110: 32612.07 | F110: 959761.62 | G110: 841502.2 | H110: 118259.42
B111: .
B112: GENERAL & ADMINISTRATIVE
A113: 00-9110-000 | B113: -Salaries Officers | C113: 0 | D113: 0 | E113: 0 | F113: 0 | G113: 0 | H113: 0
A114: 00-9110-010 | B114: -Salaries Officers | C114: 8884.63 | D114: 9615.4 | E114: -730.77 | F114: 108788.65 | G114: 310653.95 | H114: -201865.3
A115: 00-9120-000 | B115: -Salaries Office Staff | C115: 0 | D115: 0 | E115: 0 | F115: 0 | G115: 0 | H115: 0
A116: 00-9120-010 | B116: -Salaries Office Staff | C116: 32835.83 | D116: 30782.53 | E116: 2053.3 | F116: 422371.01 | G116: 376966.94 | H116: 45404.07
A117: 00-9130-000 | B117: -Directors Fees | C117: 0 | D117: 0 | E117: 0 | F117: 0 | G117: 0 | H117: 0
A118: 00-9130-010 | B118: -Directors Fees | C118: 20307.71 | D118: 19384.64 | E118: 923.07 | F118: 241846.42 | G118: 216538.76 | H118: 25307.66
A119: 00-9210-000 | B119: -Medical Insurance | C119: 0 | D119: 0 | E119: 0 | F119: 0 | G119: 0 | H119: 0
A120: 00-9210-010 | B120: -Medical Insurance | C120: 0 | D120: 0 | E120: 0 | F120: 0 | G120: 0 | H120: 0
A121: 00-9210-020 | B121: -Medical Insurance | C121: 0 | D121: 0 | E121: 0 | F121: 0 | G121: 22720.54 | H121: -22720.54
A122: 00-9220-000 | B122: -Payroll Taxes | C122: 0 | D122: 0 | E122: 0 | F122: 0 | G122: 0 | H122: 0
A123: 00-9220-030 | B123: -Payroll Taxes | C123: 4859.59 | D123: 4758.16 | E123: 101.43 | F123: 66457.18 | G123: 68673.72 | H123: -2216.54
A124: 00-9230-000 | B124: -Payroll Costs | C124: 1264.1 | D124: 2058.55 | E124: -794.45 | F124: 19198.18 | G124: 18730.22 | H124: 467.96
... A161: -9310 | B161: -Travel & Lodging | C161: 0 | D161: 0 | E161: 0 | F161: 0 | G161: 0 | H161: 0
B162: Total General & Admin | C162: 226985.16 | D162: 366422.62 | E162: -139437.46 | F162: 1350921.6 | G162: 1727577.8 | H162: -376656.22
B163: .
B164: OTHER INCOME / EXPENSE
A165: 00-7810-000 | B165: -Purchase Price Variance | C165: 0 | D165: 19.87 | E165: -19.87 | F165: -442.09 | G165: -0.38 | H165: -441.71
A166: 00-7820-000 | B166: -A/P Discounts | C166: 995.38 | D166: 389.24 | E166: 606.14 | F166: 8545.66 | G166: 6403.54 | H166: 2142.12
A167: 00-9910-000 | B167: -Interest Income | C167: 0.72 | D167: 0 | E167: 0.72 | F167: 2.22 | G167: 0 | H167: 2.22
A168: 00-9912-000 | B168: -Interest Expense | C168: -240.56 | D168: -3878.91 | E168: 3638.35 | F168: -5890.66 | G168: -13668.09 | H168: 7777.43
A169: 00-9915-000 | B169: Investment Income | C169: 4698.91 | D169: 3801.01 | E169: 897.9 | F169: 17677.45 | G169: 14523.47 | H169: 3153.98
A170: 00-9920-000 | B170: -Other Income / Expense | C170: 0 | D170: 0 | E170: 0 | F170: 0 | G170: 0 | H170: 0
A171: 00-9925-000 | B171: Realized Gain (Loss) Investments-- | C171: 0 | D171: 0 | E171: 0 | F171: 0 | G171: 0 | H171: 0
A172: 00-9935-000 | B172: -SBA Grant Funds | C172: 0 | D172: 0 | E172: 0 | F172: 0 | G172: 0 | H172: 0
A173: 00-9936-000 | B173: -FFCRA - Payroll Reimbusement | C173: 0 | D173: 0 | E173: 0 | F173: 0 | G173: 0 | H173: 0
A174: 00-9937-000 | B174: -PPP Funds | C174: 0 | D174: 0 | E174: 0 | F174: 0 | G174: 0 | H174: 0
A175: 00-9940-000 | B175: -Gain (loss) on disposal of asset | C175: -35311.14 | D175: 0 | E175: -35311.14 | F175: -35311.14 | G175: 0 | H175: -35311.14
A176: 00-9999-000 | B176: -Expense - Suspense | C176: 0 | D176: 0 | E176: 0 | F176: 598.5 | G176: 0 | H176: 598.5
B177: Total Other Income (Exp) | C177: -29856.69 | D177: 331.21 | E177: -30187.9 | F177: -14820.06 | G177: 7258.54 | H177: -22078.6
B178: .
B179: NET INCOME BEFORE TAXES | C179: 741948.47 | D179: 356157.26 | E179: 385791.21 | F179: 301399.85 | G179: 1031617.2 | H179: -730217.38
B180: .
B181: TAXES PAID
A182: 00-9990-000 | B182: -Corporate Taxes - Federal | C182: 0 | D182: 0 | E182: 0 | F182: 0 | G182: 0 | H182: 0
A183: 00-9993-000 | B183: Corporate Taxes - NYC | C183: 0 | D183: 0 | E183: 0 | F183: 0 | G183: 0 | H183: 0
A184: 00-9995-000 | B184: -Corporate Taxes - State | C184: 6209.75 | D184: 26209.75 | E184: -20000 | F184: 80165.38 | G184: 30766.59 | H184: 49398.79
B185: Total Taxes Paid | C185: 6209.75 | D185: 26209.75 | E185: -20000 | F185: 80165.38 | G185: 30766.59 | H185: 49398.79
B186: .
B187: NET PROFIT (LOSS) | C187: 735738.72 | D187: 329947.51 | E187: 405791.21 | F187: 221234.47 | G187: 1000850.6 | H187: -779616.17

Sheet 2025 IS
A1: Account | B1: Description | C1: Current Period | D1: Current Period | E1: Variance | F1: Current YTD | G1: YTD | H1: Variance
D2: Last Year | G2: Last Year
B3: REVENUES
A4: 00-5110 | B4: -Product Sales | C4: 0 | D4: 0 | E4: 0 | F4: 0 | G4: 0 | H4: 0
A5: 00-5110-000 | B5: -Product Sales | C5: 392663.3 | D5: 264560 | E5: 128103.3 | F5: 4619436.6 | G5: 4025282.1 | H5: 594154.56
A6: 00-5120-000 | B6: -Customer Returns | C6: 0 | D6: 0 | E6: 0 | F6: -21666 | G6: 0 | H6: -21666
A7: 00-5130 | B7: -Customer Credits & Discounts | C7: 0 | D7: 0 | E7: 0 | F7: 0 | G7: 0 | H7: 0
A8: 00-5130-000 | B8: -Customer Credits & Discounts | C8: 0 | D8: 0 | E8: 0 | F8: -0.02 | G8: -849.59 | H8: 849.57
A9: 00-5190-000 | B9: -Other Customer Charges | C9: 300 | D9: 0 | E9: 300 | F9: 5793.03 | G9: 19308 | H9: -13514.97
A10: 00-5510-000 | B10: -Engineering Services | C10: 0 | D10: 0 | E10: 0 | F10: 352087.8 | G10: 243810 | H10: 108277.8
A11: -5130 | B11: -Customer Credits & Discounts | C11: 0 | D11: 0 | E11: 0 | F11: 0 | G11: 0 | H11: 0
B12: Total Revenues | C12: 392963.3 | D12: 264560 | E12: 128403.3 | F12: 4955651.4 | G12: 4287550.5 | H12: 668100.96
B13: .
B14: COST OF GOODS SOLD
A15: 00-6110-000 | B15: -Material - Product Sales | C15: 44925.16 | D15: 19998.9 | E15: 24926.26 | F15: 538021.34 | G15: 401146.97 | H15: 136874.37
A16: 00-6120-000 | B16: -Labor - Product Sales | C16: 35372.67 | D16: 10588.17 | E16: 24784.5 | F16: 318975.76 | G16: 199557.05 | H16: 119418.71
A17: 00-6130-000 | B17: -Overhead - Product Sales | C17: 126933.91 | D17: 15890.88 | E17: 111043.03 | F17: 913615.09 | G17: 299579.04 | H17: 614036.05
A18: 00-6140-000 | B18: -Outside Services - Product Sales | C18: 16237.04 | D18: 7414 | E18: 8823.04 | F18: 154013.3 | G18: 111039.47 | H18: 42973.83
A19: 00-6145-000 | B19: -Non-Recurring Engineering Costs | C19: 0 | D19: 0 | E19: 0 | F19: 124570 | G19: 0 | H19: 124570
A20: 00-6150-000 | B20: -Cost of Returns | C20: -411.5 | D20: -16028.43 | E20: 15616.93 | F20: -8052.03 | G20: -17692.96 | H20: 9640.93
A21: 00-6160-000 | B21: -MFG Variance | C21: 22291.02 | D21: 0 | E21: 22291.02 | F21: 265501.26 | G21: 11872.07 | H21: 253629.19
A22: 00-6190-000 | B22: -DMR - COGS | C22: 1708.76 | D22: 691.95 | E22: 1016.81 | F22: 4694.03 | G22: 947.69 | H22: 3746.34
A23: 00-7610-000 | B23: Travel & Lodging | C23: 2830.61 | D23: 1800.83 | E23: 1029.78 | F23: 7772.34 | G23: 12501.9 | H23: -4729.56
A24: 00-7620-000 | B24: Meals & Entertainment | C24: 298.75 | D24: 415.8 | E24: -117.05 | F24: 873.21 | G24: 1863.51 | H24: -990.3
A25: 00-7010-000 | B25: -Applied Direct Labor | C25: -57527.86 | D25: -16040.61 | E25: -41487.25 | F25: -434287.18 | G25: -205030.21 | H25: -229256.97
A26: 00-7050-000 | B26: -Applied Factory Overhead | C26: -197704.17 | D26: -23221.73 | E26: -174482.44 | F26: -1360310.2 | G26: -304081.93 | H26: -1056228.3
... A79: 00-7960-000 | B79: -Depreciation & Amortization | C79: 0 | D79: 11475 | E79: -11475 | F79: 17000 | G79: 103275 | H79: -86275
B80: Total Cost of Goods Sold | C80: 308356.24 | D80: 323670.26 | E80: -15314.02 | F80: 3310089.7 | G80: 3372346.5 | H80: -62256.79
B81: .
B82: OPERATING INCOME | C82: 84607.06 | D82: -59110.26 | E82: 143717.32 | F82: 1645561.7 | G82: 915203.94 | H82: 730357.75
B83: .
B84: SALES & MARKETING
A85: 00-8110-000 | B85: -Salaries Sales Dept | C85: 0 | D85: 0 | E85: 0 | F85: 0 | G85: 0 | H85: 0
A86: 00-8110-010 | B86: -Salaries Sales Dept | C86: 43677.74 | D86: 44534.23 | E86: -856.49 | F86: 397001.36 | G86: 427778.5 | H86: -30777.14
A87: 00-8210-000 | B87: -Medical Insurance | C87: 0 | D87: 0 | E87: 0 | F87: 0 | G87: 0 | H87: 0
A88: 00-8210-020 | B88: -Medical Insurance | C88: 8135.74 | D88: 3274.49 | E88: 4861.25 | F88: 40156.73 | G88: 25133.04 | H88: 15023.69
A89: 00-8220-000 | B89: -Payroll Taxes | C89: 0 | D89: 0 | E89: 0 | F89: 0 | G89: 0 | H89: 0
A90: 00-8220-020 | B90: -Payroll Taxes | C90: 0 | D90: 0 | E90: 0 | F90: 0 | G90: 0 | H90: 0
A91: 00-8220-030 | B91: -Payroll Taxes | C91: 1298.82 | D91: 1550.57 | E91: -251.75 | F91: 24850.96 | G91: 26074.07 | H91: -1223.11
A92: 00-8310-000 | B92: -Travel & Lodging | C92: 20636.54 | D92: 7674.06 | E92: 12962.48 | F92: 95899.04 | G92: 74732.46 | H92: 21166.58
A93: 00-8310-020 | B93: -Travel & Lodging | C93: 0 | D93: 0 | E93: 0 | F93: 0 | G93: 0 | H93: 0
A94: 00-8320-000 | B94: -Meals & Entertainment | C94: 1752.67 | D94: 1100.59 | E94: 652.08 | F94: 12667.78 | G94: 9617.48 | H94: 3050.3
A95: 00-8320-030 | B95: -Meals & Entertainment | C95: 0 | D95: 0 | E95: 0 | F95: 0 | G95: 0 | H95: 0
A96: 00-8410 | B96: -Advertising | C96: 0 | D96: 0 | E96: 0 | F96: 0 | G96: 0 | H96: 0
... A109: -8540 | B109: -Customer Charges & Fees | C109: 0 | D109: 0 | E109: 0 | F109: 0 | G109: 0 | H109: 0
B110: Total Sales & Marketing | C110: 82563.36 | D110: 71089.7 | E110: 11473.66 | F110: 656402.62 | G110: 703633.16 | H110: -47230.54
B111: .
B112: GENERAL & ADMINISTRATIVE
A113: 00-9110-000 | B113: -Salaries Officers | C113: 0 | D113: 0 | E113: 0 | F113: 0 | G113: 0 | H113: 0
A114: 00-9110-010 | B114: -Salaries Officers | C114: 0 | D114: 8480.78 | E114: -8480.78 | F114: 0 | G114: 82134.75 | H114: -82134.75
A115: 00-9120-000 | B115: -Salaries Office Staff | C115: 0 | D115: 0 | E115: 0 | F115: 0 | G115: 0 | H115: 0
A116: 00-9120-010 | B116: -Salaries Office Staff | C116: 41596.21 | D116: 31337.21 | E116: 10259 | F116: 371072.69 | G116: 324064.14 | H116: 47008.55
A117: 00-9130-000 | B117: -Directors Fees | C117: 0 | D117: 0 | E117: 0 | F117: 0 | G117: 0 | H117: 0
A118: 00-9130-010 | B118: -Directors Fees | C118: 20307.71 | D118: 19384.63 | E118: 923.08 | F118: 178846.36 | G118: 180923.28 | H118: -2076.92
A119: 00-9210-000 | B119: -Medical Insurance | C119: 0 | D119: 0 | E119: 0 | F119: 0 | G119: 0 | H119: 0
A120: 00-9210-010 | B120: -Medical Insurance | C120: 0 | D120: 0 | E120: 0 | F120: 0 | G120: 0 | H120: 0
A121: 00-9210-020 | B121: -Medical Insurance | C121: 0 | D121: 0 | E121: 0 | F121: 0 | G121: 0 | H121: 0
A122: 00-9220-000 | B122: -Payroll Taxes | C122: 0 | D122: 0 | E122: 0 | F122: 0 | G122: 0 | H122: 0
A123: 00-9220-030 | B123: -Payroll Taxes | C123: 4844.35 | D123: 4612.18 | E123: 232.17 | F123: 47294.81 | G123: 51893.75 | H123: -4598.94
A124: 00-9230-000 | B124: -Payroll Costs | C124: 1582.87 | D124: 1515.29 | E124: 67.58 | F124: 13196.75 | G124: 14522.64 | H124: -1325.89
... A161: 00-8310-000 | B161: -Travel & Lodging | C161: 0 | D161: 0 | E161: 0 | F161: 0 | G161: 0 | H161: 0
A162: #N/A | B162: Total General & Admin | C162: 91491.92 | D162: 96911.5 | E162: -5419.58 | F162: 991175.71 | G162: 956259.68 | H162: 34916.03
A163: #N/A | B163: .
A164: #N/A | B164: OTHER INCOME / EXPENSE
A165: 00-7810-000 | B165: -Purchase Price Variance | C165: -259.85 | D165: -28.6 | E165: -231.25 | F165: -810.24 | G165: -374.29 | H165: -435.95
A166: 00-7820-000 | B166: -A/P Discounts | C166: 1096.6 | D166: 531.32 | E166: 565.28 | F166: 4141.48 | G166: 6144.47 | H166: -2002.99
A167: 00-9910-000 | B167: -Interest Income | C167: 0.02 | D167: 0.11 | E167: -0.09 | F167: 227.25 | G167: 1.32 | H167: 225.93
A168: 00-9912-000 | B168: -Interest Expense | C168: -724.46 | D168: -371.21 | E168: -353.25 | F168: -9986.25 | G168: -5173.68 | H168: -4812.57
A169: 00-9915-000 | B169: Investment Income | C169: 7147.64 | D169: 3661.41 | E169: 3486.23 | F169: 41956.47 | G169: 11859.01 | H169: 30097.46
A170: 00-9920-000 | B170: -Other Income / Expense | C170: 0 | D170: 0 | E170: 0 | F170: 0 | G170: 0 | H170: 0
A171: 00-9925-000 | B171: Realized Gain (Loss) Investments-- | C171: 0 | D171: 0 | E171: 0 | F171: 88475.08 | G171: 0 | H171: 88475.08
A172: 00-9935-000 | B172: -SBA Grant Funds | C172: 0 | D172: 0 | E172: 0 | F172: 0 | G172: 0 | H172: 0
A173: 00-9936-000 | B173: -FFCRA - Payroll Reimbusement | C173: 0 | D173: 0 | E173: 0 | F173: 0 | G173: 0 | H173: 0
A174: 00-9937-000 | B174: -PPP Funds | C174: 0 | D174: 0 | E174: 0 | F174: 0 | G174: 0 | H174: 0
A175: 00-9940-000 | B175: -Gain (loss) on disposal of asset | C175: 0 | D175: 0 | E175: 0 | F175: 0 | G175: 0 | H175: 0
A176: 00-9999-000 | B176: -Expense - Suspense | C176: 0 | D176: 0 | E176: 0 | F176: 0 | G176: 0 | H176: 0
A177: #N/A | B177: Total Other Income (Exp) | C177: 7259.95 | D177: 3793.03 | E177: 3466.92 | F177: 124003.79 | G177: 12456.83 | H177: 111546.96
A178: #N/A | B178: .
A179: #N/A | B179: NET INCOME BEFORE TAXES | C179: -82188.27 | D179: -223318.43 | E179: 141130.16 | F179: 121987.15 | G179: -732232.07 | H179: 854219.22
A180: #N/A | B180: .
A181: #N/A | B181: TAXES PAID
A182: 00-9990-000 | B182: -Corporate Taxes - Federal | C182: 0 | D182: 0 | E182: 0 | F182: 0 | G182: 0 | H182: 0
A183: 00-9993-000 | B183: Corporate Taxes - NYC | C183: 0 | D183: 0 | E183: 0 | F183: 0 | G183: 0 | H183: 0
A184: 00-9995-000 | B184: -Corporate Taxes - State | C184: 0 | D184: 20000 | E184: -20000 | F184: 0 | G184: 73955.63 | H184: -73955.63
A185: #N/A | B185: Total Taxes Paid | C185: 0 | D185: 20000 | E185: -20000 | F185: 0 | G185: 73955.63 | H185: -73955.63
A186: #N/A | B186: .
A187: #N/A | B187: NET PROFIT (LOSS) | C187: -82188.27 | D187: -243318.43 | E187: 161130.16 | F187: 121987.15 | G187: -806187.7 | H187: 928174.85
A188: 00-7535-000
A189: 00-7540-000
A190: 00-7545-000
A191: 00-7550-000
A192: 00-7555-000
A193: 00-7560-000
A194: 00-7565-000
A195: 00-7570-000
A196: 00-7910-000
A197: 00-7920-000
A198: 00-7930-000
A199: 00-7930-020
... A307: 00-9995-000

Sheet 2022 BS
A1: Account | B1: Description | C1: Current Year | D1: Last Year | E1: Variance | F1: Var %
B2: ASSETS
B3: CASH IN BANKS
A4: 00-1110-000 | B4: -Chase - Checking | C4: 2210695.4 | D4: 968363.21 | E4: 1242332.2 | F4: 128.29196
A5: 00-1111-000 | B5: -Chase - Payroll | C5: 185561.08 | D5: 223606.31 | E5: -38045.23 | F5: -17.014381
A6: 00-1112-000 | B6: -Chase - AR Payments | C6: 2000 | D6: 6738.44 | E6: -4738.44 | F6: -70.31954
A7: 00-1190-000 | B7: Petty Cash | C7: 500 | D7: 500 | E7: 0 | F7: 0
B8: Total Cash in Banks | C8: 2398756.5 | D8: 1199208 | E8: 1199548.5 | F8: 100.0284
B9: INVESTMENTS & SECURITIES
A10: 00-1140-000 | B10: -Morgan Stanley | C10: 405784.26 | D10: 579372.3 | E10: -173588.04 | F10: -29.961398
A11: 00-1150-000 | B11: Charles Scwab | C11: 0 | D11: 5785.03 | E11: -5785.03 | F11: -100
B12: Total Investments | C12: 405784.26 | D12: 585157.33 | E12: -179373.07 | F12: -30.653819
B13: ACCOUNTS RECEIVABLE
A14: 00-1125-000 | B14: -Allowance for Doubtful Accounts | C14: -15130.57 | D14: -15130.57 | E14: 0 | F14: 0
A15: 00-1126-000 | B15: -Customer Deposits | C15: -18599.3 | D15: -24542.41 | E15: 5943.11 | F15: 24.215674
A16: 00-1210-000 | B16: -Accounts Receivable | C16: 525775.94 | D16: 1105726.3 | E16: -579950.37 | F16: -52.449721
B17: Total Accounts Receivable | C17: 492046.07 | D17: 1066053.3 | E17: -574007.26 | F17: -53.844141
B18: INVENTORY
A19: 00-1310-000 | B19: -Raw Material | C19: 1444746.5 | D19: 1415642.8 | E19: 29103.74 | F19: 2.0558675
A20: 00-1320-000 | B20: -W I P | C20: 379024.97 | D20: 375815.92 | E20: 3209.05 | F20: 0.85388879
A21: 00-1330-000 | B21: -Finished Goods | C21: 94558.35 | D21: 289304.2 | E21: -194745.85 | F21: -67.315252
A22: 00-1340-000 | B22: -Inventory - Inspection | C22: 10288.17 | D22: 201 | E22: 10087.17 | F22: 5018.4925
A23: 00-1350-000 | B23: -Inventory - DMR Pending | C23: 7157.59 | D23: 621.11 | E23: 6536.48 | F23: 1052.3869
B24: Total Inventory | C24: 1935775.6 | D24: 2081585 | E24: -145809.41 | F24: -7.0047299
B25: PREPAID & OTHER ASSETS
A26: 00-1510-000 | B26: -Prepaid Insurance | C26: 32668.09 | D26: 36463.25 | E26: -3795.16 | F26: -10.408178
A27: 00-1530-000 | B27: -Prepaid RE Taxes | C27: 15831.96 | D27: 13995.05 | E27: 1836.91 | F27: 13.125426
A28: 00-1550-000 | B28: -Advances | C28: -1936.48 | D28: 2360.08 | E28: -4296.56 | F28: -182.05146
A29: 00-1560-000 | B29: -PPD - Trade Show Expenses | C29: 4550 | D29: 30809.98 | E29: -26259.98 | F29: -85.232058
B30: Total PPD & Other Assets | C30: 51113.57 | D30: 83628.36 | E30: -32514.79 | F30: -38.8801
B31: Total Current Assets | C31: 5283476 | D31: 5015632 | E31: 267843.97 | F31: 5.3401838
B32: PROPERTY, PLANT & EQUIPMENT
A33: 00-1410-000 | B33: -Land | C33: 122000 | D33: 122000 | E33: 0 | F33: 0
A34: 00-1420-000 | B34: -Building | C34: 1039840.7 | D34: 1039840.7 | E34: 0 | F34: 0
A35: 00-1430-000 | B35: -Leasehold Improvements | C35: 230619.89 | D35: 230619.89 | E35: 0 | F35: 0
A36: 00-1440-000 | B36: -Machinery & Equipment | C36: 2015708.6 | D36: 1849633.8 | E36: 166074.82 | F36: 8.9787948
A37: 00-1470-000 | B37: -Computer Software | C37: 96925.38 | D37: 96925.38 | E37: 0 | F37: 0
A38: 00-1480-000 | B38: -Automobiles | C38: 110411.14 | D38: 110411.14 | E38: 0 | F38: 0
A39: 00-1490-000 | B39: -Accumulated Depreciation | C39: -3221865.5 | D39: -3143237.1 | E39: -78628.32 | F39: -2.5015077
A40: 00-1495-000 | B40: -Accumulated Amortization | C40: -96925.38 | D40: -96925.38 | E40: 0 | F40: 0
B41: Total Prprty, Plant & Equip | C41: 296714.88 | D41: 209268.38 | E41: 87446.5 | F41: 41.786772
B42: TOTAL ASSETS | C42: 5580190.9 | D42: 5224900.4 | E42: 355290.47 | F42: 6.7999472
B43: LIABILITIES
B44: ACCOUNTS PAYABLE
A45: 00-2110-000 | B45: -Accounts Payable | C45: 163543.7 | D45: 38342.49 | E45: 125201.21 | F45: 326.53385
A46: 00-2115-000 | B46: AMEX Payable | C46: -10190.85 | D46: -1120.54 | E46: -9070.31 | F46: -809.45883
A47: 00-2116-000 | B47: -VISA Payable | C47: 0 | D47: -550 | E47: 550 | F47: 100
A48: 00-2120-000 | B48: -Accrued Purchase Receipts | C48: 45527.87 | D48: -2249.01 | E48: 47776.88 | F48: 2124.3516
B49: Total Accounts Payable | C49: 198880.72 | D49: 34422.94 | E49: 164457.78 | F49: 477.75635
B50: ACCRUED ACCTS PAYABLE
B51: ACCRUED WAGES & TAXES
B52: ACCRUED & OTHER LIABILITIES
A53: 00-2296-000 | B53: -Lease Payable - Pick and Place | C53: 126697.82 | D53: 0 | E53: 126697.82 | F53: 0
A54: 00-2297-000 | B54: -Lease Payable - Phone System | C54: 14833.24 | D54: 0 | E54: 14833.24 | F54: 0
A55: 00-2310-000 | B55: -Accrued Payroll & Taxes | C55: 95227.53 | D55: 70208.63 | E55: 25018.9 | F55: 35.635078
A56: 00-2340-000 | B56: -Accrued Expenses | C56: 22197.97 | D56: 0 | E56: 22197.97 | F56: 0
A57: 00-2350-000 | B57: -Accrued Profit Sharing | C57: 150000 | D57: 150000 | E57: 0 | F57: 0
B58: Total Accrued Liabilities | C58: 408956.56 | D58: 220208.63 | E58: 188747.93 | F58: 85.71323
B59: Total Current Liabilities | C59: 607837.28 | D59: 254631.57 | E59: 353205.71 | F59: 138.71246
B60: TOTAL LIABILITIES | C60: 607837.28 | D60: 254631.57 | E60: 353205.71 | F60: 138.71246
B61: EQUITY
A62: ='Detailed BS'!B47 -> 00-3300-000 | B62: Common Stock | C62: 165000 | D62: 165000 | E62: 0 | F62: 0
A63: ='Detailed BS'!B48 -> 00-3320-000 | B63: Tax Payments-Current Year | C63: -1181600 | D63: -871770 | E63: -309830 | F63: -35.540337
A64: ='Detailed BS'!B49 -> 00-3330-000 | B64: Distributions-Current Year | C64: -372450.74 | D64: -920332.57 | E64: 547881.83 | F64: 59.530853
A65: ='Detailed BS'!B50 -> 00-3340-000 | B65: Retained Earnings-Prior Years | C65: 20977735 | D65: 20857750 | E65: 119984.37 | F65: 0.57525077
A66: 00-3310-000 | B66: -Retained Earnings - Distributions | C66: -16172466 | D66: -14380363 | E66: 1792102.6 | F66: 12.462151
A67: 00-3350-000 | B67: Current Year - Profit ( Loss ) | C67: 1556135.5 | D67: 119984.37 | E67: 1436151.1 | F67: 1196.9485
B68: TOTAL EQUITY | C68: 4972353.6 | D68: 4970268.8 | E68: 2084.76 | F68: 0.041944613
B69: TOTAL LIABILITIES & EQUITY | C69: 5580190.9 | D69: 5224900.4 | E69: 355290.47 | F69: 6.7999472

Sheet 2023 BS
A1: Account | B1: Description | C1: Current Year | D1: Last Year | E1: Variance | F1: Var %
B2: ASSETS
B3: CASH IN BANKS
A4: 00-1110-000 | B4: -Chase - Checking | C4: 1598672.4 | D4: 2210695.4 | E4: -612022.98 | F4: -27.684636
A5: 00-1111-000 | B5: -Chase - Payroll | C5: 14095.12 | D5: 185561.08 | E5: -171465.96 | F5: -92.404054
A6: 00-1112-000 | B6: -Chase - AR Payments | C6: 2000 | D6: 2000 | E6: 0 | F6: 0
A7: 00-1190-000 | B7: Petty Cash | C7: 500 | D7: 500 | E7: 0 | F7: 0
B8: Total Cash in Banks | C8: 1615267.5 | D8: 2398756.5 | E8: -783488.94 | F8: -32.662296
B9: INVESTMENTS & SECURITIES
A10: 00-1140-000 | B10: -Morgan Stanley | C10: 420307.73 | D10: 405784.26 | E10: 14523.47 | F10: 3.5791112
B11: Total Investments | C11: 420307.73 | D11: 405784.26 | E11: 14523.47 | F11: 3.5791112
B12: ACCOUNTS RECEIVABLE
A13: 00-1125-000 | B13: -Allowance for Doubtful Accounts | C13: -15130.57 | D13: -15130.57 | E13: 0 | F13: 0
A14: 00-1126-000 | B14: -Customer Deposits | C14: -28159.91 | D14: -18599.3 | E14: -9560.61 | F14: -51.403064
A15: 00-1210-000 | B15: -Accounts Receivable | C15: 1262808.8 | D15: 525775.94 | E15: 737032.87 | F15: 140.18003
B16: Total Accounts Receivable | C16: 1219518.3 | D16: 492046.07 | E16: 727472.26 | F16: 147.84637
B17: INVENTORY
A18: 00-1310-000 | B18: -Raw Material | C18: 1624790.3 | D18: 1444746.5 | E18: 180043.79 | F18: 12.461964
A19: 00-1320-000 | B19: -W I P | C19: 323109.05 | D19: 379024.97 | E19: -55915.92 | F19: -14.752569
A20: 00-1330-000 | B20: -Finished Goods | C20: 147549.85 | D20: 94558.35 | E20: 52991.5 | F20: 56.041058
A21: 00-1340-000 | B21: -Inventory - Inspection | C21: 0 | D21: 10288.17 | E21: -10288.17 | F21: -100
A22: 00-1350-000 | B22: -Inventory - DMR Pending | C22: 6785.56 | D22: 7157.59 | E22: -372.03 | F22: -5.1976992
B23: Total Inventory | C23: 2102234.8 | D23: 1935775.6 | E23: 166459.17 | F23: 8.5990942
B24: PREPAID & OTHER ASSETS
A25: 00-1510-000 | B25: -Prepaid Insurance | C25: 24610.26 | D25: 32668.09 | E25: -8057.83 | F25: -24.665752
A26: 00-1530-000 | B26: -Prepaid RE Taxes | C26: 16324.17 | D26: 15831.96 | E26: 492.21 | F26: 3.1089644
A27: 00-1540-000 | B27: -Prepaid Other | C27: 40193.44 | D27: 0 | E27: 40193.44 | F27: 0
A28: 00-1550-000 | B28: -Advances | C28: -1651.05 | D28: -1936.48 | E28: 285.43 | F28: 14.739631
A29: 00-1560-000 | B29: -PPD - Trade Show Expenses | C29: 14902.33 | D29: 4550 | E29: 10352.33 | F29: 227.52374
B30: Total PPD & Other Assets | C30: 94379.15 | D30: 51113.57 | E30: 43265.58 | F30: 84.645976
B31: Total Current Assets | C31: 5451707.5 | D31: 5283476 | E31: 168231.54 | F31: 3.1841072
B32: PROPERTY, PLANT & EQUIPMENT
A33: 00-1410-000 | B33: -Land | C33: 122000 | D33: 122000 | E33: 0 | F33: 0
A34: 00-1420-000 | B34: -Building | C34: 1039840.7 | D34: 1039840.7 | E34: 0 | F34: 0
A35: 00-1430-000 | B35: -Leasehold Improvements | C35: 230619.89 | D35: 230619.89 | E35: 0 | F35: 0
A36: 00-1440-000 | B36: -Machinery & Equipment | C36: 2156400.1 | D36: 2015708.6 | E36: 140691.48 | F36: 6.979753
A37: 00-1470-000 | B37: -Computer Software | C37: 96925.38 | D37: 96925.38 | E37: 0 | F37: 0
A38: 00-1480-000 | B38: -Automobiles | C38: 110411.14 | D38: 110411.14 | E38: 0 | F38: 0
A39: 00-1490-000 | B39: -Accumulated Depreciation | C39: -3262811 | D39: -3221865.5 | E39: -40945.54 | F39: -1.2708644
A40: 00-1495-000 | B40: -Accumulated Amortization | C40: -96925.38 | D40: -96925.38 | E40: 0 | F40: 0
B41: Total Prprty, Plant & Equip | C41: 396460.82 | D41: 296714.88 | E41: 99745.94 | F41: 33.616764
B42: TOTAL ASSETS | C42: 5848168.3 | D42: 5580190.9 | E42: 267977.48 | F42: 4.8022995
B43: LIABILITIES
B44: ACCOUNTS PAYABLE
A45: 00-2110-000 | B45: -Accounts Payable | C45: 172939.26 | D45: 163543.7 | E45: 9395.56 | F45: 5.7449844
A46: 00-2115-000 | B46: AMEX Payable | C46: 0 | D46: -10190.85 | E46: 10190.85 | F46: 100
A47: 00-2120-000 | B47: -Accrued Purchase Receipts | C47: 3244.16 | D47: 45527.87 | E47: -42283.71 | F47: -92.874343
B48: Total Accounts Payable | C48: 176183.42 | D48: 198880.72 | E48: -22697.3 | F48: -11.412519
B49: ACCRUED ACCTS PAYABLE
B50: ACCRUED WAGES & TAXES
B51: ACCRUED & OTHER LIABILITIES
A52: 00-2295-000 | B52: -Lease Payable - Screen Printer | C52: 80822.44 | D52: 0 | E52: 80822.44 | F52: 0
A53: 00-2296-000 | B53: -Lease Payable - Pick and Place | C53: 85183.16 | D53: 126697.82 | E53: -41514.66 | F53: -32.766673
A54: 00-2297-000 | B54: -Lease Payable - Phone System | C54: 12417.99 | D54: 14833.24 | E54: -2415.25 | F54: -16.282687
A55: 00-2310-000 | B55: -Accrued Payroll & Taxes | C55: 75036.46 | D55: 95227.53 | E55: -20191.07 | F55: -21.202976
A56: 00-2340-000 | B56: -Accrued Expenses | C56: 38628.5 | D56: 22197.97 | E56: 16430.53 | F56: 74.018165
A57: 00-2350-000 | B57: -Accrued Profit Sharing | C57: 175000 | D57: 150000 | E57: 25000 | F57: 16.666667
B58: Total Accrued Liabilities | C58: 467088.55 | D58: 408956.56 | E58: 58131.99 | F58: 14.21471
B59: Total Current Liabilities | C59: 643271.97 | D59: 607837.28 | E59: 35434.69 | F59: 5.8296342
B60: TOTAL LIABILITIES | C60: 643271.97 | D60: 607837.28 | E60: 35434.69 | F60: 5.8296342
B61: EQUITY
A62: 00-3300-000 | B62: Common Stock | C62: 165000 | D62: 165000 | E62: 0 | F62: 0
A63: 00-3320-000 | B63: Tax Payments-Current Year | C63: -170000 | D63: -1181600 | E63: 1011600 | F63: 85.612729
A64: 00-3330-000 | B64: Distributions-Current Year | C64: -735247.85 | D64: -372450.74 | E64: -362797.11 | F64: -97.408079
A65: 00-3340-000 | B65: Retained Earnings-Prior Years | C65: 22533870 | D65: 20977735 | E65: 1556135.5 | F65: 7.418034
A66: 00-3310-000 | B66: -Retained Earnings - Distributions | C66: -17589577 | D66: -16172466 | E66: 1417110.7 | F66: 8.7624902
A67: 00-3350-000 | B67: Current Year - Profit ( Loss ) | C67: 1000850.6 | D67: 1556135.5 | E67: -555284.86 | F67: -35.68358
B68: TOTAL EQUITY | C68: 5204896.4 | D68: 4972353.6 | E68: 232542.79 | F68: 4.6767147
B69: TOTAL LIABILITIES & EQUITY | C69: 5848168.3 | D69: 5580190.9 | E69: 267977.48 | F69: 4.8022995

Sheet 2024 BS
A1: Account | B1: Description | C1: Current Year | D1: Last Year | E1: Variance | F1: Var %
B2: ASSETS
B3: CASH IN BANKS
A4: 00-1110-000 | B4: -Chase - Checking | C4: 533754.04 | D4: 1598672.4 | E4: -1064918.4 | F4: -66.612669
A5: 00-1111-000 | B5: -Chase - Payroll | C5: 131962.6 | D5: 14095.12 | E5: 117867.48 | F5: 836.22899
A6: 00-1112-000 | B6: -Chase - AR Payments | C6: 360982.28 | D6: 2000 | E6: 358982.28 | F6: 17949.114
A7: 00-1190-000 | B7: Petty Cash | C7: 0 | D7: 500 | E7: -500 | F7: -100
B8: Total Cash in Banks | C8: 1026698.9 | D8: 1615267.5 | E8: -588568.6 | F8: -36.43784
B9: INVESTMENTS & SECURITIES
A10: 00-1140-000 | B10: -Morgan Stanley | C10: 815111.44 | D10: 420307.73 | E10: 394803.71 | F10: 93.93206
B11: Total Investments | C11: 815111.44 | D11: 420307.73 | E11: 394803.71 | F11: 93.93206
B12: ACCOUNTS RECEIVABLE
A13: 00-1125-000 | B13: -Allowance for Doubtful Accounts | C13: -15130.57 | D13: -15130.57 | E13: 0 | F13: 0
A14: 00-1126-000 | B14: -Customer Deposits | C14: -31574.74 | D14: -28159.91 | E14: -3414.83 | F14: -12.126566
A15: 00-1127-000 | B15: -A/R - Other | C15: 6098.5 | D15: 0 | E15: 6098.5 | F15: 0
A16: 00-1210-000 | B16: -Accounts Receivable | C16: 1141704.1 | D16: 1262808.8 | E16: -121104.69 | F16: -9.5901049
B17: Total Accounts Receivable | C17: 1101097.3 | D17: 1219518.3 | E17: -118421.02 | F17: -9.7104748
B18: INVENTORY
A19: 00-1310-000 | B19: -Raw Material | C19: 2020749.1 | D19: 1624790.3 | E19: 395958.79 | F19: 24.369839
A20: 00-1320-000 | B20: -W I P | C20: 562533.14 | D20: 323109.05 | E20: 239424.09 | F20: 74.100088
A21: 00-1330-000 | B21: -Finished Goods | C21: 64035.8 | D21: 147549.85 | E21: -83514.05 | F21: -56.600566
A22: 00-1340-000 | B22: -Inventory - Inspection | C22: 1263.73 | D22: 0 | E22: 1263.73 | F22: 0
A23: 00-1350-000 | B23: -Inventory - DMR Pending | C23: 7186.2 | D23: 6785.56 | E23: 400.64 | F23: 5.9043027
B24: Total Inventory | C24: 2655768 | D24: 2102234.8 | E24: 553533.2 | F24: 26.330703
B25: PREPAID & OTHER ASSETS
A26: 00-1510-000 | B26: -Prepaid Insurance | C26: 31961.5 | D26: 24610.26 | E26: 7351.24 | F26: 29.870631
A27: 00-1520-000 | B27: -Prepaid Workers Comp | C27: 2474.2 | D27: 0 | E27: 2474.2 | F27: 0
A28: 00-1530-000 | B28: -Prepaid RE Taxes | C28: 19159.86 | D28: 16324.17 | E28: 2835.69 | F28: 17.371113
A29: 00-1540-000 | B29: -Prepaid Other | C29: 4173.09 | D29: 40193.44 | E29: -36020.35 | F29: -89.617485
A30: 00-1550-000 | B30: -Advances | C30: -1341.64 | D30: -1651.05 | E30: 309.41 | F30: 18.740196
A31: 00-1560-000 | B31: -PPD - Trade Show Expenses | C31: 0 | D31: 14902.33 | E31: -14902.33 | F31: -100
B32: Total PPD & Other Assets | C32: 56427.01 | D32: 94379.15 | E32: -37952.14 | F32: -40.21242
B33: Total Current Assets | C33: 5655102.7 | D33: 5451707.5 | E33: 203395.15 | F33: 3.7308522
B34: PROPERTY, PLANT & EQUIPMENT
A35: 00-1410-000 | B35: -Land | C35: 122000 | D35: 122000 | E35: 0 | F35: 0
A36: 00-1420-000 | B36: -Building | C36: 1039840.7 | D36: 1039840.7 | E36: 0 | F36: 0
A37: 00-1430-000 | B37: -Leasehold Improvements | C37: 270383.64 | D37: 230619.89 | E37: 39763.75 | F37: 17.242116
A38: 00-1440-000 | B38: -Machinery & Equipment | C38: 2162584.7 | D38: 2156400.1 | E38: 6184.6 | F38: 0.28680207
A39: 00-1460-000 | B39: -Computer Equipment | C39: 61187.02 | D39: 0 | E39: 61187.02 | F39: 0
A40: 00-1470-000 | B40: -Computer Software | C40: 96925.38 | D40: 96925.38 | E40: 0 | F40: 0
A41: 00-1480-000 | B41: -Automobiles | C41: 0 | D41: 110411.14 | E41: -110411.14 | F41: -100
A42: 00-1490-000 | B42: -Accumulated Depreciation | C42: -3322429 | D42: -3262811 | E42: -59618 | F42: -1.8271975
A43: 00-1495-000 | B43: -Accumulated Amortization | C43: -96925.38 | D43: -96925.38 | E43: 0 | F43: 0
B44: Total Prprty, Plant & Equip | C44: 333567.05 | D44: 396460.82 | E44: -62893.77 | F44: -15.863805
B45: TOTAL ASSETS | C45: 5988669.7 | D45: 5848168.3 | E45: 140501.38 | F45: 2.4024852
B46: LIABILITIES
B47: ACCOUNTS PAYABLE
A48: 00-2110-000 | B48: -Accounts Payable | C48: 106538.51 | D48: 172939.26 | E48: -66400.75 | F48: -38.395417
A49: 00-2115-000 | B49: AMEX Payable | C49: -0.6 | D49: 0 | E49: -0.6 | F49: 0
A50: 00-2120-000 | B50: -Accrued Purchase Receipts | C50: 9048.5 | D50: 3244.16 | E50: 5804.34 | F50: 178.91658
B51: Total Accounts Payable | C51: 115586.41 | D51: 176183.42 | E51: -60597.01 | F51: -34.394275
B52: ACCRUED ACCTS PAYABLE
B53: ACCRUED WAGES & TAXES
B54: ACCRUED & OTHER LIABILITIES
A55: 00-2230-000 | B55: -401K Payable | C55: 0.01 | D55: 0 | E55: 0.01 | F55: 0
A56: 00-2295-000 | B56: -Lease Payable - Screen Printer | C56: 66272.92 | D56: 80822.44 | E56: -14549.52 | F56: -18.001832
A57: 00-2296-000 | B57: -Lease Payable - Pick and Place | C57: 37510.28 | D57: 85183.16 | E57: -47672.88 | F57: -55.965146
A58: 00-2297-000 | B58: -Lease Payable - Phone System | C58: 12724.56 | D58: 12417.99 | E58: 306.57 | F58: 2.468757
A59: 00-2310-000 | B59: -Accrued Payroll & Taxes | C59: 114875.16 | D59: 75036.46 | E59: 39838.7 | F59: 53.092457
A60: 00-2340-000 | B60: -Accrued Expenses | C60: 40809.63 | D60: 38628.5 | E60: 2181.13 | F60: 5.6464269
A61: 00-2350-000 | B61: -Accrued Profit Sharing | C61: 50000 | D61: 175000 | E61: -125000 | F61: -71.428571
B62: Total Accrued Liabilities | C62: 322192.56 | D62: 467088.55 | E62: -144895.99 | F62: -31.021097
B63: Total Current Liabilities | C63: 437778.97 | D63: 643271.97 | E63: -205493 | F63: -31.944964
B64: TOTAL LIABILITIES | C64: 437778.97 | D64: 643271.97 | E64: -205493 | F64: -31.944964
B65: EQUITY
A66: 00-3300-000 | B66: Common Stock | C66: 165000 | D66: 165000 | E66: 0 | F66: 0
A67: 00-3320-000 | B67: Tax Payments-Current Year | C67: 0 | D67: -170000 | E67: 170000 | F67: 100
A68: 00-3330-000 | B68: Distributions-Current Year | C68: 0 | D68: -735247.85 | E68: 735247.85 | F68: 100
A69: 00-3340-000 | B69: Retained Earnings-Prior Years | C69: 23534721 | D69: 22533870 | E69: 1000850.6 | F69: 4.441539
A70: 00-3310-000 | B70: -Retained Earnings - Distributions | C70: -18370065 | D70: -17589577 | E70: 780487.94 | F70: 4.4372184
A71: 00-3350-000 | B71: Current Year - Profit ( Loss ) | C71: 221234.47 | D71: 1000850.6 | E71: -779616.17 | F71: -77.895356
B72: TOTAL EQUITY | C72: 5550890.8 | D72: 5204896.4 | E72: 345994.38 | F72: 6.6474787
B73: TOTAL LIABILITIES & EQUITY | C73: 5988669.7 | D73: 5848168.3 | E73: 140501.38 | F73: 2.4024852

Sheet Sep 2025 BS
A1: Account | B1: Description | C1: Current Year | D1: Last Year | E1: Variance | F1: Var %
B2: ASSETS
B3: CASH IN BANKS
A4: 00-1110-000 | B4: -Chase - Checking | C4: 382938.75 | D4: 1036066.4 | E4: -653127.67 | F4: -63.03917
A5: 00-1111-000 | B5: -Chase - Payroll | C5: 116237.34 | D5: 71935.39 | E5: 44301.95 | F5: 61.585751
A6: 00-1112-000 | B6: -Chase - AR Payments | C6: 81142.26 | D6: 13609.7 | E6: 67532.56 | F6: 496.20903
A7: 00-1190-000 | B7: Petty Cash | C7: 0 | D7: 500 | E7: -500 | F7: -100
B8: Total Cash in Banks | C8: 580318.35 | D8: 1122111.5 | E8: -541793.16 | F8: -48.283362
B9: INVESTMENTS & SECURITIES
A10: 00-1140-000 | B10: -Morgan Stanley | C10: 1723864.4 | D10: 432268.06 | E10: 1291596.3 | F10: 298.79522
B11: Total Investments | C11: 1723864.4 | D11: 432268.06 | E11: 1291596.3 | F11: 298.79522
B12: ACCOUNTS RECEIVABLE
A13: 00-1125-000 | B13: -Allowance for Doubtful Accounts | C13: -15130.57 | D13: -15130.57 | E13: 0 | F13: 0
A14: 00-1126-000 | B14: -Customer Deposits | C14: -19542.76 | D14: -5791.64 | E14: -13751.12 | F14: -237.4305
A15: 00-1210-000 | B15: -Accounts Receivable | C15: 437988.79 | D15: 341789.78 | E15: 96199.01 | F15: 28.145666
B16: Total Accounts Receivable | C16: 403315.46 | D16: 320867.57 | E16: 82447.89 | F16: 25.695302
B17: INVENTORY
A18: 00-1310-000 | B18: -Raw Material | C18: 2080333.4 | D18: 1813398.5 | E18: 266934.91 | F18: 14.720146
A19: 00-1320-000 | B19: -W I P | C19: 741600.29 | D19: 363163.99 | E19: 378436.3 | F19: 104.20535
A20: 00-1330-000 | B20: -Finished Goods | C20: 96448.06 | D20: 232978.38 | E20: -136530.32 | F20: -58.602142
A21: 00-1340-000 | B21: -Inventory - Inspection | C21: 0 | D21: 874 | E21: -874 | F21: -100
A22: 00-1350-000 | B22: -Inventory - DMR Pending | C22: 3902.04 | D22: 6849.13 | E22: -2947.09 | F22: -43.028677
B23: Total Inventory | C23: 2922283.8 | D23: 2417264 | E23: 505019.8 | F23: 20.892207
B24: PREPAID & OTHER ASSETS
A25: 00-1510-000 | B25: -Prepaid Insurance | C25: 25825.99 | D25: 21086.56 | E25: 4739.43 | F25: 22.47607
A26: 00-1520-000 | B26: -Prepaid Workers Comp | C26: -731.02 | D26: 3779.03 | E26: -4510.05 | F26: -119.34412
A27: 00-1530-000 | B27: -Prepaid RE Taxes | C27: 9578.21 | D27: 6529.69 | E27: 3048.52 | F27: 46.687056
A28: 00-1550-000 | B28: -Advances | C28: 0 | D28: -2331.89 | E28: 2331.89 | F28: 100
A29: 00-1560-000 | B29: -PPD - Trade Show Expenses | C29: 2031.6 | D29: 2120.15 | E29: -88.55 | F29: -4.1765913
B30: Total PPD & Other Assets | C30: 36704.78 | D30: 31183.54 | E30: 5521.24 | F30: 17.705623
B31: Total Current Assets | C31: 5666486.8 | D31: 4323694.7 | E31: 1342792.1 | F31: 31.056588
B32: PROPERTY, PLANT & EQUIPMENT
A33: 00-1410-000 | B33: -Land | C33: 122000 | D33: 122000 | E33: 0 | F33: 0
A34: 00-1420-000 | B34: -Building | C34: 1039840.7 | D34: 1039840.7 | E34: 0 | F34: 0
A35: 00-1430-000 | B35: -Leasehold Improvements | C35: 270383.64 | D35: 270383.64 | E35: 0 | F35: 0
A36: 00-1440-000 | B36: -Machinery & Equipment | C36: 2162584.7 | D36: 2156400.1 | E36: 6184.6 | F36: 0.28680207
A37: 00-1460-000 | B37: -Computer Equipment | C37: 61187.02 | D37: 61187.02 | E37: 0 | F37: 0
A38: 00-1470-000 | B38: -Computer Software | C38: 96925.38 | D38: 96925.38 | E38: 0 | F38: 0
A39: 00-1480-000 | B39: -Automobiles | C39: 0 | D39: 110411.14 | E39: -110411.14 | F39: -100
A40: 00-1490-000 | B40: -Accumulated Depreciation | C40: -3344929 | D40: -3384311 | E40: 39382 | F40: 1.1636637
A41: 00-1495-000 | B41: -Accumulated Amortization | C41: -96925.38 | D41: -96925.38 | E41: 0 | F41: 0
B42: Total Prprty, Plant & Equip | C42: 311067.05 | D42: 375911.59 | E42: -64844.54 | F42: -17.249944
B43: TOTAL ASSETS | C43: 5977553.8 | D43: 4699606.3 | E43: 1277947.5 | F43: 27.192651
B44: LIABILITIES
B45: ACCOUNTS PAYABLE
A46: 00-2110-000 | B46: -Accounts Payable | C46: 39600.14 | D46: 94757.55 | E46: -55157.41 | F46: -58.208987
A47: 00-2115-000 | B47: AMEX Payable | C47: 17482.41 | D47: 0 | E47: 17482.41 | F47: 0
A48: 00-2120-000 | B48: -Accrued Purchase Receipts | C48: 20935.07 | D48: 34728.92 | E48: -13793.85 | F48: -39.718626
B49: Total Accounts Payable | C49: 78017.62 | D49: 129486.47 | E49: -51468.85 | F49: -39.748439
B50: ACCRUED ACCTS PAYABLE
B51: ACCRUED WAGES & TAXES
B52: ACCRUED & OTHER LIABILITIES
A53: 00-2295-000 | B53: -Lease Payable - Screen Printer | C53: 56805.28 | D53: 68864.05 | E53: -12058.77 | F53: -17.51098
A54: 00-2296-000 | B54: -Lease Payable - Pick and Place | C54: 0 | D54: 45069.79 | E54: -45069.79 | F54: -100
A55: 00-2297-000 | B55: -Lease Payable - Phone System | C55: 9543.39 | D55: 9613.21 | E55: -69.82 | F55: -0.72629226
A56: 00-2310-000 | B56: -Accrued Payroll & Taxes | C56: 112033.32 | D56: 139079.51 | E56: -27046.19 | F56: -19.446567
A57: 00-2340-000 | B57: -Accrued Expenses | C57: 5156.98 | D57: 10815.25 | E57: -5658.27 | F57: -52.317515
A58: 00-2350-000 | B58: -Accrued Profit Sharing | C58: 6101.91 | D58: 0 | E58: 6101.91 | F58: 0
B59: Total Accrued Liabilities | C59: 189640.88 | D59: 273441.81 | E59: -83800.93 | F59: -30.646714
B60: Total Current Liabilities | C60: 267658.5 | D60: 402928.28 | E60: -135269.78 | F60: -33.571677
B61: TOTAL LIABILITIES | C61: 267658.5 | D61: 402928.28 | E61: -135269.78 | F61: -33.571677
B62: EQUITY
A63: 00-3300-000 | B63: Common Stock | C63: 165000 | D63: 165000 | E63: 0 | F63: 0
A64: 00-3320-000 | B64: Tax Payments-Current Year | C64: 37017.44 | D64: 0 | E64: 37017.44 | F64: 0
A65: 00-3330-000 | B65: Distributions-Current Year | C65: 0 | D65: -102030.64 | E65: 102030.64 | F65: 100
A66: 00-3340-000 | B66: Retained Earnings-Prior Years | C66: 23755955 | D66: 23534721 | E66: 221234.47 | F66: 0.94003439
A67: 00-3310-000 | B67: -Retained Earnings - Distributions | C67: -18370065 | D67: -18494825 | E67: -124759.91 | F67: -0.67456661
A68: 00-3350-000 | B68: Current Year - Profit ( Loss ) | C68: 121987.15 | D68: -806187.7 | E68: 928174.85 | F68: 115.13136
B69: TOTAL EQUITY | C69: 5709895.3 | D69: 4296678 | E69: 1413217.3 | F69: 32.890929
B70: TOTAL LIABILITIES & EQUITY | C70: 5977553.8 | D70: 4699606.3 | E70: 1277947.5 | F70: 27.192651
